Workbook

Sheet Prévisionnels (2)
A1: États des résultats prévisionnels | F1: Grille tarfaires
B2: Garderie non-Subventionnée | D2: Garderie Subventionnée | H2: Tarif | K2: Tarif | L2: Nbr jour
A3: Places non-subventionnées | B3: =(G3*H3*L3)+(J3*K3*L3) -> 1083411 | C3: =B3/$B$6 -> 1 | D3: 0 | E3: =D3/$D$6 -> 0 | F3: places rég non sub | G3: 70 | H3: 52.25 | I3: places poupons | J3: 10 | K3: 49.35 | L3: 261
A4: Places subventionnées | C4: =B4/$B$6 -> 0 | D4: =(G4*H4*L4)+(J4*K4*L4)+(G5*H5*L4) -> 1100323.8 | E4: =D4/$D$6 -> 0.76769141 | F4: places rég subventionnée | G4: 40 | H4: 48.77 | I4: places poupons | J4: 20 | K4: 72.33 | L4: 261
A5: autres subventions fonctionnement ( voir section de droite) | D5: =+L15 -> 332965.4 | F5: enfants 4 ans | G5: 20 | H5: 40.92
A6: Total - Chiffre d'affaires | B6: =SUM(B3:B4) -> 1083411 | C6: =B6/$B$6 -> 1 | D6: =SUM(D3:D5) -> 1433289.2 | E6: =D6/$D$6 -> 1
A7: Total - Coûts directs | B7: 0 | C7: =B7/$B$6 -> 0 | D7: 0 | E7: =D7/$D$6 -> 0 | G7: Autres subventions de fonctionnement | J7: taux annuel | K7: nbr place | M7: taux 1-60 | O7: taux 60& plus
A8: Bénéfice brut | B8: =B6-B7 -> 1083411 | C8: =B8/$B$6 -> 1 | D8: =D6-D7 -> 1433289.2 | E8: =D8/$D$6 -> 1 | H8: service administratifs | J8: voir à droite | K8: 80 | L8: =+(M8*N8)+(O8*P8) -> 172203 | M8: 2217.1 | N8: 60 | O8: 1958.85 | P8: 20
A9: Marge bénéficiaire brute | B9: =B8/$B$6 -> 1 | D9: =D8/$D$6 -> 1 | H9: Service auxiliaire | J9: 2111.49 | K9: 80 | L9: =+J9*K9 -> 168919.2 | M9: 8.09 | N9: 80 | O9: =+L4 -> 261 | Q9: 8,09 par jour d'occupation par place
A10: Salaires et avantages sociaux éducatrices & aide educ | B10: ='annexes salaires (2)'!E17 -> 633753.08 | C10: =B10/$B$6 -> 0.5849609 | D10: ='annexes salaires (2)'!E17 -> 633753.08 | E10: =D10/$D$6 -> 0.44216693 | H10: Cout occupation locaux ref 3.1.4 | J10: 773.04 | K10: 80 | L10: =+J10*K10 -> 61843.2
A11: Salaires et avantages employés aide-cuisine | B11: =D11 -> 26845 | C11: =B11/$B$6 -> 0.024778224 | D11: ='annexes salaires (2)'!E32 -> 26845 | E11: =D11/$D$6 -> 0.018729646 | H11: Optimisaiton des services 3.1.5
A12: Salaires et avantages employés gestion et proprio. | B12: ='annexes salaires (2)'!N17 -> 44179.2 | C12: =B12/$B$6 -> 0.040777877 | D12: ='annexes salaires (2)'!N17 -> 44179.2 | E12: =D12/$D$6 -> 0.030823647 | H12: Subvention assurance collective
A13: Assurances | B13: 8000 | C13: =B13/$B$6 -> 0.007384086 | D13: 8000 | E13: =D13/$D$6 -> 0.0055815672 | H13: Subvention fonds pension
A14: Cotisations | B14: 600 | C14: =B14/$B$6 -> 0.00055380645 | D14: 600 | E14: =D14/$D$6 -> 0.00041861754 | H14: Moins réserve pour ajustemet absences | L14: -70000
A15: Énergie | B15: 11500 | C15: =B15/$B$6 -> 0.010614624 | D15: 11500 | E15: =D15/$D$6 -> 0.0080235029 | J15: Total autres subventions | L15: =SUM(L8:L14) -> 332965.4
A16: Entretien général | B16: 20000 | C16: =B16/$B$6 -> 0.018460215 | D16: 20000 | E16: =D16/$D$6 -> 0.013953918
A17: Formation et perfectionnement | B17: 5000 | C17: =B17/$B$6 -> 0.0046150538 | D17: 5000 | E17: =D17/$D$6 -> 0.0034884795
A18: Fournitures de garderie | B18: 6000 | C18: =B18/$B$6 -> 0.0055380645 | D18: 6000 | E18: =D18/$D$6 -> 0.0041861754
A19: Frais de bureau | B19: 6000 | C19: =B19/$B$6 -> 0.0055380645 | D19: 6000 | E19: =D19/$D$6 -> 0.0041861754
A20: Frais de déplacement | B20: 100 | C20: =B20/$B$6 -> 9.2301075e-05 | D20: 100 | E20: =D20/$D$6 -> 6.976959e-05
A21: Honoraires professionnels | B21: 4000 | C21: =B21/$B$6 -> 0.003692043 | D21: 4000 | E21: =D21/$D$6 -> 0.0027907836 | F21: Nourriture
A22: Nourriture | B22: =K23*K22 -> 104400 | C22: =B22/$B$6 -> 0.096362322 | D22: =+K23*K22 -> 104400 | E22: =D22/$D$6 -> 0.072839452 | F22: taux quotidien par enfants | G22: nbr enfant | H22: 80 | I22: 261 | J22: totalprés/jour | K22: =+H22*I22 -> 20880
A23: Publicité et promotion | B23: 5000 | C23: =B23/$B$6 -> 0.0046150538 | D23: 0 | E23: =D23/$D$6 -> 0 | I23: Coût enfant/jour | K23: 5
A24: Taxes licences et permis | B24: 16000 | C24: =B24/$B$6 -> 0.014768172 | D24: 20000 | E24: =D24/$D$6 -> 0.013953918
A25: Télécommunications | B25: 1200 | C25: =B25/$B$6 -> 0.0011076129 | D25: 1200 | E25: =D25/$D$6 -> 0.00083723508
A26: Loyer | B26: 180000 | C26: =B26/$B$6 -> 0.16614194 | D26: 180000 | E26: =D26/$D$6 -> 0.12558526
A27: Divers | B27: 6000 | C27: =B27/$B$6 -> 0.0055380645 | D27: 6000 | E27: =D27/$D$6 -> 0.0041861754
A28: Intérets et frais bancaires | B28: 4500 | C28: =B28/$B$6 -> 0.0041535484 | D28: 4500 | E28: =D28/$D$6 -> 0.0031396316
A29: Amortissement | B29: 5000 | C29: =B29/$B$6 -> 0.0046150538 | D29: 5000 | E29: =D29/$D$6 -> 0.0034884795
A30: Total - Frais d'exploitation | B30: =SUM(B10:B29) -> 1088077.3 | C30: =B30/$B$6 -> 1.004307 | D30: =SUM(D10:D29) -> 1087077.3 | E30: =D30/$D$6 -> 0.75844936
A31: Bénéfice avant impôts | B31: =B8-B30 -> -4666.2784 | C31: =B31/$B$6 -> -0.0043070251 | D31: =D8-D30 -> 346211.92 | E31: =D31/$D$6 -> 0.24155064
A32: Impôt | B32: =IF(B31<0,0,B31*19%) -> 0 | C32: =B32/$B$6 -> 0 | D32: =IF(D31<0,0,D31*19%) -> 65780.265 | E32: =D32/$D$6 -> 0.045894621
A33: Bénéfice net | B33: =B31-B32 -> -4666.2784 | C33: =B33/$B$6 -> -0.0043070251 | D33: =D31-D32 -> 280431.66 | E33: =D33/$D$6 -> 0.19565602
A34: Marge bénéficiaire nette | B34: =B33/B6 -> -0.0043070251 | D34: =D33/D6 -> 0.19565602
B36: =B2 -> Garderie non-Subventionnée | D36: =D2 -> Garderie Subventionnée
A37: BAIA (fonds générés) | B37: =B33+B29+B32 -> 333.7216 | D37: =D33+D29+D32 -> 351211.92

Sheet annexes salaires (2)
A2: PROJET | B2: GARDERIE LES TRÉSORS DE L'ILE
A4: SOMMAIRE DES SALAIRES
A5: TYPE D'EMPLOYÉS | C5: ÉDUCATRICES GARDERIE | J5: TYPE D'EMPLOYÉS | L5: administration et propiétaire
B6: TAUX | C6: heures / | D6: Nombre | E6: Total frais | K6: TAUX | L6: heures / | M6: Nombre | N6: Total frais
A7: Nbre Employés | B7: Horaire | C7: semaine | D7: semaine/ an | E7: annuels | J7: Nbre Employés | K7: Horaire | L7: semaine | M7: semaine/ an | N7: annuels
A8: 10 | B8: 22.04 | C8: 36 | D8: 52 | E8: =+((B8*C8)*D8)*A8 -> 412588.8 | J8: 1 | K8: 18 | L8: 40 | M8: 52 | N8: =+((K8*L8)*M8)*J8 -> 37440
A9: 3 | B9: 20.2 | C9: 25 | D9: 52 | E9: =+((B9*C9)*D9)*A9 -> 78780
A10: 1 | B10: 27.47 | C10: 32 | D10: 52 | E10: =+((B10*C10)*D10)*A10 -> 45710.08 | N10: =+((K10*L10)*M10)*J10 -> 0
E11: =+((B11*C11)*D11)*A11 -> 0 | N11: =+((K11*L11)*M11)*J11 -> 0
E12: =+((B12*C12)*D12)*A12 -> 0 | N12: =+((K12*L12)*M12)*J12 -> 0
E13: =+((B13*C13)*D13)*A13 -> 0 | N13: =+((K13*L13)*M13)*J13 -> 0
E14: =+((B14*C14)*D14)*A14 -> 0 | N14: =+((K14*L14)*M14)*J14 -> 0
D15: Total | E15: =SUM(E8:E14) -> 537078.88 | M15: Total | N15: =SUM(N8:N14) -> 37440
D16: avantages | E16: =+E15*F16 -> 96674.198 | F16: 0.18 | M16: avantages | N16: =+N15*O16 -> 6739.2 | O16: 0.18
D17: Total | E17: =+E15+E16 -> 633753.08 | M17: Total | N17: =+N15+N16 -> 44179.2
A19: Type d'employés | B19: Employés de soutien et cuisine
B20: TAUX | C20: heures / | D20: Nombre | E20: Total frais
A21: Nbre Employés | B21: Horaire | C21: semaine | D21: semaine/ an | E21: annuels
A22: 1 | B22: 17.5 | C22: 25 | D22: 52 | E22: =+((B22*C22)*D22)*A22 -> 22750
E23: =+((B23*C23)*D23)*A23 -> 0
E24: =+((B24*C24)*D24)*A24 -> 0
E25: =+((B25*C25)*D25)*A25 -> 0
E26: =+((B26*C26)*D26)*A26 -> 0
E27: =+((B27*C27)*D27)*A27 -> 0
E28: =+((B28*C28)*D28)*A28 -> 0
D30: Total | E30: =SUM(E22:E29) -> 22750
D31: avantages | E31: =+E30*F31 -> 4095 | F31: =+F16 -> 0.18
D32: Total | E32: =+E30+E31 -> 26845

Sheet Feuil1
