Workbook
Name Honoraire: #REF!

Sheet Medzy P&L Summary
C1: Medzy Inc - Summary Profit and Loss Statement
D3: Fiscal Year Ending On
D4: Oct 31 2021 | E4: Oct 31 2022 | F4: Oct 31 2023 | G4: Oct 31 2024 | H4: Oct 31 2025 | I4: Oct 31 2026 | J4: Oct 31 2027 | K4: Oct 31 2028
B5: REVENUES & KPIS | D5: ACTUALS | G5: FORECASTS
C6: New Clients | E6: =SUM('P&L Medzy '!F10:Q10) -> 0 | F6: =SUM('P&L Medzy '!P10:AA10) -> 461.42857 | G6: =SUM('P&L Medzy '!AD10:AO10) -> 12909.77 | H6: =SUM('P&L Medzy '!AP10:BA10) -> 32575.341 | I6: =SUM('P&L Medzy '!BB10:BM10) -> 54208.941 | J6: =SUM('P&L Medzy '!BN10:BY10) -> 73562.541 | K6: =SUM('P&L Medzy '!BZ10:CK10) -> 92916.141
C7: Churn | E7: =SUM('P&L Medzy '!F11:Q11) -> 0 | F7: =SUM('P&L Medzy '!P11:AA11) -> 231.8558 | G7: =SUM('P&L Medzy '!AD11:AO11) -> 1557.4311 | H7: =SUM('P&L Medzy '!AP11:BA11) -> 5199.0281 | I7: =SUM('P&L Medzy '!BB11:BM11) -> 12824.986 | J7: =SUM('P&L Medzy '!BN11:BY11) -> 22808.062 | K7: =SUM('P&L Medzy '!BZ11:CK11) -> 34422.459
C8: Total Clients | E8: ='P&L Medzy '!Q12 -> 0 | F8: ='P&L Medzy '!AA12 -> 4645.6078 | G8: ='P&L Medzy '!AO12 -> 15819.69 | H8: ='P&L Medzy '!BA12 -> 42560.003 | I8: =SUM('P&L Medzy '!BB12:BM12) -> 740659.65 | J8: =SUM('P&L Medzy '!BN12:BY12) -> 1240124.2 | K8: =SUM('P&L Medzy '!BZ12:CK12) -> 1832417.5
C9: ='P&L Medzy '!B13 -> Pharmacy Revenues | D9: 2869230.8 | E9: 4030102.3 | F9: =SUM('P&L Medzy '!P13:AA13) -> 4942683.8 | G9: =SUM('P&L Medzy '!AD13:AO13) -> 8978508.2 | H9: =SUM('P&L Medzy '!AP13:BA13) -> 27076732 | I9: =SUM('P&L Medzy '!BB13:BM13) -> 56566517 | J9: =SUM('P&L Medzy '!BN13:BY13) -> 94205353 | K9: =SUM('P&L Medzy '!BZ13:CK13) -> 1.3774834e+08
C11: Medzy Platform Revenues | D11: 502115.3 | E11: 706554.49 | F11: =SUM('P&L Medzy '!P16:AA16) -> 843819.37 | G11: =SUM('P&L Medzy '!AD16:AO16) -> 1445221.5 | H11: =SUM('P&L Medzy '!AP16:BA16) -> 4353571.7 | I11: =SUM('P&L Medzy '!BB16:BM16) -> 11598674 | J11: =SUM('P&L Medzy '!BN16:BY16) -> 20629791 | K11: =SUM('P&L Medzy '!BZ16:CK16) -> 30917512
C12: Other Revenues | D12: 86807.64 | E12: 3590.43
C14: NET REVENUES | D14: =SUM(D11:D12) -> 588922.94 | E14: =SUM(E11:E12) -> 710144.92 | F14: =SUM(F11:F12) -> 843819.37 | G14: =SUM(G11:G12) -> 1445221.5 | H14: =SUM(H11:H12) -> 4353571.7 | I14: =SUM(I11:I12) -> 11598674 | J14: =SUM(J11:J12) -> 20629791 | K14: =SUM(K11:K12) -> 30917512
D16: Oct 31 2021 | E16: Oct 31 2022 | F16: Oct 31 2023 | G16: Oct 31 2024 | H16: Oct 31 2025 | I16: Oct 31 2026 | J16: Oct 31 2027 | K16: Oct 31 2028
B17: EXPENSES | C17: ='P&L Medzy '!B31 -> COS | D17: ACTUALS | G17: FORECASTS
C19: ='P&L Medzy '!B33 -> Salaries
C20: ='P&L Medzy '!B34 -> IT | D20: 417888.58 | E20: 717436.34 | F20: =SUM('P&L Medzy '!P34:AA34) -> 1126399.9 | G20: =SUM('P&L Medzy '!AB34:AM34) -> 1017794.4 | H20: =SUM('P&L Medzy '!AN34:BA34) -> 1593879.2 | I20: =SUM('P&L Medzy '!BB34:BM34) -> 1492200 | J20: =SUM('P&L Medzy '!BN34:BY34) -> 1492200 | K20: =SUM('P&L Medzy '!BZ34:CK34) -> 1492200
C21: ='P&L Medzy '!B35 -> Sales / Marketing | D21: 93569.48 | E21: 81287.16 | F21: =SUM('P&L Medzy '!P35:AA35) -> 105541.57 | G21: =SUM('P&L Medzy '!AB35:AM35) -> 318550 | H21: =SUM('P&L Medzy '!AN35:BA35) -> 1105866.7 | I21: =SUM('P&L Medzy '!BB35:BM35) -> 1025085 | J21: =SUM('P&L Medzy '!BN35:BY35) -> 1055624.2 | K21: =SUM('P&L Medzy '!BZ35:CK35) -> 1087690.5
C22: ='P&L Medzy '!B36 -> Operations | D22: 104396.35 | E22: 39939.72 | F22: =SUM('P&L Medzy '!P36:AA36) -> 110207 | G22: =SUM('P&L Medzy '!AB36:AM36) -> 325416.67 | H22: =SUM('P&L Medzy '!AN36:BA36) -> 1057916.7 | I22: =SUM('P&L Medzy '!BB36:BM36) -> 912500 | J22: =SUM('P&L Medzy '!BN36:BY36) -> 912500 | K22: =SUM('P&L Medzy '!BZ36:CK36) -> 912500
C23: ='P&L Medzy '!B37 -> Sub total | D23: =SUM(D20:D22) -> 615854.41 | E23: =SUM(E20:E22) -> 838663.22 | F23: =SUM('P&L Medzy '!P37:AA37) -> 1342148.5 | G23: =SUM('P&L Medzy '!AB37:AM37) -> 1661761.1 | H23: =SUM('P&L Medzy '!AN37:BA37) -> 3757662.5 | I23: =SUM('P&L Medzy '!BB37:BM37) -> 3429785 | J23: =SUM('P&L Medzy '!BN37:BY37) -> 3460324.2 | K23: =SUM('P&L Medzy '!BZ37:CK37) -> 3492390.5
C25: ='P&L Medzy '!B39 -> Fringes + Bonus | D25: 0 | E25: 0 | F25: =SUM('P&L Medzy '!P39:AA39) -> 0 | G25: =SUM('P&L Medzy '!AB39:AM39) -> 160241.9 | H25: =SUM('P&L Medzy '!AN39:BA39) -> 450919.5 | I25: =SUM('P&L Medzy '!BB39:BM39) -> 411574.2 | J25: =SUM('P&L Medzy '!BN39:BY39) -> 415238.91 | K25: =SUM('P&L Medzy '!BZ39:CK39) -> 419086.86
C27: ='P&L Medzy '!B41 -> Contractuals - Tech | D27: 0 | E27: 0 | F27: =SUM('P&L Medzy '!P41:AA41) -> 8448 | G27: =SUM('P&L Medzy '!AB41:AM41) -> 0 | H27: =SUM('P&L Medzy '!AN41:BA41) -> 0 | I27: =SUM('P&L Medzy '!BB41:BM41) -> 0 | J27: =SUM('P&L Medzy '!BN41:BY41) -> 0 | K27: =SUM('P&L Medzy '!BZ41:CK41) -> 0
C28: ='P&L Medzy '!B42 -> Contractuals - Operations | D28: =140930.08+254789.8 -> 395719.88 | E28: =281521.71+520357.4 -> 801879.11 | F28: =SUM('P&L Medzy '!P42:AA42) -> 342552.55 | G28: =SUM('P&L Medzy '!AB42:AM42) -> 70000 | H28: =SUM('P&L Medzy '!AN42:BA42) -> 5000 | I28: =SUM('P&L Medzy '!BB42:BM42) -> 0 | J28: =SUM('P&L Medzy '!BN42:BY42) -> 0 | K28: =SUM('P&L Medzy '!BZ42:CK42) -> 0
C30: ='P&L Medzy '!B44 -> Professionals
C31: ='P&L Medzy '!B45 -> Accounting Fees | F31: =SUM('P&L Medzy '!P45:AA45) -> 34550.5 | G31: =SUM('P&L Medzy '!AB45:AM45) -> 40000 | H31: =SUM('P&L Medzy '!AN45:BA45) -> 42000 | I31: =SUM('P&L Medzy '!BB45:BM45) -> 39500 | J31: =SUM('P&L Medzy '!BN45:BY45) -> 39500 | K31: =SUM('P&L Medzy '!BZ45:CK45) -> 39500
C32: ='P&L Medzy '!B46 -> Legal Fees | D32: 43059.58 | E32: 113846.78 | F32: =SUM('P&L Medzy '!P46:AA46) -> 28264.65 | G32: =SUM('P&L Medzy '!AB46:AM46) -> 60000 | H32: =SUM('P&L Medzy '!AN46:BA46) -> 68000 | I32: =SUM('P&L Medzy '!BB46:BM46) -> 60000 | J32: =SUM('P&L Medzy '!BN46:BY46) -> 60000 | K32: =SUM('P&L Medzy '!BZ46:CK46) -> 60000
C33: ='P&L Medzy '!B47 -> Other | F33: =SUM('P&L Medzy '!P47:AA47) -> 37076.4 | G33: =SUM('P&L Medzy '!AB47:AM47) -> 80000 | H33: =SUM('P&L Medzy '!AN47:BA47) -> 170000 | I33: =SUM('P&L Medzy '!BB47:BM47) -> 150000 | J33: =SUM('P&L Medzy '!BN47:BY47) -> 150000 | K33: =SUM('P&L Medzy '!BZ47:CK47) -> 150000
C37: ='P&L Medzy '!B51 -> SubTotal Salaries
C38: ='P&L Medzy '!B52 -> 0 | F38: =SUM('P&L Medzy '!P52:AA52) -> 0 | G38: =SUM('P&L Medzy '!AB52:AM52) -> 0 | H38: =SUM('P&L Medzy '!AN52:BA52) -> 0
C39: ='P&L Medzy '!B53 -> Rent | D39: 28253.4 | E39: 35644.64 | F39: =SUM('P&L Medzy '!P53:AA53) -> 54996.27 | G39: =SUM('P&L Medzy '!AB53:AM53) -> 63029.36 | H39: =SUM('P&L Medzy '!AN53:BA53) -> 84000 | I39: =SUM('P&L Medzy '!BB53:BM53) -> 72000 | J39: =SUM('P&L Medzy '!BN53:BY53) -> 72000 | K39: =SUM('P&L Medzy '!BZ53:CK53) -> 72000
C40: ='P&L Medzy '!B54 -> Utilities | F40: =SUM('P&L Medzy '!P54:AA54) -> 2075.75 | G40: =SUM('P&L Medzy '!AB54:AM54) -> 5400 | H40: =SUM('P&L Medzy '!AN54:BA54) -> 9600 | I40: =SUM('P&L Medzy '!BB54:BM54) -> 8400 | J40: =SUM('P&L Medzy '!BN54:BY54) -> 8400 | K40: =SUM('P&L Medzy '!BZ54:CK54) -> 8400
C41: ='P&L Medzy '!B55 -> Insurance | D41: 9863.01 | E41: =-230961.75+16209.9 -> -214751.85 | F41: =SUM('P&L Medzy '!P55:AA55) -> 13884.76 | G41: =SUM('P&L Medzy '!AB55:AM55) -> 14407.44 | H41: =SUM('P&L Medzy '!AN55:BA55) -> 30400 | I41: =SUM('P&L Medzy '!BB55:BM55) -> 26400 | J41: =SUM('P&L Medzy '!BN55:BY55) -> 26400 | K41: =SUM('P&L Medzy '!BZ55:CK55) -> 26400
C42: ='P&L Medzy '!B56 -> Meals and Entertainment | D42: 619.4 | E42: 34.89 | F42: =SUM('P&L Medzy '!P56:AA56) -> 293.76 | G42: =SUM('P&L Medzy '!AB56:AM56) -> 10837.52 | H42: =SUM('P&L Medzy '!AN56:BA56) -> 40250 | I42: =SUM('P&L Medzy '!BB56:BM56) -> 29500 | J42: =SUM('P&L Medzy '!BN56:BY56) -> 29500 | K42: =SUM('P&L Medzy '!BZ56:CK56) -> 29500
C43: ='P&L Medzy '!B57 -> Travel Expenses | D43: 373.71 | E43: 12153.03 | F43: =SUM('P&L Medzy '!P57:AA57) -> 2308.58 | G43: =SUM('P&L Medzy '!AB57:AM57) -> 24001.72 | H43: =SUM('P&L Medzy '!AN57:BA57) -> 54000 | I43: =SUM('P&L Medzy '!BB57:BM57) -> 48000 | J43: =SUM('P&L Medzy '!BN57:BY57) -> 48000 | K43: =SUM('P&L Medzy '!BZ57:CK57) -> 48000
C44: ='P&L Medzy '!B58 -> Depreciation - (delivery box) | D44: =23881.13+12920.71 -> 36801.84 | E44: 29169.96 | F44: =SUM('P&L Medzy '!P58:AA58) -> 1290.48 | G44: =SUM('P&L Medzy '!AB58:AM58) -> 5161.92 | H44: =SUM('P&L Medzy '!AN58:BA58) -> 6022.24 | I44: =SUM('P&L Medzy '!BB58:BM58) -> 5161.92 | J44: =SUM('P&L Medzy '!BN58:BY58) -> 5161.92 | K44: =SUM('P&L Medzy '!BZ58:CK58) -> 5161.92
C45: ='P&L Medzy '!B59 -> Telecommunication | D45: 1091.13 | E45: 1096.07 | F45: =SUM('P&L Medzy '!P59:AA59) -> 1925.77 | G45: =SUM('P&L Medzy '!AB59:AM59) -> 3439.68 | H45: =SUM('P&L Medzy '!AN59:BA59) -> 5500 | I45: =SUM('P&L Medzy '!BB59:BM59) -> 4800 | J45: =SUM('P&L Medzy '!BN59:BY59) -> 4800 | K45: =SUM('P&L Medzy '!BZ59:CK59) -> 4800
C46: ='P&L Medzy '!B60 -> License and Subscriptions | D46: 64710.01 | E46: =72183.09-89.97 -> 72093.12 | F46: =SUM('P&L Medzy '!P60:AA60) -> 72750.86 | G46: =SUM('P&L Medzy '!AB60:AM60) -> 92311.6 | H46: =SUM('P&L Medzy '!AN60:BA60) -> 170000 | I46: =SUM('P&L Medzy '!BB60:BM60) -> 150000 | J46: =SUM('P&L Medzy '!BN60:BY60) -> 150000 | K46: =SUM('P&L Medzy '!BZ60:CK60) -> 150000
C47: ='P&L Medzy '!B61 -> Repair and Maintenance | D47: 19290.5 | E47: 10770 | F47: =SUM('P&L Medzy '!P61:AA61) -> 2980.01 | G47: =SUM('P&L Medzy '!AB61:AM61) -> 12000 | H47: =SUM('P&L Medzy '!AN61:BA61) -> 27000 | I47: =SUM('P&L Medzy '!BB61:BM61) -> 24000 | J47: =SUM('P&L Medzy '!BN61:BY61) -> 24000 | K47: =SUM('P&L Medzy '!BZ61:CK61) -> 24000
C48: ='P&L Medzy '!B62 -> Recruitment Charges | D48: 11605.5 | E48: 4555.82 | F48: =SUM('P&L Medzy '!P62:AA62) -> 1634.73 | G48: =SUM('P&L Medzy '!AB62:AM62) -> 20890.56 | H48: =SUM('P&L Medzy '!AN62:BA62) -> 35000 | I48: =SUM('P&L Medzy '!BB62:BM62) -> 30000 | J48: =SUM('P&L Medzy '!BN62:BY62) -> 30000 | K48: =SUM('P&L Medzy '!BZ62:CK62) -> 30000
C49: ='P&L Medzy '!B63 -> Offices Expenses | D49: 107890.65 | E49: =151.37+36765.19 -> 36916.56 | F49: =SUM('P&L Medzy '!P63:AA63) -> 24286.95 | G49: =SUM('P&L Medzy '!AB63:AM63) -> 36203 | H49: =SUM('P&L Medzy '!AN63:BA63) -> 67000 | I49: =SUM('P&L Medzy '!BB63:BM63) -> 60000 | J49: =SUM('P&L Medzy '!BN63:BY63) -> 60000 | K49: =SUM('P&L Medzy '!BZ63:CK63) -> 60000
C50: ='P&L Medzy '!B64 -> Taxes, Permit | D50: =218+1299.03 -> 1517.03 | E50: =787+2736.7 -> 3523.7 | F50: =SUM('P&L Medzy '!P64:AA64) -> 2345.01 | G50: =SUM('P&L Medzy '!AB64:AM64) -> 4000 | H50: =SUM('P&L Medzy '!AN64:BA64) -> 10000 | I50: =SUM('P&L Medzy '!BB64:BM64) -> 9000 | J50: =SUM('P&L Medzy '!BN64:BY64) -> 9000 | K50: =SUM('P&L Medzy '!BZ64:CK64) -> 9000
C51: ='P&L Medzy '!B65 -> Interest and bank charges | D51: =2315.7+10750 -> 13065.7 | E51: =9261.43+163.76+710.54 -> 10135.73 | F51: =SUM('P&L Medzy '!P65:AA65) -> 23233.89 | G51: =SUM('P&L Medzy '!AB65:AM65) -> 16914.96 | H51: =SUM('P&L Medzy '!AN65:BA65) -> 16400 | I51: =SUM('P&L Medzy '!BB65:BM65) -> 14400 | J51: =SUM('P&L Medzy '!BN65:BY65) -> 14400 | K51: =SUM('P&L Medzy '!BZ65:CK65) -> 14400
C52: ='P&L Medzy '!B66 -> Shipping | D52: 0 | E52: 0 | F52: =SUM('P&L Medzy '!P66:AA66) -> 3095.98 | G52: =SUM('P&L Medzy '!AB66:AM66) -> 5401.96 | H52: =SUM('P&L Medzy '!AN66:BA66) -> 7000 | I52: =SUM('P&L Medzy '!BB66:BM66) -> 6000 | J52: =SUM('P&L Medzy '!BN66:BY66) -> 6000 | K52: =SUM('P&L Medzy '!BZ66:CK66) -> 6000
C53: ='P&L Medzy '!B67 -> Exchange Gain or Loss | D53: 58.95 | E53: 5.79 | F53: =SUM('P&L Medzy '!P67:AA67) -> 261.92 | G53: =SUM('P&L Medzy '!AB67:AM67) -> 492.96 | H53: =SUM('P&L Medzy '!AN67:BA67) -> 0 | I53: =SUM('P&L Medzy '!BB67:BM67) -> 0 | J53: =SUM('P&L Medzy '!BN67:BY67) -> 0 | K53: =SUM('P&L Medzy '!BZ67:CK67) -> 0
C54: ='P&L Medzy '!B68 -> Loans Interests | D54: 59246.09 | E54: 32208.44 | F54: =SUM('P&L Medzy '!P68:AA68) -> 31118.13 | G54: =SUM('P&L Medzy '!AB68:AM68) -> 29301.72 | H54: =SUM('P&L Medzy '!AN68:BA68) -> 21453.6 | I54: =SUM('P&L Medzy '!BB68:BM68) -> 6423.6 | J54: =SUM('P&L Medzy '!BN68:BY68) -> 36.75 | K54: =SUM('P&L Medzy '!BZ68:CK68) -> 0
C56: ='P&L Medzy '!B70 -> Tech & Marketing (Content&Advertising) | D56: =49919.07+439413.4 -> 489332.47 | E56: 184257.88 | F56: =SUM('P&L Medzy '!P70:AA70) -> 51790.15 | G56: =SUM('P&L Medzy '!AB70:AM70) -> 424790.93 | H56: =SUM('P&L Medzy '!AN70:BA70) -> 1469722.2 | I56: =SUM('P&L Medzy '!BB70:BM70) -> 2905224 | J56: =SUM('P&L Medzy '!BN70:BY70) -> 4991582 | K56: =SUM('P&L Medzy '!BZ70:CK70) -> 7494553.9
C57: ='P&L Medzy '!B71 -> Trade and Events | D57: 436.9 | E57: 3685 | F57: =SUM('P&L Medzy '!P71:AA71) -> 6986.4 | G57: =SUM('P&L Medzy '!AB71:AM71) -> 31334.8 | H57: =SUM('P&L Medzy '!AN71:BA71) -> 100000 | I57: =SUM('P&L Medzy '!BB71:BM71) -> 90000 | J57: =SUM('P&L Medzy '!BN71:BY71) -> 90000 | K57: =SUM('P&L Medzy '!BZ71:CK71) -> 90000
C60: TOTAL EXPENSES | D60: =SUM(D23:D59) -> 1898790.2 | E60: =SUM(E23:E59) -> 1975887.9 | F60: =SUM(F23:F59) -> 2090300 | G60: =SUM(G23:G59) -> 2871923.1 | H60: =SUM(H23:H59) -> 6646930 | I60: =SUM(I23:I59) -> 7580168.7 | J60: =SUM(J23:J59) -> 9694343.8 | K60: =SUM(K23:K59) -> 12233193
B62: P&L | C62: P&L (Before Taxes Credits) | D62: =D14-D60 -> -1309867.2 | E62: =E14-E60 -> -1265743 | F62: =F14-F60 -> -1246480.6 | G62: =G14-G60 -> -1426701.7 | H62: =H14-H60 -> -2293358.3 | I62: =I14-I60 -> 4018505.6 | J62: =J14-J60 -> 10935447 | K62: =K14-K60 -> 18684319 | M62: CF | N62: =SUM(G62:K62) -> 29918212
C63: Tax Credits | D63: 139000 | E63: 139000 | F63: ='Loans & Grants'!AH41+'Loans & Grants'!AK42 -> 415732.59 | G63: =F63 -> 415732.59 | H63: =G63 -> 415732.59 | I63: =H63 -> 415732.59 | J63: =I63 -> 415732.59 | K63: =J63 -> 415732.59 | M63: Discount | N63: 0.15
C64: P&L (After Taxes Credits) | D64: =+D62+D63 -> -1170867.2 | E64: =+E62+E63 -> -1126743 | F64: =+F62+F63 -> -830748.05 | G64: =+G62+G63 -> -1010969.1 | H64: =+H62+H63 -> -1877625.7 | I64: =+I62+I63 -> 4434238.2 | J64: =+J62+J63 -> 11351180 | K64: =+K62+K63 -> 19100052 | M64: NPV | N64: =NPV(N63,G62,H62,I62,J62,K62) -> 15209300
D67: 2022 | E67: 2022 | F67: 2023 | G67: 2024 | H67: 2025 | I67: 2026 | J67: 2027 | K67: 2028
B68: Financing | D68: ACTUALS | G68: FORECASTS
C70: Investment | D70: 2500000 | F70: =SUM('P&L Medzy '!Z91:Z95) -> 300000 | G70: =SUM('P&L Medzy '!AB91:AM95) -> 2800000 | H70: =SUM('P&L Medzy '!AN91:BA95) -> 0 | I70: =SUM('P&L Medzy '!AO91:BB95) -> 0 | J70: =SUM('P&L Medzy '!AP91:BC95) -> 0 | K70: =SUM('P&L Medzy '!AQ91:BD95) -> 0
C71: Loans/Credit Margin | D71: =250000+216000 -> 466000 | E71: 200000 | F71: 0 | G71: =SUM('P&L Medzy '!AB96:AM96) -> 0 | H71: =SUM('P&L Medzy '!AN96:BA96) -> 0 | I71: =SUM('P&L Medzy '!AO96:BB96) -> 0 | J71: =SUM('P&L Medzy '!AP96:BC96) -> 0 | K71: =SUM('P&L Medzy '!AQ96:BD96) -> 0
C72: Grants / Tax Credits | D72: 139000 | E72: 305000 | F72: =SUM('P&L Medzy '!P98:AA98) -> 227169 | G72: =SUM('P&L Medzy '!AB98:AM98) -> 835732.59 | H72: =SUM('P&L Medzy '!AN98:BA98) -> 1565732.6 | I72: =SUM('P&L Medzy '!AO98:BB98) -> 1290732.6 | J72: =SUM('P&L Medzy '!AP98:BC98) -> 1265732.6 | K72: =SUM('P&L Medzy '!AQ98:BD98) -> 1240732.6
C74: TOTAL | D74: =SUM(D70:D72) -> 3105000 | E74: =SUM(E70:E72) -> 505000 | F74: =SUM(F68:F73) -> 527169 | G74: =SUM(G68:G73) -> 3635732.6 | H74: =SUM(H68:H73) -> 1565732.6 | I74: =SUM(I68:I73) -> 1290732.6 | J74: =SUM(J68:J73) -> 1265732.6 | K74: =SUM(K68:K73) -> 1240732.6
C76: TOTAL FINANCING/Investment | D76: =D74 -> 3105000 | E76: =D74+E74 -> 3610000 | F76: =E74+F74 -> 1032169 | G76: =F76+G74 -> 4667901.6 | H76: =G76+H74 -> 6233634.2 | I76: =H76+I74 -> 7524366.8 | J76: =I76+J74 -> 8790099.4 | K76: =J76+K74 -> 10030832
C80: MEDZY - Financing Recap to get to Cashflow Positive 2023-2025
C82: Financing Round | D82: 2500000 | F82: =D82/$D$89 -> 0.48063381
C83: =C72 -> Grants / Tax Credits | D83: =G72+H72 -> 2401465.2 | F83: =D83/$D$89 -> 0.46169014
C84: Loans | D84: 300000 | F84: =D84/$D$89 -> 0.057676057
C86: Bridge/Margin Payback | D86: partial due | E86: 750000 | F86: =E86/E89 -> 0.14419014
C87: Payables Repayment | E87: 400000 | F87: =E87/E89 -> 0.076901409
C88: Operational Cashflow | E88: =D89-E86-E87 -> 4051465.2 | F88: =E88/E89 -> 0.77890845
D89: =SUM(D82:D88) -> 5201465.2 | E89: =SUM(E82:E88) -> 5201465.2

Sheet P&L Medzy 
B1: MEDZY Inc - Forecast 2023-2025
P3: ACTUALS - indication of costs (NOT FORMAL FINANCIAL STATEMENTS) | AB3: Forecast | AC3: Forecast | AD3: Forecast | AE3: Forecast | AF3: Forecast | AG3: Forecast | AH3: Forecast | AI3: Forecast | AJ3: Forecast | AK3: Forecast | AL3: Forecast | AM3: Forecast | AN3: Forecast | AO3: Forecast | AP3: Forecast | AQ3: Forecast | AR3: Forecast | AS3: Forecast | AT3: Forecast | AU3: Forecast | AV3: Forecast | AW3: Forecast | AX3: Forecast | AY3: Forecast | AZ3: Forecast | BA3: Forecast | BB3: Forecast | BC3: Forecast | BD3: Forecast | BE3: Forecast | BF3: Forecast | BG3: Forecast | BH3: Forecast | BI3: Forecast | BJ3: Forecast | BK3: Forecast | BL3: Forecast | BM3: Forecast | BN3: Forecast | BO3: Forecast | BP3: Forecast | BQ3: Forecast | BR3: Forecast | BS3: Forecast | BT3: Forecast | BU3: Forecast | BV3: Forecast | BW3: Forecast | BX3: Forecast | BY3: Forecast | BZ3: Forecast | CA3: Forecast | CB3: Forecast | CC3: Forecast | CD3: Forecast | CE3: Forecast | CF3: Forecast | CG3: Forecast | CH3: Forecast | CI3: Forecast | CJ3: Forecast | CK3: Forecast
B4: REVENUS | F4: 2022 | R4: 2023 | AD4: 2024 | AP4: 2025 | BB4: 2026 | BN4: 2027 | BZ4: 2028
F5: 44562 | G5: 44593 | H5: 44621 | I5: 44652 | J5: 44682 | K5: 44713 | L5: 44743 | M5: 44774 | N5: 44805 | O5: 44835 | P5: 44866 | Q5: 44896 | R5: 44927 | S5: 44958 | T5: 44986 | U5: 45017 | V5: 45047 | W5: 45078 | X5: 45108 | Y5: 45139 | Z5: 45170 | AA5: 45200 | AB5: 45231 | AC5: 45261 | AD5: 45292 | AE5: 45323 | AF5: 45352 | AG5: 45383 | AH5: 45413 | AI5: 45444 | AJ5: 45474 | AK5: 45505 | AL5: 45536 | AM5: 45566 | AN5: 45597 | AO5: 45627 | AP5: 45658 | AQ5: 45689 | AR5: 45717 | AS5: 45748 | AT5: 45778 | AU5: 45809 | AV5: 45839 | AW5: 45870 | AX5: 45901 | AY5: 45931 | AZ5: 45962 | BA5: 45992 | BB5: 45658 | BC5: 45689 | BD5: 45717 | BE5: 45748 | BF5: 45778 | BG5: 45809 | BH5: 45839 | BI5: 45870 | BJ5: 45901 | BK5: 45931 | BL5: 45962 | BM5: 45992 | BN5: 45658 | BO5: 45689 | BP5: 45717 | BQ5: 45748 | BR5: 45778 | BS5: 45809 | BT5: 45839 | BU5: 45870 | BV5: 45901 | BW5: 45931 | BX5: 45962 | BY5: 45992 | BZ5: 45658 | CA5: 45689 | CB5: 45717 | CC5: 45748 | CD5: 45778 | CE5: 45809 | CF5: 45839 | CG5: 45870 | CH5: 45901 | CI5: 45931 | CJ5: 45962 | CK5: 45992
B8: KPIS
B10: New Clients | Y10: ='Marketing and Sales'!Y5 -> 151.80952 | Z10: ='Marketing and Sales'!Z5 -> 153.80952 | AA10: ='Marketing and Sales'!AA5 -> 155.80952 | AB10: ='Marketing and Sales'!AB5 -> 179 | AC10: ='Marketing and Sales'!AC5 -> 181 | AD10: ='Marketing and Sales'!AD5 -> 184.31579 | AE10: ='Marketing and Sales'!AE5 -> 226.31579 | AF10: ='Marketing and Sales'!AF5 -> 294.10526 | ... CK10: ='Marketing and Sales'!CK5 -> 8499.4667
B11: Churn | Y11: ='Marketing and Sales'!Y6 -> 76.320674 | Z11: ='Marketing and Sales'!Z6 -> 77.171637 | AA11: ='Marketing and Sales'!AA6 -> 78.363484 | AB11: ='Marketing and Sales'!AB6 -> 79.540252 | AC11: ='Marketing and Sales'!AC6 -> 80.716811 | AD11: ='Marketing and Sales'!AD6 -> 82.222232 | AE11: ='Marketing and Sales'!AE6 -> 83.729918 | AF11: ='Marketing and Sales'!AF6 -> 85.210688 | ... CK11: ='Marketing and Sales'!CK6 -> 3345.2054
B12: Total Clients | F12: 3500 | G12: 3500 | H12: 3500 | I12: 3500 | J12: 3500 | K12: 3500 | L12: 3550 | M12: 3800 | N12: 4000 | O12: 4100 | U12: ='Marketing and Sales'!U7 -> 4343.444 | V12: ='Marketing and Sales'!V7 -> 4370.632 | W12: ='Marketing and Sales'!W7 -> 4398.0362 | X12: ='Marketing and Sales'!X7 -> 4446.035 | Y12: ='Marketing and Sales'!Y7 -> 4513.5239 | Z12: ='Marketing and Sales'!Z7 -> 4580.1618 | AA12: ='Marketing and Sales'!AA7 -> 4645.6078 | AB12: ='Marketing and Sales'!AB7 -> 4731.0676 | ... CK12: ='Marketing and Sales'!CK7 -> 177380.24
B13: Pharmacy Revenues | F13: 271351.31 | G13: 346671.19 | H13: 299360.68 | I13: 286619.21 | J13: 335521.54 | K13: 308437.92 | L13: 327251.67 | M13: 423725.2 | N13: 381647.99 | O13: 392558 | P13: ='Marketing and Sales'!P8 -> 375747.67 | Q13: ='Marketing and Sales'!Q8 -> 359175 | R13: 395802 | S13: 393267.57 | T13: 385053.93 | U13: 436144.26 | V13: 429750.16 | W13: 407798.21 | X13: 462265.2 | Y13: =Y16/17.5*100 -> 399268.34 | Z13: =Z16/17.5*100 -> 397411.43 | AA13: 501000 | AB13: ='Marketing and Sales'!AB8 -> 450193.95 | AC13: ='Marketing and Sales'!AC8 -> 460150.73 | AD13: ='Marketing and Sales'!AD8 -> 426918.17 | AE13: ='Marketing and Sales'!AE8 -> 434143.85 | AF13: ='Marketing and Sales'!AF8 -> 448390.13 | AG13: ='Marketing and Sales'!AG8 -> 504042.4 | AH13: ='Marketing and Sales'!AH8 -> 568991.43 | AI13: ='Marketing and Sales'!AI8 -> 641535.19 | ... CK13: ='Marketing and Sales'!CK8 -> 13279308
B14: Original Target | F14: na | G14: na | H14: na | I14: na | J14: na | K14: na | L14: 325000 | M14: 340000 | N14: 345000 | O14: 360000
B16: Medzy Platform Revenues | C16: 0.175 | F16: =F13*$C$16 -> 47486.479 | G16: =G13*$C$16 -> 60667.458 | H16: =H13*$C$16 -> 52388.119 | I16: =I13*$C$16 -> 50158.362 | J16: =J13*$C$16 -> 58716.269 | K16: =K13*$C$16 -> 53976.636 | L16: =L13*$C$16 -> 57269.042 | M16: =M13*$C$16 -> 74151.91 | ... O16: =O13*$C$16 -> 68697.65 | P16: ='Marketing and Sales'!P10 -> 67254.145 | Q16: ='Marketing and Sales'!Q10 -> 69258.154 | R16: ='Marketing and Sales'!R10 -> 70328.32 | S16: 68821 | T16: 67834 | U16: 73237 | V16: 71263.84 | W16: 69604.03 | X16: 77682.41 | Y16: 69871.96 | Z16: 69547 | AA16: ='Marketing and Sales'!AA10 -> 69117.51 | AB16: ='Marketing and Sales'!AB10 -> 69586.356 | AC16: ='Marketing and Sales'!AC10 -> 70049.787 | AD16: ='Marketing and Sales'!AD10 -> 70527.864 | AE16: ='Marketing and Sales'!AE10 -> 71347.257 | AF16: ='Marketing and Sales'!AF10 -> 72915.688 | AG16: ='Marketing and Sales'!AG10 -> 81651.115 | AH16: ='Marketing and Sales'!AH10 -> 91935.22 | ... CK16: ='Marketing and Sales'!CK10 -> 2996024.2
B17: Rev Share PAID
B18: Due to Medzy Reimbursment
B19: Due to Medzy
B21: OTC upsell Medzy | C21: 0 | D21: avg | X21: =X12*$C21*$C22 -> 0 | Y21: =Y12*$C21*$C22 -> 0 | Z21: =Z12*$C21*$C22 -> 0 | AA21: =AA12*$C21*$C22 -> 0 | AB21: =AB12*$C21*$C22 -> 0 | AC21: =AC12*$C21*$C22 -> 0 | AD21: =AD12*$C21*$C22 -> 0 | AE21: =AE12*$C21*$C22 -> 0 | ... CK21: =CK12*$C21*$C22 -> 0
C22: 0 | D22: user base
B24: MEDZY TOTAL REVENUES | F24: =F17 -> 0 | G24: =G17 -> 0 | H24: =H17 -> 0 | I24: =I17 -> 0 | J24: =J17 -> 0 | K24: =K17 -> 0 | L24: =L17 -> 0 | M24: =M17 -> 0 | ... O24: =O17 -> 0 | P24: =SUM(P16:P23) -> 67254.145 | Q24: =SUM(Q16:Q23) -> 69258.154 | R24: =SUM(R16:R23) -> 70328.32 | S24: =SUM(S16:S23) -> 68821 | T24: =SUM(T16:T23) -> 67834 | U24: =SUM(U16:U23) -> 73237 | V24: =SUM(V16:V23) -> 71263.84 | W24: =SUM(W16:W23) -> 69604.03 | ... CK24: =SUM(CK16:CK23) -> 2996024.2
B25: CUMULATIVE TOTAL REVENUES | F25: =E25+F24 -> 0 | G25: =F25+G24 -> 0 | H25: =G25+H24 -> 0 | I25: =H25+I24 -> 0 | J25: =I25+J24 -> 0 | K25: =J25+K24 -> 0 | L25: =K25+L24 -> 0 | M25: =L25+M24 -> 0 | ... CK25: =CJ25+CK24 -> 69928226
B29: Expenses | C29: Annual | F29: 2022 | R29: 2023 | AD29: 2024 | AP29: 2025 | BB29: 2026 | BN29: 2027 | BZ29: 2028
C30: compensation | F30: 44562 | G30: 44593 | H30: 44621 | I30: 44652 | J30: 44682 | K30: 44713 | L30: 44743 | M30: 44774 | N30: 44805 | O30: 44835 | P30: 44866 | Q30: 44896 | R30: 44927 | S30: 44958 | T30: 44986 | U30: 45017 | V30: 45047 | W30: 45078 | X30: 45108 | Y30: 45139 | Z30: 45170 | AA30: 45200 | AB30: 45231 | AC30: 45261 | AD30: 45292 | AE30: 45323 | AF30: 45352 | AG30: 45383 | AH30: 45413 | AI30: 45444 | AJ30: 45474 | AK30: 45505 | AL30: 45536 | AM30: 45566 | AN30: 45597 | AO30: 45627 | AP30: 45658 | AQ30: 45689 | AR30: 45717 | AS30: 45748 | AT30: 45778 | AU30: 45809 | AV30: 45839 | AW30: 45870 | AX30: 45901 | AY30: 45931 | AZ30: 45962 | BA30: 45992 | BB30: 45658 | BC30: 45689 | BD30: 45717 | BE30: 45748 | BF30: 45778 | BG30: 45809 | BH30: 45839 | BI30: 45870 | BJ30: 45901 | BK30: 45931 | BL30: 45962 | BM30: 45992 | BN30: 45658 | BO30: 45689 | BP30: 45717 | BQ30: 45748 | BR30: 45778 | BS30: 45809 | BT30: 45839 | BU30: 45870 | BV30: 45901 | BW30: 45931 | BX30: 45962 | BY30: 45992 | BZ30: 45658 | CA30: 45689 | CB30: 45717 | CC30: 45748 | CD30: 45778 | CE30: 45809 | CF30: 45839 | CG30: 45870 | CH30: 45901 | CI30: 45931 | CJ30: 45962 | CK30: 45992
B31: COS
B33: Salaries
B34: IT | F34: 48745.74 | G34: 54972.78 | H34: 84348.68 | I34: 58881.67 | J34: 56288.86 | K34: 59612.95 | L34: 67173.04 | M34: 44926.4 | N34: 67827.67 | O34: 72345.39 | P34: 76912.42 | Q34: 80555.26 | R34: 79313.91 | S34: =-12000+103958.34 -> 91958.34 | T34: 137055.95 | U34: 104155.54 | V34: 93533.52 | W34: 98175.1 | X34: 80667.6 | Y34: 102940.38 | Z34: 90565.96 | AA34: 90565.96 | AB34: 90565.96 | AC34: 90565.96 | AD34: 80000 | AE34: 60000 | AF34: 60000 | AG34: ='Salaries & Contractuals'!AH29 -> 80654.167 | AH34: ='Salaries & Contractuals'!AI29 -> 80654.167 | AI34: ='Salaries & Contractuals'!AJ29 -> 95070.833 | AJ34: ='Salaries & Contractuals'!AK29 -> 95070.833 | AK34: ='Salaries & Contractuals'!AL29 -> 95070.833 | AL34: ='Salaries & Contractuals'!AM29 -> 95070.833 | AM34: ='Salaries & Contractuals'!AN29 -> 95070.833 | AN34: ='Salaries & Contractuals'!AO29 -> 95070.833 | ... CK34: ='Salaries & Contractuals'!CL29 -> 124350
B35: Sales / Marketing | F35: 7108.15 | G35: 9225.63 | H35: 11046.54 | I35: 7268.44 | J35: 7196.29 | K35: 9403.81 | L35: 11246.98 | M35: 3205.51 | N35: 1715.57 | O35: 0 | P35: 0 | Q35: 0 | R35: 0 | S35: 0 | T35: 0 | U35: 39609.07 | V35: 22272.5 | W35: 13460 | X35: 18545 | Y35: 9015 | Z35: 1320 | AA35: 1320 | AB35: 1320 | AC35: 1320 | AD35: 1320 | AE35: 1320 | AF35: 1320 | AG35: ='Salaries & Contractuals'!AH44 -> 16683.333 | AH35: ='Salaries & Contractuals'!AI44 -> 30433.333 | AI35: ='Salaries & Contractuals'!AJ44 -> 40016.667 | AJ35: ='Salaries & Contractuals'!AK44 -> 40016.667 | AK35: ='Salaries & Contractuals'!AL44 -> 57433.333 | AL35: ='Salaries & Contractuals'!AM44 -> 63683.333 | AM35: ='Salaries & Contractuals'!AN44 -> 63683.333 | AN35: ='Salaries & Contractuals'!AO44 -> 63683.333 | ... CK35: ='Salaries & Contractuals'!CL44 -> 90640.872
B36: Operations | F36: 6338.31 | G36: 1869.05 | H36: 0 | I36: 0 | J36: 0 | K36: 0 | L36: 676.06 | M36: 1944.12 | N36: 0 | O36: 0 | P36: =2600+300+2250+2422 -> 7572 | Q36: =5000+1400+525 -> 6925 | R36: 14200 | S36: 2700 | T36: 5650 | U36: 28600 | V36: 17778 | W36: 21232 | X36: 5550 | Y36: 0 | Z36: 0 | AA36: 0 | AB36: 0 | AC36: 0 | AD36: 0 | AE36: 0 | AG36: ='Salaries & Contractuals'!AH57 -> 22916.667 | AH36: ='Salaries & Contractuals'!AI57 -> 22916.667 | AI36: ='Salaries & Contractuals'!AJ57 -> 45833.333 | AJ36: ='Salaries & Contractuals'!AK57 -> 45833.333 | AK36: ='Salaries & Contractuals'!AL57 -> 55000 | AL36: ='Salaries & Contractuals'!AM57 -> 66458.333 | AM36: ='Salaries & Contractuals'!AN57 -> 66458.333 | AN36: ='Salaries & Contractuals'!AO57 -> 72708.333 | ... CK36: ='Salaries & Contractuals'!CL57 -> 76041.667
B37: Sub total | F37: =SUM(F34:F36) -> 62192.2 | G37: =SUM(G34:G36) -> 66067.46 | H37: =SUM(H34:H36) -> 95395.22 | I37: =SUM(I34:I36) -> 66150.11 | J37: =SUM(J34:J36) -> 63485.15 | K37: =SUM(K34:K36) -> 69016.76 | L37: =SUM(L34:L36) -> 79096.08 | M37: =SUM(M34:M36) -> 50076.03 | ... CK37: =SUM(CK34:CK36) -> 291032.54
B39: Fringes + Bonus | C39: 0.12 | AF39: =(SUM(AF34:AF36))*$C39 -> 7358.4 | AG39: =(SUM(AG34:AG36))*$C39 -> 14430.5 | AH39: =(SUM(AH34:AH36))*$C39 -> 16080.5 | AI39: =(SUM(AI34:AI36))*$C39 -> 21710.5 | AJ39: =(SUM(AJ34:AJ36))*$C39 -> 21710.5 | AK39: =(SUM(AK34:AK36))*$C39 -> 24900.5 | AL39: =(SUM(AL34:AL36))*$C39 -> 27025.5 | AM39: =(SUM(AM34:AM36))*$C39 -> 27025.5 | ... CK39: =(SUM(CK34:CK36))*$C39 -> 34923.905
B41: Contractuals - Tech | S41: 3168 | T41: 5280 | V41: ='Salaries & Contractuals'!W71 -> 0 | W41: ='Salaries & Contractuals'!X71 -> 0 | X41: ='Salaries & Contractuals'!Y71 -> 0 | Y41: ='Salaries & Contractuals'!Z71 -> 0 | Z41: ='Salaries & Contractuals'!AA71 -> 0 | AA41: ='Salaries & Contractuals'!AB71 -> 0 | AB41: ='Salaries & Contractuals'!AC71 -> 0 | AC41: ='Salaries & Contractuals'!AD71 -> 0 | ... CK41: ='Salaries & Contractuals'!CL71 -> 0
B42: Contractuals - Operations | P42: =0.87+5497.4+15000+9000+31035.9 -> 60534.17 | Q42: =15000+9000+15000+41934.91 -> 80934.91 | R42: =19229.24+24000 -> 43229.24 | S42: =37523.37+29000 -> 66523.37 | T42: =24998.48+24000 -> 48998.48 | U42: 0 | V42: 0 | W42: 0 | X42: 0 | Y42: =14475-3750 -> 10725 | Z42: =25357.38-3750 -> 21607.38 | AA42: 10000 | AB42: 10000 | AC42: 10000 | AD42: 5000 | AE42: 5000 | AF42: 5000 | AG42: 5000 | AH42: 5000 | AI42: 5000 | AJ42: 5000 | AK42: 5000 | AL42: 5000 | AM42: 5000 | AN42: 5000 | AO42: ='Salaries & Contractuals'!AP82 -> 0 | AP42: ='Salaries & Contractuals'!AQ82 -> 0 | AQ42: ='Salaries & Contractuals'!AR82 -> 0 | AR42: ='Salaries & Contractuals'!AS82 -> 0 | AS42: ='Salaries & Contractuals'!AT82 -> 0 | AT42: ='Salaries & Contractuals'!AU82 -> 0 | AU42: ='Salaries & Contractuals'!AV82 -> 0 | AV42: ='Salaries & Contractuals'!AW82 -> 0 | ... CK42: ='Salaries & Contractuals'!CL82 -> 0
B44: Professionals
B45: Accounting Fees | F45: 1000 | G45: 1000 | H45: 1000 | I45: 1000 | J45: 1000 | K45: 1000 | L45: 1000 | M45: 1000 | N45: 1000 | O45: 1000 | P45: =4456+1000+4150 -> 9606 | Q45: =2750+3123 -> 5873 | R45: 4756.5 | S45: 1815 | T45: 1250 | U45: 0 | V45: 0 | W45: 0 | X45: 0 | Y45: 3750 | Z45: 3750 | AA45: 3750 | AB45: 3750 | AC45: 3750 | AD45: 3750 | AE45: 3750 | AF45: 1250 | AG45: =15000+1250 -> 16250 | AH45: 1250 | AI45: 1250 | AJ45: 1250 | AK45: 1250 | AL45: 1250 | AM45: 1250 | AN45: 1250 | AO45: 1250 | AP45: 1500 | AQ45: 1500 | AR45: 1500 | AS45: =20000+1500 -> 21500 | AT45: 1500 | AU45: 1500 | AV45: 1750 | AW45: 1750 | AX45: 1750 | AY45: 1750 | AZ45: 1750 | BA45: 1750 | BB45: 1500 | BC45: 1500 | BD45: 1500 | BE45: =20000+1500 -> 21500 | BF45: 1500 | BG45: 1500 | BH45: 1750 | BI45: 1750 | BJ45: 1750 | BK45: 1750 | BL45: 1750 | BM45: 1750 | BN45: 1500 | BO45: 1500 | BP45: 1500 | BQ45: =20000+1500 -> 21500 | BR45: 1500 | BS45: 1500 | BT45: 1750 | BU45: 1750 | BV45: 1750 | BW45: 1750 | BX45: 1750 | BY45: 1750 | BZ45: 1500 | CA45: 1500 | CB45: 1500 | CC45: =20000+1500 -> 21500 | CD45: 1500 | CE45: 1500 | CF45: 1750 | CG45: 1750 | CH45: 1750 | CI45: 1750 | CJ45: 1750 | CK45: 1750
B46: Legal Fees | F46: 4875.76 | G46: 29404.68 | H46: 1876.64 | I46: 0 | J46: 0 | K46: 1672.4 | L46: 29404.12 | M46: 4237.1 | N46: 21453.37 | O46: -1498.26 | P46: 8814.06 | Q46: 503.59 | R46: 0 | S46: 0 | T46: 0 | U46: 1647 | V46: 2801 | W46: 3237 | X46: 1383 | Y46: 6684 | Z46: 3195 | AA46: 0 | AB46: 0 | AC46: 0 | AD46: 0 | AE46: 0 | AF46: 0 | AG46: 20000 | AH46: 20000 | AI46: 4000 | AJ46: 4000 | AK46: 4000 | AL46: 4000 | AM46: 4000 | AN46: 4000 | AO46: 4000 | AP46: 5000 | AQ46: 5000 | AR46: 5000 | AS46: 5000 | AT46: 5000 | AU46: 5000 | AV46: 5000 | AW46: 5000 | AX46: 5000 | AY46: 5000 | AZ46: 5000 | BA46: 5000 | BB46: 5000 | BC46: 5000 | BD46: 5000 | BE46: 5000 | BF46: 5000 | BG46: 5000 | BH46: 5000 | BI46: 5000 | BJ46: 5000 | BK46: 5000 | BL46: 5000 | BM46: 5000 | BN46: 5000 | BO46: 5000 | BP46: 5000 | BQ46: 5000 | BR46: 5000 | BS46: 5000 | BT46: 5000 | BU46: 5000 | BV46: 5000 | BW46: 5000 | BX46: 5000 | BY46: 5000 | BZ46: 5000 | CA46: 5000 | CB46: 5000 | CC46: 5000 | CD46: 5000 | CE46: 5000 | CF46: 5000 | CG46: 5000 | CH46: 5000 | CI46: 5000 | CJ46: 5000 | CK46: 5000
B47: Other | F47: 0 | G47: 0 | H47: 0 | I47: 0 | J47: 0 | K47: 0 | L47: 0 | M47: 0 | N47: 0 | O47: 0 | R47: =4956.76-500 -> 4456.76 | S47: =8408.39-500 -> 7908.39 | T47: =(16065.53-T41)+(6440.72-500) -> 16726.25 | U47: 0 | V47: 2657 | W47: 1017 | X47: 2311 | Y47: 0 | Z47: 0 | AA47: 2000 | AB47: 2000 | AC47: 2000 | AD47: 2000 | AE47: 2000 | AF47: 2000 | AG47: 10000 | AH47: 10000 | AI47: 10000 | AJ47: 10000 | AK47: 10000 | AL47: 10000 | AM47: 10000 | AN47: 10000 | AO47: 10000 | AP47: 12500 | AQ47: 12500 | AR47: 12500 | AS47: 12500 | AT47: 12500 | AU47: 12500 | AV47: 12500 | AW47: 12500 | AX47: 12500 | AY47: 12500 | AZ47: 12500 | BA47: 12500 | BB47: 12500 | BC47: 12500 | BD47: 12500 | BE47: 12500 | BF47: 12500 | BG47: 12500 | BH47: 12500 | BI47: 12500 | BJ47: 12500 | BK47: 12500 | BL47: 12500 | BM47: 12500 | BN47: 12500 | BO47: 12500 | BP47: 12500 | BQ47: 12500 | BR47: 12500 | BS47: 12500 | BT47: 12500 | BU47: 12500 | BV47: 12500 | BW47: 12500 | BX47: 12500 | BY47: 12500 | BZ47: 12500 | CA47: 12500 | CB47: 12500 | CC47: 12500 | CD47: 12500 | CE47: 12500 | CF47: 12500 | CG47: 12500 | CH47: 12500 | CI47: 12500 | CJ47: 12500 | CK47: 12500
B51: SubTotal Salaries | F51: =SUM(F45:F49)+F37 -> 68067.96 | G51: =SUM(G45:G49)+G37 -> 96472.14 | H51: =SUM(H45:H49)+H37 -> 98271.86 | I51: =SUM(I45:I49)+I37 -> 67150.11 | J51: =SUM(J45:J49)+J37 -> 64485.15 | K51: =SUM(K45:K49)+K37 -> 71689.16 | L51: =SUM(L45:L49)+L37 -> 109500.2 | M51: =SUM(M45:M49)+M37 -> 55313.13 | ... O51: =SUM(O45:O49)+O37 -> 71847.13 | P51: =SUM(P39:P49)+P37 -> 163438.65 | Q51: =SUM(Q37:Q47) -> 174791.76 | R51: =SUM(R37:R47) -> 145956.41 | S51: =SUM(S37:S47) -> 174073.1 | T51: =SUM(T37:T47) -> 214960.68 | U51: =SUM(U37:U47) -> 174011.61 | V51: =SUM(V37:V47) -> 139042.02 | W51: =SUM(W37:W47) -> 137121.1 | X51: =SUM(X37:X47) -> 108456.6 | ... CK51: =SUM(CK37:CK47) -> 345206.44
B53: Rent | C53: Net of Recharge to PSB | F53: 2823.34 | G53: 2823.34 | H53: 2823.34 | I53: 2823.34 | J53: 2823.34 | K53: 2823.34 | L53: 2823.34 | M53: 4235 | N53: 2999.79 | O53: 2999.79 | P53: 3000.01 | Q53: 3209.56 | R53: 4878.67 | S53: 4878.67 | T53: 4878.67 | U53: 4878.67 | V53: 4878.67 | W53: 4878.67 | X53: 4878.67 | Y53: 4878.67 | Z53: 4878.67 | AA53: 4878.67 | AB53: 4878.67 | AC53: 4878.67 | AD53: 4878.67 | AE53: 4878.67 | AF53: 4878.67 | AG53: 4878.67 | AH53: 4878.67 | AI53: 4878.67 | AJ53: =6000-'PSB-P&L '!AJ54 -> 6000 | AK53: =6000-'PSB-P&L '!AK54 -> 6000 | AL53: =6000-'PSB-P&L '!AL54 -> 6000 | AM53: =6000-'PSB-P&L '!AM54 -> 6000 | AN53: =6000-'PSB-P&L '!AN54 -> 6000 | AO53: =6000-'PSB-P&L '!AO54 -> 6000 | AP53: =6000-'PSB-P&L '!AP54 -> 6000 | AQ53: =6000-'PSB-P&L '!AQ54 -> 6000 | ... CK53: =6000-'PSB-P&L '!CK54 -> 6000
B54: Utilities | F54: 312.99 | G54: 0 | H54: 341.73 | I54: 0 | J54: 304.98 | K54: 0 | L54: 425.14 | M54: 0 | N54: 729.91 | O54: 0 | T54: 646.98 | Y54: 1428.77 | AE54: 600 | AF54: 600 | AG54: 600 | AH54: 600 | AI54: 600 | AJ54: 600 | AK54: 600 | AL54: 600 | AM54: 600 | AN54: 600 | AO54: 600 | AP54: 700 | AQ54: 700 | AR54: 700 | AS54: 700 | AT54: 700 | AU54: 700 | AV54: 700 | AW54: 700 | AX54: 700 | AY54: 700 | AZ54: 700 | BA54: 700 | BB54: 700 | BC54: 700 | BD54: 700 | BE54: 700 | BF54: 700 | BG54: 700 | BH54: 700 | BI54: 700 | BJ54: 700 | BK54: 700 | BL54: 700 | BM54: 700 | BN54: 700 | BO54: 700 | BP54: 700 | BQ54: 700 | BR54: 700 | BS54: 700 | BT54: 700 | BU54: 700 | BV54: 700 | BW54: 700 | BX54: 700 | BY54: 700 | BZ54: 700 | CA54: 700 | CB54: 700 | CC54: 700 | CD54: 700 | CE54: 700 | CF54: 700 | CG54: 700 | CH54: 700 | CI54: 700 | CJ54: 700 | CK54: 700
B55: Insurance | F55: 1136.86 | G55: 1136.86 | H55: 563.51 | I55: 1777.77 | J55: -29182.89 | K55: -198482.74 | L55: 1517.26 | M55: 1517.26 | N55: 1919.09 | O55: 1115.43 | P55: 1517.26 | Q55: 1517.26 | R55: 1517.26 | S55: 1517.26 | T55: 3590.08 | U55: 1814.48 | V55: 401.86 | W55: 401.86 | X55: 401.86 | Y55: 401.86 | Z55: 401.86 | AA55: 401.86 | AB55: 401.86 | AC55: 401.86 | AD55: 401.86 | AE55: 401.86 | AF55: 1200 | AG55: 1200 | AH55: 1200 | AI55: 1200 | AJ55: 2000 | AK55: 2000 | AL55: 2000 | AM55: 2000 | AN55: 2000 | AO55: 2000 | AP55: 2200 | AQ55: 2200 | AR55: 2200 | AS55: 2200 | AT55: 2200 | AU55: 2200 | AV55: 2200 | AW55: 2200 | AX55: 2200 | AY55: 2200 | AZ55: 2200 | BA55: 2200 | BB55: 2200 | BC55: 2200 | BD55: 2200 | BE55: 2200 | BF55: 2200 | BG55: 2200 | BH55: 2200 | BI55: 2200 | BJ55: 2200 | BK55: 2200 | BL55: 2200 | BM55: 2200 | BN55: 2200 | BO55: 2200 | BP55: 2200 | BQ55: 2200 | BR55: 2200 | BS55: 2200 | BT55: 2200 | BU55: 2200 | BV55: 2200 | BW55: 2200 | BX55: 2200 | BY55: 2200 | BZ55: 2200 | CA55: 2200 | CB55: 2200 | CC55: 2200 | CD55: 2200 | CE55: 2200 | CF55: 2200 | CG55: 2200 | CH55: 2200 | CI55: 2200 | CJ55: 2200 | CK55: 2200
B56: Meals and Entertainment | F56: 0 | G56: 0 | H56: 225 | I56: 3460 | J56: 0 | K56: 0 | L56: 0 | M56: 0 | N56: 0 | O56: 0 | Y56: 0 | Z56: 146.88 | AA56: 146.88 | AB56: 146.88 | AC56: 146.88 | AD56: 146.88 | AE56: 146.88 | AF56: 750 | AG56: 750 | AH56: 750 | AI56: 5000 | AJ56: 750 | AK56: 750 | AL56: 750 | AM56: 750 | AN56: 750 | AO56: 10000 | AP56: 1000 | AQ56: 1000 | AR56: 1000 | AS56: 1000 | AT56: 1000 | AU56: 7000 | AV56: 1000 | AW56: 1000 | AX56: 1000 | AY56: 1000 | AZ56: 1000 | BA56: 12500 | BB56: 1000 | BC56: 1000 | BD56: 1000 | BE56: 1000 | BF56: 1000 | BG56: 7000 | BH56: 1000 | BI56: 1000 | BJ56: 1000 | BK56: 1000 | BL56: 1000 | BM56: 12500 | BN56: 1000 | BO56: 1000 | BP56: 1000 | BQ56: 1000 | BR56: 1000 | BS56: 7000 | BT56: 1000 | BU56: 1000 | BV56: 1000 | BW56: 1000 | BX56: 1000 | BY56: 12500 | BZ56: 1000 | CA56: 1000 | CB56: 1000 | CC56: 1000 | CD56: 1000 | CE56: 7000 | CF56: 1000 | CG56: 1000 | CH56: 1000 | CI56: 1000 | CJ56: 1000 | CK56: 12500
B57: Travel Expenses | F57: 0 | G57: 0 | H57: 0 | I57: 0 | J57: 282.78 | K57: 360.01 | L57: 0 | M57: 9822.31 | N57: 769.24 | O57: 769.24 | P57: 769.24 | Q57: 1153.86 | R57: 384.62 | S57: 0 | T57: 0 | U57: 0 | Y57: 0 | Z57: 0.43 | AA57: 0.43 | AB57: 0.43 | AC57: 0.43 | AD57: 0.43 | AE57: 0.43 | AF57: 3000 | AG57: 3000 | AH57: 3000 | AI57: 3000 | AJ57: 3000 | AK57: 3000 | AL57: 3000 | AM57: 3000 | AN57: 3000 | AO57: 3000 | AP57: 4000 | AQ57: 4000 | AR57: 4000 | AS57: 4000 | AT57: 4000 | AU57: 4000 | AV57: 4000 | AW57: 4000 | AX57: 4000 | AY57: 4000 | AZ57: 4000 | BA57: 4000 | BB57: 4000 | BC57: 4000 | BD57: 4000 | BE57: 4000 | BF57: 4000 | BG57: 4000 | BH57: 4000 | BI57: 4000 | BJ57: 4000 | BK57: 4000 | BL57: 4000 | BM57: 4000 | BN57: 4000 | BO57: 4000 | BP57: 4000 | BQ57: 4000 | BR57: 4000 | BS57: 4000 | BT57: 4000 | BU57: 4000 | BV57: 4000 | BW57: 4000 | BX57: 4000 | BY57: 4000 | BZ57: 4000 | CA57: 4000 | CB57: 4000 | CC57: 4000 | CD57: 4000 | CE57: 4000 | CF57: 4000 | CG57: 4000 | CH57: 4000 | CI57: 4000 | CJ57: 4000 | CK57: 4000
B58: Depreciation - (delivery box) | F58: 0 | G58: 0 | H58: 0 | I58: 0 | J58: 0 | K58: 0 | L58: 0 | M58: 0 | N58: 0 | O58: 26739.13 | U58: =U89/36 -> 0 | V58: =U58 -> 0 | W58: =V58 -> 0 | X58: =W58 -> 0 | Y58: 430.16 | Z58: =Y58 -> 430.16 | AA58: =Z58 -> 430.16 | AB58: =AA58 -> 430.16 | AC58: =AB58 -> 430.16 | AD58: =AC58 -> 430.16 | AE58: =AD58 -> 430.16 | AF58: =AE58 -> 430.16 | AG58: =AF58 -> 430.16 | ... CK58: =CJ58 -> 430.16
B59: Telecommunication | F59: 89.95 | G59: 89.95 | H59: 89.95 | I59: 89.95 | J59: 89.95 | K59: 89.95 | L59: 89.95 | M59: 89.95 | N59: 122.62 | O59: 73.95 | P59: 341.58 | Q59: 139.91 | R59: 79.96 | S59: 184.7 | T59: 79.96 | U59: 171.91 | V59: 92 | W59: 252 | X59: 92 | Y59: 171.91 | Z59: 159.92 | AA59: 159.92 | AB59: 159.92 | AC59: 159.92 | AD59: 159.92 | AE59: 159.92 | AF59: 350 | AG59: 350 | AH59: 350 | AI59: 350 | AJ59: 350 | AK59: 350 | AL59: 350 | AM59: 350 | AN59: 350 | AO59: 350 | AP59: 400 | AQ59: 400 | AR59: 400 | AS59: 400 | AT59: 400 | AU59: 400 | AV59: 400 | AW59: 400 | AX59: 400 | AY59: 400 | AZ59: 400 | BA59: 400 | BB59: 400 | BC59: 400 | BD59: 400 | BE59: 400 | BF59: 400 | BG59: 400 | BH59: 400 | BI59: 400 | BJ59: 400 | BK59: 400 | BL59: 400 | BM59: 400 | BN59: 400 | BO59: 400 | BP59: 400 | BQ59: 400 | BR59: 400 | BS59: 400 | BT59: 400 | BU59: 400 | BV59: 400 | BW59: 400 | BX59: 400 | BY59: 400 | BZ59: 400 | CA59: 400 | CB59: 400 | CC59: 400 | CD59: 400 | CE59: 400 | CF59: 400 | CG59: 400 | CH59: 400 | CI59: 400 | CJ59: 400 | CK59: 400
B60: License and Subscriptions | F60: 5929.37 | G60: 7248.04 | H60: 6920.16 | I60: 5969.14 | J60: 4363.07 | K60: 4342.28 | L60: 5749.74 | M60: 5043.74 | N60: 4577.25 | O60: 7442.18 | P60: =5477.58+3602.22 -> 9079.8 | Q60: =5412.68+900.59 -> 6313.27 | R60: 8762.52 | S60: 5158.04 | T60: 7727.19 | U60: 4816.22 | V60: 5409 | W60: 5098 | X60: 4606 | Y60: 7125.02 | Z60: 4327.9 | AA60: 4327.9 | AB60: 4327.9 | AC60: 4327.9 | AD60: 4327.9 | AE60: 4327.9 | AF60: 7500 | AG60: 7500 | AH60: 10000 | AI60: 10000 | AJ60: 10000 | AK60: 10000 | AL60: 10000 | AM60: 10000 | AN60: 10000 | AO60: 10000 | AP60: 12500 | AQ60: 12500 | AR60: 12500 | AS60: 12500 | AT60: 12500 | AU60: 12500 | AV60: 12500 | AW60: 12500 | AX60: 12500 | AY60: 12500 | AZ60: 12500 | BA60: 12500 | BB60: 12500 | BC60: 12500 | BD60: 12500 | BE60: 12500 | BF60: 12500 | BG60: 12500 | BH60: 12500 | BI60: 12500 | BJ60: 12500 | BK60: 12500 | BL60: 12500 | BM60: 12500 | BN60: 12500 | BO60: 12500 | BP60: 12500 | BQ60: 12500 | BR60: 12500 | BS60: 12500 | BT60: 12500 | BU60: 12500 | BV60: 12500 | BW60: 12500 | BX60: 12500 | BY60: 12500 | BZ60: 12500 | CA60: 12500 | CB60: 12500 | CC60: 12500 | CD60: 12500 | CE60: 12500 | CF60: 12500 | CG60: 12500 | CH60: 12500 | CI60: 12500 | CJ60: 12500 | CK60: 12500
B61: Repair and Maintenance | F61: 0 | G61: 1125 | H61: 900 | I61: 900 | J61: 900 | K61: 1125 | L61: 900 | M61: 1035 | N61: 2070 | O61: 0 | P61: 315 | Q61: 1190.01 | R61: 455 | S61: 340 | T61: 340 | U61: 340 | Y61: 0 | Z61: 0 | AA61: 0 | AB61: 0 | AC61: 0 | AD61: 0 | AE61: 0 | AF61: 1500 | AG61: 1500 | AH61: 1500 | AI61: 1500 | AJ61: 1500 | AK61: 1500 | AL61: 1500 | AM61: 1500 | AN61: 1500 | AO61: 1500 | AP61: 2000 | AQ61: 2000 | AR61: 2000 | AS61: 2000 | AT61: 2000 | AU61: 2000 | AV61: 2000 | AW61: 2000 | AX61: 2000 | AY61: 2000 | AZ61: 2000 | BA61: 2000 | BB61: 2000 | BC61: 2000 | BD61: 2000 | BE61: 2000 | BF61: 2000 | BG61: 2000 | BH61: 2000 | BI61: 2000 | BJ61: 2000 | BK61: 2000 | BL61: 2000 | BM61: 2000 | BN61: 2000 | BO61: 2000 | BP61: 2000 | BQ61: 2000 | BR61: 2000 | BS61: 2000 | BT61: 2000 | BU61: 2000 | BV61: 2000 | BW61: 2000 | BX61: 2000 | BY61: 2000 | BZ61: 2000 | CA61: 2000 | CB61: 2000 | CC61: 2000 | CD61: 2000 | CE61: 2000 | CF61: 2000 | CG61: 2000 | CH61: 2000 | CI61: 2000 | CJ61: 2000 | CK61: 2000
B62: Recruitment Charges | F62: 0 | G62: 0 | H62: 0 | I62: 103.79 | J62: 838.68 | K62: 226.71 | L62: 311.62 | M62: 984.05 | N62: 967.74 | O62: 294.14 | R62: 506.83 | S62: 206.94 | T62: 206.94 | U62: 0 | Y62: 268.74 | Z62: 222.64 | AA62: 222.64 | AB62: 222.64 | AC62: 222.64 | AD62: 222.64 | AE62: 222.64 | AF62: 2500 | AG62: 2500 | AH62: 2500 | AI62: 2500 | AJ62: 2500 | AK62: 2500 | AL62: 2500 | AM62: 2500 | AN62: 2500 | AO62: 2500 | AP62: 2500 | AQ62: 2500 | AR62: 2500 | AS62: 2500 | AT62: 2500 | AU62: 2500 | AV62: 2500 | AW62: 2500 | AX62: 2500 | AY62: 2500 | AZ62: 2500 | BA62: 2500 | BB62: 2500 | BC62: 2500 | BD62: 2500 | BE62: 2500 | BF62: 2500 | BG62: 2500 | BH62: 2500 | BI62: 2500 | BJ62: 2500 | BK62: 2500 | BL62: 2500 | BM62: 2500 | BN62: 2500 | BO62: 2500 | BP62: 2500 | BQ62: 2500 | BR62: 2500 | BS62: 2500 | BT62: 2500 | BU62: 2500 | BV62: 2500 | BW62: 2500 | BX62: 2500 | BY62: 2500 | BZ62: 2500 | CA62: 2500 | CB62: 2500 | CC62: 2500 | CD62: 2500 | CE62: 2500 | CF62: 2500 | CG62: 2500 | CH62: 2500 | CI62: 2500 | CJ62: 2500 | CK62: 2500
B63: Offices Expenses | F63: 3779.2 | G63: 1006.48 | H63: 720.84 | I63: 4210.31 | J63: 1693.41 | K63: 1449.16 | L63: 1811.64 | M63: 1047.89 | N63: 6486.74 | O63: 3543.39 | P63: 3372.02 | Q63: 2900.8 | R63: 1817.78 | S63: 1375.97 | T63: 1135.87 | U63: 3542.94 | V63: 949 | W63: 1252 | X63: 2374 | Y63: 1465.07 | Z63: 2050.75 | AA63: 2050.75 | AB63: 2050.75 | AC63: 2050.75 | AD63: 2050.75 | AE63: 2050.75 | AF63: 3500 | AG63: 3500 | AH63: 3500 | AI63: 3500 | AJ63: 3500 | AK63: 3500 | AL63: 3500 | AM63: 3500 | AN63: 3500 | AO63: 3500 | AP63: 5000 | AQ63: 5000 | AR63: 5000 | AS63: 5000 | AT63: 5000 | AU63: 5000 | AV63: 5000 | AW63: 5000 | AX63: 5000 | AY63: 5000 | AZ63: 5000 | BA63: 5000 | BB63: 5000 | BC63: 5000 | BD63: 5000 | BE63: 5000 | BF63: 5000 | BG63: 5000 | BH63: 5000 | BI63: 5000 | BJ63: 5000 | BK63: 5000 | BL63: 5000 | BM63: 5000 | BN63: 5000 | BO63: 5000 | BP63: 5000 | BQ63: 5000 | BR63: 5000 | BS63: 5000 | BT63: 5000 | BU63: 5000 | BV63: 5000 | BW63: 5000 | BX63: 5000 | BY63: 5000 | BZ63: 5000 | CA63: 5000 | CB63: 5000 | CC63: 5000 | CD63: 5000 | CE63: 5000 | CF63: 5000 | CG63: 5000 | CH63: 5000 | CI63: 5000 | CJ63: 5000 | CK63: 5000
B64: Taxes, Permit | F64: 393.9 | G64: 0 | H64: 0 | I64: 0 | J64: 0 | K64: 393.9 | L64: 0 | M64: 0 | N64: 0 | O64: 0 | R64: 393.9 | S64: 0 | T64: 0 | U64: 834.11 | V64: 0 | W64: 1052 | X64: 0 | Y64: 65 | Z64: 0 | AA64: 0 | AB64: 0 | AC64: 0 | AD64: 0 | AE64: 0 | AF64: 500 | AG64: 500 | AH64: 500 | AI64: 500 | AJ64: 500 | AK64: 500 | AL64: 500 | AM64: 500 | AN64: 500 | AO64: 500 | AP64: 750 | AQ64: 750 | AR64: 750 | AS64: 750 | AT64: 750 | AU64: 750 | AV64: 750 | AW64: 750 | AX64: 750 | AY64: 750 | AZ64: 750 | BA64: 750 | BB64: 750 | BC64: 750 | BD64: 750 | BE64: 750 | BF64: 750 | BG64: 750 | BH64: 750 | BI64: 750 | BJ64: 750 | BK64: 750 | BL64: 750 | BM64: 750 | BN64: 750 | BO64: 750 | BP64: 750 | BQ64: 750 | BR64: 750 | BS64: 750 | BT64: 750 | BU64: 750 | BV64: 750 | BW64: 750 | BX64: 750 | BY64: 750 | BZ64: 750 | CA64: 750 | CB64: 750 | CC64: 750 | CD64: 750 | CE64: 750 | CF64: 750 | CG64: 750 | CH64: 750 | CI64: 750 | CJ64: 750 | CK64: 750
B65: Interest and bank charges | F65: 372.82 | G65: 219.36 | H65: 341.01 | I65: 1117.72 | J65: 1006.03 | K65: 486.22 | L65: 778.79 | M65: 2139.61 | N65: 1329.3 | O65: 1480.39 | P65: 991.17 | Q65: 1878.27 | R65: 2049.55 | S65: 540.48 | T65: 1857.55 | U65: 2223.86 | V65: 2741 | W65: 2091 | X65: 2139 | Y65: 2264.53 | Z65: 2228.74 | AA65: 2228.74 | AB65: 2228.74 | AC65: 2228.74 | AD65: 2228.74 | AE65: 2228.74 | AF65: 1000 | AG65: 1000 | AH65: 1000 | AI65: 1000 | AJ65: 1000 | AK65: 1000 | AL65: 1000 | AM65: 1000 | AN65: 1000 | AO65: 1000 | AP65: 1200 | AQ65: 1200 | AR65: 1200 | AS65: 1200 | AT65: 1200 | AU65: 1200 | AV65: 1200 | AW65: 1200 | AX65: 1200 | AY65: 1200 | AZ65: 1200 | BA65: 1200 | BB65: 1200 | BC65: 1200 | BD65: 1200 | BE65: 1200 | BF65: 1200 | BG65: 1200 | BH65: 1200 | BI65: 1200 | BJ65: 1200 | BK65: 1200 | BL65: 1200 | BM65: 1200 | BN65: 1200 | BO65: 1200 | BP65: 1200 | BQ65: 1200 | BR65: 1200 | BS65: 1200 | BT65: 1200 | BU65: 1200 | BV65: 1200 | BW65: 1200 | BX65: 1200 | BY65: 1200 | BZ65: 1200 | CA65: 1200 | CB65: 1200 | CC65: 1200 | CD65: 1200 | CE65: 1200 | CF65: 1200 | CG65: 1200 | CH65: 1200 | CI65: 1200 | CJ65: 1200 | CK65: 1200
B66: Shipping | F66: 0 | G66: 0 | H66: 0 | I66: 0 | J66: 0 | K66: 0 | L66: 0 | M66: 0 | N66: 0 | O66: 0 | R66: 500 | S66: 500 | T66: 500 | U66: 0 | V66: 281 | W66: 631 | X66: -17 | Y66: 0 | Z66: 350.49 | AA66: 350.49 | AB66: 350.49 | AC66: 350.49 | AD66: 350.49 | AE66: 350.49 | AF66: 500 | AG66: 500 | AH66: 500 | AI66: 500 | AJ66: 500 | AK66: 500 | AL66: 500 | AM66: 500 | AN66: 500 | AO66: 500 | AP66: 500 | AQ66: 500 | AR66: 500 | AS66: 500 | AT66: 500 | AU66: 500 | AV66: 500 | AW66: 500 | AX66: 500 | AY66: 500 | AZ66: 500 | BA66: 500 | BB66: 500 | BC66: 500 | BD66: 500 | BE66: 500 | BF66: 500 | BG66: 500 | BH66: 500 | BI66: 500 | BJ66: 500 | BK66: 500 | BL66: 500 | BM66: 500 | BN66: 500 | BO66: 500 | BP66: 500 | BQ66: 500 | BR66: 500 | BS66: 500 | BT66: 500 | BU66: 500 | BV66: 500 | BW66: 500 | BX66: 500 | BY66: 500 | BZ66: 500 | CA66: 500 | CB66: 500 | CC66: 500 | CD66: 500 | CE66: 500 | CF66: 500 | CG66: 500 | CH66: 500 | CI66: 500 | CJ66: 500 | CK66: 500
B67: Exchange Gain or Loss | F67: 0.94 | G67: -0.41 | H67: 5.26 | I67: 0 | J67: 0 | K67: 0 | L67: 0 | M67: 0 | N67: 0 | O67: 0 | U67: 14.01 | Y67: 1.43 | Z67: 123.24 | AA67: 123.24 | AB67: 123.24 | AC67: 123.24 | AD67: 123.24 | AE67: 123.24
B68: Loans Interests | F68: 2664.21 | G68: 2617.11 | H68: 2399.77 | I68: 2507.17 | J68: 2489.94 | K68: 2893.64 | L68: 1759.84 | M68: 4027.01 | N68: 2741.86 | O68: 2814.59 | P68: =2750.34 -> 2750.34 | Q68: 2654.32 | R68: 2716.08 | S68: 2684.78 | T68: 2553.1 | U68: 2678.82 | V68: 2801.82 | W68: 3237.25 | X68: 1386.5 | Y68: 2508.66 | Z68: 2573.23 | AA68: 2573.23 | AB68: 2573.23 | AC68: 2573.23 | AD68: 2573.23 | AE68: 2573.23 | AF68: =-'Loans & Grants'!AG29 -> 2644.55 | AG68: =-'Loans & Grants'!AH29 -> 2567.85 | AH68: =-'Loans & Grants'!AI29 -> 2491.15 | AI68: =-'Loans & Grants'!AJ29 -> 2414.45 | AJ68: =-'Loans & Grants'!AK29 -> 2337.75 | AK68: =-'Loans & Grants'!AL29 -> 2261.05 | AL68: =-'Loans & Grants'!AM29 -> 2184.35 | AM68: =-'Loans & Grants'!AN29 -> 2107.65 | ... CK68: =-'Loans & Grants'!CL29 -> 0
B70: Tech & Marketing (Content&Advertising) | F70: 26348.95 | G70: 9027.58 | H70: 11044.43 | I70: 8226.14 | J70: 7905.56 | K70: 8613.13 | L70: 9210.07 | M70: 8864.3 | N70: 6201.45 | O70: 7632.06 | P70: =2727+5270.86 -> 7997.86 | Q70: =1074+4602.84 -> 5676.84 | R70: =1218+4752.33 -> 5970.33 | S70: =1868.57+1299 -> 3167.57 | T70: =815.81+1371 -> 2186.81 | U70: 404.69 | V70: 1527 | W70: 1722 | X70: 1824 | Y70: =1810.81+1950 -> 3760.81 | Z70: =1126.12+7650 -> 8776.12 | AA70: =1126.12+7650 -> 8776.12 | AB70: =1126.12+7650 -> 8776.12 | AC70: =1126.12+7650 -> 8776.12 | AD70: =1126.12+7650 -> 8776.12 | AE70: =1126.12+7650 -> 8776.12 | AF70: ='Marketing and Sales'!AF9 -> 10663.612 | AG70: ='Marketing and Sales'!AG9 -> 47480.233 | AH70: ='Marketing and Sales'!AH9 -> 49008.946 | AI70: ='Marketing and Sales'!AI9 -> 50847.173 | AJ70: ='Marketing and Sales'!AJ9 -> 52981.334 | AK70: ='Marketing and Sales'!AK9 -> 55525.891 | AL70: ='Marketing and Sales'!AL9 -> 59435.57 | AM70: ='Marketing and Sales'!AM9 -> 63743.696 | ... CK70: ='Marketing and Sales'!CK9 -> 728771.6
B71: Trade and Events | R71: 4900 | S71: ='Marketing and Sales'!S29 -> 0 | T71: ='Marketing and Sales'!T29 -> 0 | U71: 1419 | V71: ='Marketing and Sales'!V29 -> 0 | W71: ='Marketing and Sales'!W29 -> 0 | X71: ='Marketing and Sales'!X29 -> 0 | Y71: ='Marketing and Sales'!Y29 -> 0 | Z71: 333.7 | AA71: 333.7 | AB71: 333.7 | AC71: 333.7 | AD71: 333.7 | AE71: 333.7 | AF71: ='Marketing and Sales'!AF29 -> 0 | AG71: ='Marketing and Sales'!AG29 -> 0 | AH71: ='Marketing and Sales'!AH29 -> 5000 | AI71: ='Marketing and Sales'!AI29 -> 5000 | AJ71: ='Marketing and Sales'!AJ29 -> 5000 | AK71: ='Marketing and Sales'!AK29 -> 5000 | AL71: ='Marketing and Sales'!AL29 -> 5000 | AM71: ='Marketing and Sales'!AM29 -> 5000 | ... CK71: ='Marketing and Sales'!CK29 -> 7500
B73: TOTAL OPERATIONS EXPENSES | F73: =F51+SUM(F53:F71)+F31 -> 111920.49 | G73: =G51+SUM(G53:G71)+G31 -> 121765.45 | H73: =H51+SUM(H53:H71)+H31 -> 124646.86 | I73: =I51+SUM(I53:I71)+I31 -> 98335.44 | J73: =J51+SUM(J53:J71)+J31 -> 58000 | K73: =K51+SUM(K53:K71)+K31 -> -103990.24 | L73: =L51+SUM(L53:L71)+L31 -> 134877.59 | M73: =M51+SUM(M53:M71)+M31 -> 94119.25 | ... Q73: =Q51+SUM(Q53:Q71)+Q31 -> 201425.86 | R73: =R51+SUM(R53:R71) -> 180888.91 | S73: =S51+SUM(S53:S71) -> 194627.51 | T73: =T51+SUM(T53:T71) -> 240663.83 | U73: 193988.57 | V73: 159244.96 | W73: 158858.36 | X73: 127263.09 | Y73: 157896.54 | Z73: 147095.41 | AA73: =AA51+SUM(AA53:AA71) -> 134640.69 | AB73: =AB51+SUM(AB53:AB71) -> 134640.69 | AC73: =AC51+SUM(AC53:AC71) -> 134640.69 | AD73: =AD51+SUM(AD53:AD71) -> 119074.73 | AE73: =AE51+SUM(AE53:AE71) -> 99674.73 | AF73: =AF51+SUM(AF53:AF71) -> 118445.39 | AG73: =AG51+SUM(AG53:AG71) -> 264191.58 | AH73: =AH51+SUM(AH53:AH71) -> 273543.59 | ... CK73: =CK51+SUM(CK53:CK71) -> 1132158.2
B75: P&L (Before Taxes Credits) | F75: =F24-F73 -> -111920.49 | G75: =G24-G73 -> -121765.45 | H75: =H24-H73 -> -124646.86 | I75: =I24-I73 -> -98335.44 | J75: =J24-J73 -> -58000 | K75: =K24-K73 -> 103990.24 | L75: =L24-L73 -> -134877.59 | M75: =M24-M73 -> -94119.25 | ... CK75: =CK24-CK73 -> 1863866
B76: CUMULATIVE P&L (Before Taxes Credit) | P76: =P75 -> -126318.78 | Q76: =P76+Q75 -> -258486.49 | R76: =Q76+R75 -> -369047.08 | S76: =R76+S75 -> -494853.59 | T76: =S76+T75 -> -667683.42 | U76: =T76+U75 -> -788434.99 | V76: =U76+V75 -> -876416.11 | W76: =V76+W75 -> -965670.44 | X76: =W76+X75 -> -1015251.1 | ... CK76: =CJ76+CK75 -> 28811501
B77: P&L + Grants (without SRED and CDAE) | P77: =P75+('Loans & Grants'!Q50-'Loans & Grants'!Q41-'Loans & Grants'!Q42) -> -21318.785 | Q77: =Q75+('Loans & Grants'!R50-'Loans & Grants'!R41-'Loans & Grants'!R42) -> -132167.71 | R77: =R75+('Loans & Grants'!S50-'Loans & Grants'!S41-'Loans & Grants'!S42) -> -110560.59 | S77: =S75+('Loans & Grants'!T50-'Loans & Grants'!T41-'Loans & Grants'!T42) -> -125806.51 | T77: =T75+('Loans & Grants'!U50-'Loans & Grants'!U41-'Loans & Grants'!U42) -> -172829.83 | U77: =U75+('Loans & Grants'!V50-'Loans & Grants'!V41-'Loans & Grants'!V42) -> -120751.57 | V77: =V75+('Loans & Grants'!W50-'Loans & Grants'!W41-'Loans & Grants'!W42) -> -87981.12 | W77: =W75+('Loans & Grants'!X50-'Loans & Grants'!X41-'Loans & Grants'!X42) -> -89254.33 | ... CK77: =CK75+('Loans & Grants'!CL50-'Loans & Grants'!CL41-'Loans & Grants'!CL42) -> 1863866
B79: CASHFLOW | R79: 2023 | AD79: 2024 | AP79: 2025 | BB79: 2026 | BN79: 2027 | BZ79: 2028
P80: 44866 | Q80: 44896 | R80: 44927 | S80: 44958 | T80: 44986 | U80: 45017 | V80: 45047 | W80: 45078 | X80: 45108 | Y80: 45139 | Z80: 45170 | AA80: 45200 | AB80: 45231 | AC80: 45261 | AD80: 45292 | AE80: 45323 | AF80: 45352 | AG80: 45383 | AH80: 45413 | AI80: 45444 | AJ80: 45474 | AK80: 45505 | AL80: 45536 | AM80: 45566 | AN80: 45597 | AO80: 45627 | AP80: 45658 | AQ80: 45689 | AR80: 45717 | AS80: 45748 | AT80: 45778 | AU80: 45809 | AV80: 45839 | AW80: 45870 | AX80: 45901 | AY80: 45931 | AZ80: 45962 | BA80: 45992 | BB80: 45658 | BC80: 45689 | BD80: 45717 | BE80: 45748 | BF80: 45778 | BG80: 45809 | BH80: 45839 | BI80: 45870 | BJ80: 45901 | BK80: 45931 | BL80: 45962 | BM80: 45992 | BN80: 45658 | BO80: 45689 | BP80: 45717 | BQ80: 45748 | BR80: 45778 | BS80: 45809 | BT80: 45839 | BU80: 45870 | BV80: 45901 | BW80: 45931 | BX80: 45962 | BY80: 45992 | BZ80: 45658 | CA80: 45689 | CB80: 45717 | CC80: 45748 | CD80: 45778 | CE80: 45809 | CF80: 45839 | CG80: 45870 | CH80: 45901 | CI80: 45931 | CJ80: 45962 | CK80: 45992
B82: CASH Beginning of Month | P82: 0 | Q82: =P108 -> 21427.07 | R82: 0 | S82: =R108 -> 38111.09 | T82: =S108 -> 48035.766 | U82: =T108 -> 103294.02 | V82: =U108 -> 71081.927 | W82: =V108 -> 56581.609 | X82: =W108 -> 131101.96 | Y82: =X108 -> 70056.483 | Z82: =Y108 -> 55320.648 | ... CK82: =CJ108 -> 33232997
B84: Profit or Lost | F84: =F75 -> -111920.49 | G84: =G75 -> -121765.45 | H84: =H75 -> -124646.86 | I84: =I75 -> -98335.44 | J84: =J75 -> -58000 | K84: =K75 -> 103990.24 | L84: =L75 -> -134877.59 | M84: =M75 -> -94119.25 | ... CK84: =CK75 -> 1863866
B85: Invoiced but not received from PSB | P85: =IF('PSB-P&L '!P78<0,-'PSB-P&L '!P74,0) -> -67254.145 | Q85: =IF('PSB-P&L '!Q78<0,-'PSB-P&L '!Q74,0) -> -69258.154 | R85: =IF('PSB-P&L '!R78<0,-'PSB-P&L '!R74,0) -> -70328.32 | S85: =IF('PSB-P&L '!S78<0,-'PSB-P&L '!S74,0) -> -69268.814 | T85: =IF('PSB-P&L '!T78<0,-'PSB-P&L '!T74,0) -> -68791.918 | U85: =IF('PSB-P&L '!U78<0,-'PSB-P&L '!U74,0) -> -68340.521 | V85: =IF('PSB-P&L '!V78<0,-'PSB-P&L '!V74,0) -> -68246.948 | W85: =IF('PSB-P&L '!W78<0,-'PSB-P&L '!W74,0) -> -68161.064 | ... CK85: =IF('PSB-P&L '!CK78<0,-'PSB-P&L '!CK74,0) -> 0
B86: PSB Payment of Interco Partial | R86: =-'PSB-P&L '!R91 -> 0 | S86: =-'PSB-P&L '!S91 -> 0 | T86: =-'PSB-P&L '!T91 -> 0 | U86: 10000 | V86: 50000 | W86: 0 | X86: -75000 | Y86: 0 | Z86: 25000 | AA86: 25000 | AB86: 35000 | AC86: =-'PSB-P&L '!AC91 -> 50000 | AD86: =-'PSB-P&L '!AD91 -> 0 | AE86: =-'PSB-P&L '!AE91 -> 0 | AF86: =-'PSB-P&L '!AF91 -> 0 | AG86: =-'PSB-P&L '!AG91 -> 0 | AH86: =-'PSB-P&L '!AH91 -> 0 | AI86: =-'PSB-P&L '!AI91 -> 0 | AJ86: =-'PSB-P&L '!AJ91 -> 0 | ... CK86: =-'PSB-P&L '!CK91 -> 0
B87: PSB Payment of Interco Balance | P87: =IF('PSB-P&L '!P78>0,'PSB-P&L '!P78,0) -> 0 | Q87: =IF('PSB-P&L '!Q78>0,'PSB-P&L '!Q78,0) -> 0 | R87: =IF('PSB-P&L '!R78>0,'PSB-P&L '!R78,0) -> 0 | S87: =IF('PSB-P&L '!S78>0,'PSB-P&L '!S78,0) -> 0 | T87: =IF('PSB-P&L '!T78>0,'PSB-P&L '!T78,0) -> 0 | U87: =IF('PSB-P&L '!U78>0,'PSB-P&L '!U78,0) -> 0 | V87: =IF('PSB-P&L '!V78>0,'PSB-P&L '!V78,0) -> 0 | W87: =IF('PSB-P&L '!W78>0,'PSB-P&L '!W78,0) -> 0 | ... AY87: =IF('PSB-P&L '!AY78>0,'PSB-P&L '!AY78,0) -> 277896.74 | AZ87: 111000
B89: Delivery Box CT purchase
B91: Financing Round | AG91: 1750000
B92: Investissement Quebec | AG92: 750000
B93: BNC (Inventory Loan) | Z93: 300000
B94: JEAN COUTU | AF94: 300000
B95: Warrants
B96: Loans Received
B97: Loans Capital Reimbursement | P97: ='Loans & Grants'!Q28 -> 0 | Q97: ='Loans & Grants'!R28 -> 0 | R97: ='Loans & Grants'!S28 -> 0 | S97: ='Loans & Grants'!T28 -> 0 | T97: ='Loans & Grants'!U28+'Loans & Grants'!U29 -> -3120 | U97: ='Loans & Grants'!V28+'Loans & Grants'!V29 -> -3120 | V97: ='Loans & Grants'!W28+'Loans & Grants'!W29 -> -8272.25 | W97: ='Loans & Grants'!X28+'Loans & Grants'!X29 -> -8233.25 | X97: ='Loans & Grants'!Y28+'Loans & Grants'!Y29 -> -8194.25 | Y97: ='Loans & Grants'!Z28+'Loans & Grants'!Z29 -> -8155.25 | Z97: ='Loans & Grants'!AA28+'Loans & Grants'!AA29 -> -8116.25 | AA97: ='Loans & Grants'!AB28+'Loans & Grants'!AB29 -> -8077.25 | ... CK97: ='Loans & Grants'!CL28+'Loans & Grants'!CL29 -> 0
B98: Grants / Tax Credits | P98: ='Loans & Grants'!Q50 -> 105000 | Q98: ='Loans & Grants'!R50 -> 0 | R98: ='Loans & Grants'!S50 -> 37000 | T98: ='Loans & Grants'!U50 -> 0 | U98: ='Loans & Grants'!V50 -> 0 | V98: ='Loans & Grants'!W50 -> 0 | W98: ='Loans & Grants'!X50 -> 70169 | X98: ='Loans & Grants'!Y50 -> 0 | Y98: ='Loans & Grants'!Z50 -> 0 | Z98: 15000 | AA98: ='Loans & Grants'!AB50 -> 0 | AB98: ='Loans & Grants'!AC50 -> 0 | AC98: ='Loans & Grants'!AD50 -> 0 | AD98: ='Loans & Grants'!AE50 -> 0 | AE98: ='Loans & Grants'!AF50 -> 0 | AF98: ='Loans & Grants'!AG50 -> 45000 | AG98: ='Loans & Grants'!AH50 -> 185033.19 | AH98: ='Loans & Grants'!AI50 -> 0 | ... CK98: ='Loans & Grants'!CL50 -> 0
B100: Previous months payable Financing Delay | D100: =SUM(P100:AC100) -> 375000 | P100: 50000 | Q100: 0 | R100: 100000 | S100: 125000 | T100: =150000-150000 -> 0 | U100: 50000 | V100: 0 | X100: 50000 | Y100: 0 | AA100: 0 | AB100: 0
B101: Payables in arrears
B102: - TG Consulting (salaires non payés) | D102: =SUM(P102:AD102) -> -25000 | Z102: -25000 | AF102: -25000 | AH102: -125000
B103: - Others | D103: =SUM(P103:AD103) -> -75000 | Z103: -75000 | AH103: -175000
B104: Bridge Loans by Sonia Boutin/Marc Airoldi | D104: =SUM(P104:AH104) -> 1672000 | P104: 60000 | Q104: =90000 -> 90000 | R104: =50000+32000 -> 82000 | S104: 80000 | T104: 300000 | U104: 100000 | V104: 100000 | W104: 170000 | X104: 90000 | Y104: 150000 | Z104: 50000 | AB104: 50000 | AC104: 100000 | AD104: 100000 | AE104: 100000 | AF104: 50000
B105: Remboursement Avances de Sonia Boutin | AG105: -250000 | AM105: -250000 | AS105: -250000 | BD105: -500000 | BP105: -500000
B106: Credit Margin payback | AG106: -200000
B108: Cash End of Month | P108: =SUM(P82:P107) -> 21427.07 | Q108: =SUM(Q82:Q107) -> -89998.79 | R108: =SUM(R82:R107) -> 38111.09 | S108: =SUM(S82:S107) -> 48035.766 | T108: =SUM(T82:T107) -> 103294.02 | U108: =SUM(U82:U107) -> 71081.927 | V108: =SUM(V82:V107) -> 56581.609 | W108: =SUM(W82:W107) -> 131101.96 | ... CK108: =SUM(CK82:CK107) -> 35096863
B111: PSB Owed to Medzy Balance | Q111: 1752759 | R111: =+Q111-R85-R87-R86 -> 1823087.3 | S111: =+R111-S85-S87-S86 -> 1892356.1 | T111: =+S111-T85-T87-T86 -> 1961148.1 | U111: =+T111-U85-U87-U86 -> 2019488.6 | V111: =+U111-V85-V87-V86 -> 2037735.5 | W111: =+V111-W85-W87-W86 -> 2105896.6 | X111: =+W111-X85-X87-X86 -> 2249167.1 | Y111: =+X111-Y85-Y87-Y86 -> 2317723.1 | ... CK111: =+CJ111-CK85-CK87-CK86 -> 1114186
B115: KPIs | R115: 2023 | AD115: 2024 | AP115: 2025 | BB115: 2026 | BN115: 2027 | BZ115: 2028
P116: 44866 | Q116: 44896 | R116: 44927 | S116: 44958 | T116: 44986 | U116: 45017 | V116: 45047 | W116: 45078 | X116: 45108 | Y116: 45139 | Z116: 45170 | AA116: 45200 | AB116: 45231 | AC116: 45261 | AD116: 45292 | AE116: 45323 | AF116: 45352 | AG116: 45383 | AH116: 45413 | AI116: 45444 | AJ116: 45474 | AK116: 45505 | AL116: 45536 | AM116: 45566 | AN116: 45597 | AO116: 45627 | AP116: 45658 | AQ116: 45689 | AR116: 45717 | AS116: 45748 | AT116: 45778 | AU116: 45809 | AV116: 45839 | AW116: 45870 | AX116: 45901 | AY116: 45931 | AZ116: 45962 | BA116: 45992 | BB116: 45658 | BC116: 45689 | BD116: 45717 | BE116: 45748 | BF116: 45778 | BG116: 45809 | BH116: 45839 | BI116: 45870 | BJ116: 45901 | BK116: 45931 | BL116: 45962 | BM116: 45992 | BN116: 45658 | BO116: 45689 | BP116: 45717 | BQ116: 45748 | BR116: 45778 | BS116: 45809 | BT116: 45839 | BU116: 45870 | BV116: 45901 | BW116: 45931 | BX116: 45962 | BY116: 45992 | BZ116: 45658 | CA116: 45689 | CB116: 45717 | CC116: 45748 | CD116: 45778 | CE116: 45809 | CF116: 45839 | CG116: 45870 | CH116: 45901 | CI116: 45931 | CJ116: 45962 | CK116: 45992
B118: Salaries / Revenues
B119: IT | P119: =P34/P$24 -> 1.1436086 | Q119: =Q34/Q$24 -> 1.1631159 | R119: =R34/R$24 -> 1.1277663 | S119: =S34/S24 -> 1.3361959 | T119: =T34/T24 -> 2.020461 | U119: =U34/U24 -> 1.422171 | V119: =V34/V24 -> 1.3124962 | W119: =W34/W24 -> 1.4104801 | X119: =X34/X24 -> 1.0384281 | Y119: =Y34/Y24 -> 1.4732717 | Z119: =Z34/Z24 -> 1.3022267 | ... CK119: =CK34/CK24 -> 0.041505005
B120: Sales / Marketing | P120: =P35/P$24 -> 0 | Q120: =Q35/Q$24 -> 0 | R120: =R35/R$24 -> 0 | S120: =S35/S$24 -> 0 | T120: =T35/T$24 -> 0 | U120: =U35/U$24 -> 0.54083414 | V120: =V35/V$24 -> 0.31253578 | W120: =W35/W$24 -> 0.19337961 | ... CK120: =CK35/CK$24 -> 0.030253718
B121: Operations | P121: =P36/P$24 -> 0.11258786 | Q121: =Q36/Q$24 -> 0.099988226 | R121: =R36/R$24 -> 0.20191013 | S121: =S36/S$24 -> 0.039232211 | T121: =T36/T$24 -> 0.083291565 | U121: =U36/U$24 -> 0.39051299 | V121: =V36/V$24 -> 0.24946733 | W121: =W36/W$24 -> 0.30503981 | ... CK121: =CK36/CK$24 -> 0.025380859
B122: Sub total | P122: =P37/P$24 -> 1.2561965 | Q122: =Q37/Q$24 -> 1.2631041 | R122: =R37/R$24 -> 1.3296764 | S122: =S37/S$24 -> 1.3754281 | T122: =T37/T$24 -> 2.1037525 | U122: =U37/U$24 -> 2.3535182 | V122: =V37/V$24 -> 1.8744993 | W122: =W37/W$24 -> 1.9088995 | ... CK122: =CK37/CK$24 -> 0.097139583
B124: Fringes + Bonus | P124: =P39/P$24 -> 0 | Q124: =Q39/Q$24 -> 0 | R124: =R39/R$24 -> 0 | S124: =S39/S$24 -> 0 | T124: =T39/T$24 -> 0 | U124: =U39/U$24 -> 0 | V124: =V39/V$24 -> 0 | W124: =W39/W$24 -> 0 | ... CK124: =CK39/CK$24 -> 0.01165675
B126: Contractuals
P127: =P41/P$24 -> 0 | Q127: =Q41/Q$24 -> 0 | R127: =R41/R$24 -> 0 | S127: =S41/S$24 -> 0.046032461 | T127: =T41/T$24 -> 0.077837073 | U127: =U41/U$24 -> 0 | V127: =V41/V$24 -> 0 | W127: =W41/W$24 -> 0 | ... CK127: =CK41/CK$24 -> 0
B128: Professionals
B129: Accounting Fees | P129: =P45/P$24 -> 0.14283134 | Q129: =Q45/Q$24 -> 0.084798679 | R129: =R45/R$24 -> 0.067632783 | S129: =S45/S$24 -> 0.026372764 | T129: =T45/T$24 -> 0.018427337 | U129: =U45/U$24 -> 0 | V129: =V45/V$24 -> 0 | W129: =W45/W$24 -> 0 | ... CK129: =CK45/CK$24 -> 0.00058410743
B130: Legal Fees | P130: =P46/P$24 -> 0.13105601 | Q130: =Q46/Q$24 -> 0.0072712016 | R130: =R46/R$24 -> 0 | S130: =S46/S$24 -> 0 | T130: =T46/T$24 -> 0 | U130: =U46/U$24 -> 0.022488633 | V130: =V46/V$24 -> 0.039304646 | W130: =W46/W$24 -> 0.046505928 | ... CK130: =CK46/CK$24 -> 0.0016688784
B131: Other | P131: =P47/P$24 -> 0 | Q131: =Q47/Q$24 -> 0 | R131: =R47/R$24 -> 0.063370773 | S131: =S47/S$24 -> 0.11491245 | T131: =T47/T$24 -> 0.2465762 | U131: =U47/U$24 -> 0 | V131: =V47/V$24 -> 0.037283986 | W131: =W47/W$24 -> 0.014611223 | ... CK131: =CK47/CK$24 -> 0.004172196
B134: Total Operations Expenses / Revenus | P134: =P73/P24 -> 2.8782305 | Q134: =Q73/Q24 -> 2.9083342 | R134: =R73/R24 -> 2.5720636 | S134: =S73/S24 -> 2.828025 | T134: =T73/T24 -> 3.5478349 | U134: =U73/U24 -> 2.6487782 | V134: =V73/V24 -> 2.2345829 | W134: =W73/W24 -> 2.2823155 | ... CK134: =CK73/CK24 -> 0.37788687
B135: Marketing (Partners, Content&Advertising) / Revenus | P135: =P70/P24 -> 0.11891996 | Q135: =Q70/Q24 -> 0.081966377 | R135: =R70/R24 -> 0.08489226 | S135: =S70/S24 -> 0.046026213 | T135: =T70/T24 -> 0.032237668 | U135: =U70/U24 -> 0.0055257588 | V135: =V70/V24 -> 0.021427417 | W135: =W70/W24 -> 0.024739947 | ... CK135: =CK70/CK24 -> 0.24324623

Sheet Salaries & Contractuals
B2: Annual Raise | C2: 0.05
B4: SALARIES | G4: 2022 | S4: 2023 | AE4: 2024 | AQ4: 2025 | BC4: 2026 | BO4: 2027 | CA4: 2027
G5: 44562 | H5: 44593 | I5: 44621 | J5: 44652 | K5: 44682 | L5: 44713 | M5: 44743 | N5: 44774 | O5: 44805 | P5: 44835 | Q5: 44866 | R5: 44896 | S5: 44927 | T5: 44958 | U5: 44986 | V5: 45017 | W5: 45047 | X5: 45078 | Y5: 45108 | Z5: 45139 | AA5: 45170 | AB5: 45200 | AC5: 45231 | AD5: 45261 | AE5: 45292 | AF5: 45323 | AG5: 45352 | AH5: 45383 | AI5: 45413 | AJ5: 45444 | AK5: 45474 | AL5: 45505 | AM5: 45536 | AN5: 45566 | AO5: 45597 | AP5: 45627 | AQ5: 45658 | AR5: 45689 | AS5: 45717 | AT5: 45748 | AU5: 45778 | AV5: 45809 | AW5: 45839 | AX5: 45870 | AY5: 45901 | AZ5: 45931 | BA5: 45962 | BB5: 45992 | BC5: 45658 | BD5: 45689 | BE5: 45717 | BF5: 45748 | BG5: 45778 | BH5: 45809 | BI5: 45839 | BJ5: 45870 | BK5: 45901 | BL5: 45931 | BM5: 45962 | BN5: 45992 | BO5: 45658 | BP5: 45689 | BQ5: 45717 | BR5: 45748 | BS5: 45778 | BT5: 45809 | BU5: 45839 | BV5: 45870 | BW5: 45901 | BX5: 45931 | BY5: 45962 | BZ5: 45992 | CA5: 45658 | CB5: 45689 | CC5: 45717 | CD5: 45748 | CE5: 45778 | CF5: 45809 | CG5: 45839 | CH5: 45870 | CI5: 45901 | CJ5: 45931 | CK5: 45962 | CL5: 45992
B6: Role | C6: Employee | D6: Annual Compensation
B8: IT
B10: CTO | C10: Mathieu | D10: 175000 | O10: =$D10/12 -> 14583.333 | P10: =$D10/12 -> 14583.333 | Q10: =$D10/12 -> 14583.333 | R10: =$D10/12 -> 14583.333 | S10: =($D10/12)*(1+$C$2) -> 15312.5 | T10: =($D10/12)*(1+$C$2) -> 15312.5 | U10: =($D10/12)*(1+$C$2) -> 15312.5 | V10: =($D10/12)*(1+$C$2) -> 15312.5 | W10: =($D10/12)*(1+$C$2) -> 15312.5 | X10: =($D10/12)*(1+$C$2) -> 15312.5 | Y10: =($D10/12)*(1+$C$2) -> 15312.5 | Z10: =($D10/12)*(1+$C$2) -> 15312.5 | ... AD10: =($D10/12)*(1+$C$2) -> 15312.5 | AE10: =($D10/12)*(1+$C$2+$C$2) -> 16041.667 | AF10: =($D10/12)*(1+$C$2+$C$2) -> 16041.667 | AG10: =($D10/12)*(1+$C$2+$C$2) -> 16041.667 | AH10: =($D10/12)*(1+$C$2+$C$2) -> 16041.667 | AI10: =($D10/12)*(1+$C$2+$C$2) -> 16041.667 | AJ10: =($D10/12)*(1+$C$2+$C$2) -> 16041.667 | AK10: =($D10/12)*(1+$C$2+$C$2) -> 16041.667 | AL10: =($D10/12)*(1+$C$2+$C$2) -> 16041.667 | ... AP10: =($D10/12)*(1+$C$2+$C$2) -> 16041.667 | AQ10: =($D10/12)*(1+$C$2+$C$2+$C$2) -> 16770.833 | AR10: =($D10/12)*(1+$C$2+$C$2+$C$2) -> 16770.833 | AS10: =($D10/12)*(1+$C$2+$C$2+$C$2) -> 16770.833 | AT10: =($D10/12)*(1+$C$2+$C$2+$C$2) -> 16770.833 | AU10: =($D10/12)*(1+$C$2+$C$2+$C$2) -> 16770.833 | AV10: =($D10/12)*(1+$C$2+$C$2+$C$2) -> 16770.833 | AW10: =($D10/12)*(1+$C$2+$C$2+$C$2) -> 16770.833 | AX10: =($D10/12)*(1+$C$2+$C$2+$C$2) -> 16770.833 | ... BB10: =($D10/12)*(1+$C$2+$C$2+$C$2) -> 16770.833 | BC10: =($D10/12)*(1+$C$2+$C$2+$C$2+$C$2) -> 17500 | BD10: =($D10/12)*(1+$C$2+$C$2+$C$2+$C$2) -> 17500 | BE10: =($D10/12)*(1+$C$2+$C$2+$C$2+$C$2) -> 17500 | BF10: =($D10/12)*(1+$C$2+$C$2+$C$2+$C$2) -> 17500 | BG10: =($D10/12)*(1+$C$2+$C$2+$C$2+$C$2) -> 17500 | BH10: =($D10/12)*(1+$C$2+$C$2+$C$2+$C$2) -> 17500 | BI10: =($D10/12)*(1+$C$2+$C$2+$C$2+$C$2) -> 17500 | BJ10: =($D10/12)*(1+$C$2+$C$2+$C$2+$C$2) -> 17500 | ... CL10: =($D10/12)*(1+$C$2+$C$2+$C$2+$C$2) -> 17500
B11: Data Scientist | C11: Sitech | D11: 145000 | P11: =$D11/12 -> 12083.333 | Q11: =$D11/12 -> 12083.333 | R11: =$D11/12 -> 12083.333 | S11: =($D11/12)*(1+$C$2) -> 12687.5 | T11: =($D11/12)*(1+$C$2) -> 12687.5 | U11: =($D11/12)*(1+$C$2) -> 12687.5 | V11: =($D11/12)*(1+$C$2) -> 12687.5 | W11: =($D11/12)*(1+$C$2) -> 12687.5 | X11: =($D11/12)*(1+$C$2) -> 12687.5 | Y11: =($D11/12)*(1+$C$2) -> 12687.5 | Z11: =($D11/12)*(1+$C$2) -> 12687.5 | ... AD11: =($D11/12)*(1+$C$2) -> 12687.5 | AE11: =($D11/12)*(1+$C$2+$C$2) -> 13291.667 | AF11: =($D11/12)*(1+$C$2+$C$2) -> 13291.667 | AG11: =($D11/12)*(1+$C$2+$C$2) -> 13291.667 | AH11: =($D11/12)*(1+$C$2+$C$2) -> 13291.667 | AI11: =($D11/12)*(1+$C$2+$C$2) -> 13291.667 | AJ11: =($D11/12)*(1+$C$2+$C$2) -> 13291.667 | AK11: =($D11/12)*(1+$C$2+$C$2) -> 13291.667 | AL11: =($D11/12)*(1+$C$2+$C$2) -> 13291.667 | ... AP11: =($D11/12)*(1+$C$2+$C$2) -> 13291.667 | AQ11: =($D11/12)*(1+$C$2+$C$2+$C$2) -> 13895.833 | AR11: =($D11/12)*(1+$C$2+$C$2+$C$2) -> 13895.833 | AS11: =($D11/12)*(1+$C$2+$C$2+$C$2) -> 13895.833 | AT11: =($D11/12)*(1+$C$2+$C$2+$C$2) -> 13895.833 | AU11: =($D11/12)*(1+$C$2+$C$2+$C$2) -> 13895.833 | AV11: =($D11/12)*(1+$C$2+$C$2+$C$2) -> 13895.833 | AW11: =($D11/12)*(1+$C$2+$C$2+$C$2) -> 13895.833 | AX11: =($D11/12)*(1+$C$2+$C$2+$C$2) -> 13895.833 | ... BB11: =($D11/12)*(1+$C$2+$C$2+$C$2) -> 13895.833 | BC11: =($D11/12)*(1+$C$2+$C$2+$C$2+$C$2) -> 14500 | BD11: =($D11/12)*(1+$C$2+$C$2+$C$2+$C$2) -> 14500 | BE11: =($D11/12)*(1+$C$2+$C$2+$C$2+$C$2) -> 14500 | BF11: =($D11/12)*(1+$C$2+$C$2+$C$2+$C$2) -> 14500 | BG11: =($D11/12)*(1+$C$2+$C$2+$C$2+$C$2) -> 14500 | BH11: =($D11/12)*(1+$C$2+$C$2+$C$2+$C$2) -> 14500 | BI11: =($D11/12)*(1+$C$2+$C$2+$C$2+$C$2) -> 14500 | BJ11: =($D11/12)*(1+$C$2+$C$2+$C$2+$C$2) -> 14500 | ... CL11: =($D11/12)*(1+$C$2+$C$2+$C$2+$C$2) -> 14500
B12: Software Developer | C12: Luis | D12: 118000 | O12: =$D12/12 -> 9833.3333 | P12: =$D12/12 -> 9833.3333 | Q12: =$D12/12 -> 9833.3333 | R12: =$D12/12 -> 9833.3333 | S12: =($D12/12)*(1+$C$2) -> 10325 | T12: =($D12/12)*(1+$C$2) -> 10325 | U12: =($D12/12)*(1+$C$2) -> 10325 | V12: =($D12/12)*(1+$C$2) -> 10325
B13: Software Developer | C13: Vincent | D13: 117500 | E13: 135k in May 23 | O13: =$D13/12 -> 9791.6667 | P13: =$D13/12 -> 9791.6667 | Q13: =$D13/12 -> 9791.6667 | R13: =$D13/12 -> 9791.6667 | S13: =($D13/12)*(1+$C$2) -> 10281.25 | T13: =($D13/12)*(1+$C$2) -> 10281.25 | U13: =($D13/12)*(1+$C$2) -> 10281.25 | V13: =($D13/12)*(1+$C$2) -> 10281.25 | W13: =135000/12 -> 11250 | X13: =135000/12 -> 11250 | Y13: =135000/12 -> 11250 | Z13: =135000/12 -> 11250 | AA13: =135000/12 -> 11250 | AB13: =135000/12 -> 11250 | AC13: =135000/12 -> 11250 | AD13: =135000/12 -> 11250 | AE13: =AD13*(1+$C$2) -> 11812.5 | AF13: =AE13 -> 11812.5 | AG13: =AF13 -> 11812.5 | AH13: =AG13 -> 11812.5 | AI13: =AH13 -> 11812.5 | AJ13: =AI13 -> 11812.5 | AK13: =AJ13 -> 11812.5 | AL13: =AK13 -> 11812.5 | AM13: =AL13 -> 11812.5 | ... AP13: =AO13 -> 11812.5 | AQ13: =AP13*(1+$C$2) -> 12403.125 | AR13: =AQ13 -> 12403.125 | AS13: =AR13 -> 12403.125 | AT13: =AS13 -> 12403.125 | AU13: =AT13 -> 12403.125 | AV13: =AU13 -> 12403.125 | AW13: =AV13 -> 12403.125 | AX13: =AW13 -> 12403.125 | AY13: =AX13 -> 12403.125 | ... BB13: =BA13 -> 12403.125 | BC13: =($D13/12)*(1+$C$2+$C$2+$C$2+$C$2) -> 11750 | BD13: =($D13/12)*(1+$C$2+$C$2+$C$2+$C$2) -> 11750 | BE13: =($D13/12)*(1+$C$2+$C$2+$C$2+$C$2) -> 11750 | BF13: =($D13/12)*(1+$C$2+$C$2+$C$2+$C$2) -> 11750 | BG13: =($D13/12)*(1+$C$2+$C$2+$C$2+$C$2) -> 11750 | BH13: =($D13/12)*(1+$C$2+$C$2+$C$2+$C$2) -> 11750 | BI13: =($D13/12)*(1+$C$2+$C$2+$C$2+$C$2) -> 11750 | BJ13: =($D13/12)*(1+$C$2+$C$2+$C$2+$C$2) -> 11750 | ... CL13: =($D13/12)*(1+$C$2+$C$2+$C$2+$C$2) -> 11750
B14: Software Developer | C14: Carl | D14: 110000 | E14: fin septembre 2022 | O14: =$D14/12 -> 9166.6667
B15: Software Developer | C15: Austin | D15: 100000 | S15: =($D15/12)*(1+$C$2) -> 8750 | T15: =($D15/12)*(1+$C$2) -> 8750 | U15: =($D15/12)*(1+$C$2) -> 8750 | V15: =($D15/12)*(1+$C$2) -> 8750 | W15: =($D15/12)*(1+$C$2) -> 8750 | X15: =($D15/12)*(1+$C$2) -> 8750 | Y15: =($D15/12)*(1+$C$2) -> 8750 | Z15: =($D15/12)*(1+$C$2) -> 8750 | ... AD15: =($D15/12)*(1+$C$2) -> 8750 | AE15: =($D15/12)*(1+$C$2+$C$2) -> 9166.6667 | AF15: =($D15/12)*(1+$C$2+$C$2) -> 9166.6667 | AG15: =($D15/12)*(1+$C$2+$C$2) -> 9166.6667 | AH15: =($D15/12)*(1+$C$2+$C$2) -> 9166.6667 | AI15: =($D15/12)*(1+$C$2+$C$2) -> 9166.6667 | AJ15: =($D15/12)*(1+$C$2+$C$2) -> 9166.6667 | AK15: =($D15/12)*(1+$C$2+$C$2) -> 9166.6667 | AL15: =($D15/12)*(1+$C$2+$C$2) -> 9166.6667 | ... AP15: =($D15/12)*(1+$C$2+$C$2) -> 9166.6667 | AQ15: =($D15/12)*(1+$C$2+$C$2+$C$2) -> 9583.3333 | AR15: =($D15/12)*(1+$C$2+$C$2+$C$2) -> 9583.3333 | AS15: =($D15/12)*(1+$C$2+$C$2+$C$2) -> 9583.3333 | AT15: =($D15/12)*(1+$C$2+$C$2+$C$2) -> 9583.3333 | AU15: =($D15/12)*(1+$C$2+$C$2+$C$2) -> 9583.3333 | AV15: =($D15/12)*(1+$C$2+$C$2+$C$2) -> 9583.3333 | AW15: =($D15/12)*(1+$C$2+$C$2+$C$2) -> 9583.3333 | AX15: =($D15/12)*(1+$C$2+$C$2+$C$2) -> 9583.3333 | ... BB15: =($D15/12)*(1+$C$2+$C$2+$C$2) -> 9583.3333 | BC15: =($D15/12)*(1+$C$2+$C$2+$C$2+$C$2) -> 10000 | BD15: =($D15/12)*(1+$C$2+$C$2+$C$2+$C$2) -> 10000 | BE15: =($D15/12)*(1+$C$2+$C$2+$C$2+$C$2) -> 10000 | BF15: =($D15/12)*(1+$C$2+$C$2+$C$2+$C$2) -> 10000 | BG15: =($D15/12)*(1+$C$2+$C$2+$C$2+$C$2) -> 10000 | BH15: =($D15/12)*(1+$C$2+$C$2+$C$2+$C$2) -> 10000 | BI15: =($D15/12)*(1+$C$2+$C$2+$C$2+$C$2) -> 10000 | BJ15: =($D15/12)*(1+$C$2+$C$2+$C$2+$C$2) -> 10000 | ... CL15: =($D15/12)*(1+$C$2+$C$2+$C$2+$C$2) -> 10000
B16: Software Developer | C16: Adrien | D16: 81000 | O16: =$D16/12 -> 6750 | P16: =$D16/12 -> 6750 | Q16: =$D16/12 -> 6750 | R16: =$D16/12 -> 6750 | S16: =($D16/12)*(1+$C$2) -> 7087.5 | T16: =($D16/12)*(1+$C$2) -> 7087.5 | U16: =($D16/12)*(1+$C$2) -> 7087.5 | V16: =($D16/12)*(1+$C$2) -> 7087.5 | W16: =($D16/12)*(1+$C$2) -> 7087.5 | X16: =($D16/12)*(1+$C$2) -> 7087.5 | Y16: =($D16/12)*(1+$C$2) -> 7087.5 | Z16: =($D16/12)*(1+$C$2) -> 7087.5 | ... AD16: =($D16/12)*(1+$C$2) -> 7087.5 | AE16: =($D16/12)*(1+$C$2+$C$2) -> 7425 | AF16: =($D16/12)*(1+$C$2+$C$2) -> 7425 | AG16: =($D16/12)*(1+$C$2+$C$2) -> 7425 | AH16: =($D16/12)*(1+$C$2+$C$2) -> 7425 | AI16: =($D16/12)*(1+$C$2+$C$2) -> 7425 | AJ16: =($D16/12)*(1+$C$2+$C$2) -> 7425 | AK16: =($D16/12)*(1+$C$2+$C$2) -> 7425 | AL16: =($D16/12)*(1+$C$2+$C$2) -> 7425 | ... AP16: =($D16/12)*(1+$C$2+$C$2) -> 7425 | AQ16: =($D16/12)*(1+$C$2+$C$2+$C$2) -> 7762.5 | AR16: =($D16/12)*(1+$C$2+$C$2+$C$2) -> 7762.5 | AS16: =($D16/12)*(1+$C$2+$C$2+$C$2) -> 7762.5 | AT16: =($D16/12)*(1+$C$2+$C$2+$C$2) -> 7762.5 | AU16: =($D16/12)*(1+$C$2+$C$2+$C$2) -> 7762.5 | AV16: =($D16/12)*(1+$C$2+$C$2+$C$2) -> 7762.5 | AW16: =($D16/12)*(1+$C$2+$C$2+$C$2) -> 7762.5 | AX16: =($D16/12)*(1+$C$2+$C$2+$C$2) -> 7762.5 | ... BB16: =($D16/12)*(1+$C$2+$C$2+$C$2) -> 7762.5 | BC16: =($D16/12)*(1+$C$2+$C$2+$C$2+$C$2) -> 8100 | BD16: =($D16/12)*(1+$C$2+$C$2+$C$2+$C$2) -> 8100 | BE16: =($D16/12)*(1+$C$2+$C$2+$C$2+$C$2) -> 8100 | BF16: =($D16/12)*(1+$C$2+$C$2+$C$2+$C$2) -> 8100 | BG16: =($D16/12)*(1+$C$2+$C$2+$C$2+$C$2) -> 8100 | BH16: =($D16/12)*(1+$C$2+$C$2+$C$2+$C$2) -> 8100 | BI16: =($D16/12)*(1+$C$2+$C$2+$C$2+$C$2) -> 8100 | BJ16: =($D16/12)*(1+$C$2+$C$2+$C$2+$C$2) -> 8100 | ... CL16: =($D16/12)*(1+$C$2+$C$2+$C$2+$C$2) -> 8100
B17: Software Developer | C17: Thomas | D17: 58000 | O17: =$D17/12 -> 4833.3333 | P17: =$D17/12 -> 4833.3333 | Q17: =$D17/12 -> 4833.3333 | R17: =$D17/12 -> 4833.3333 | S17: =($D17/12)*(1+$C$2) -> 5075 | T17: =($D17/12)*(1+$C$2) -> 5075 | U17: =($D17/12)*(1+$C$2) -> 5075 | V17: =($D17/12)*(1+$C$2) -> 5075
B18: Software Developer | C18: Eric L | D18: 70000 | E18: conversion de stagiaire a full time en février | T18: =($D18/12)*(1+$C$2) -> 6125 | U18: =($D18/12)*(1+$C$2) -> 6125 | V18: =($D18/12)*(1+$C$2) -> 6125 | W18: =($D18/12)*(1+$C$2) -> 6125 | X18: =($D18/12)*(1+$C$2) -> 6125 | Y18: =($D18/12)*(1+$C$2) -> 6125 | Z18: =($D18/12)*(1+$C$2) -> 6125 | AA18: =($D18/12)*(1+$C$2) -> 6125 | ... AD18: =($D18/12)*(1+$C$2) -> 6125 | AE18: =($D18/12)*(1+$C$2+$C$2) -> 6416.6667 | AF18: =($D18/12)*(1+$C$2+$C$2) -> 6416.6667 | AG18: =($D18/12)*(1+$C$2+$C$2) -> 6416.6667 | AH18: =($D18/12)*(1+$C$2+$C$2) -> 6416.6667 | AI18: =($D18/12)*(1+$C$2+$C$2) -> 6416.6667 | AJ18: =($D18/12)*(1+$C$2+$C$2) -> 6416.6667 | AK18: =($D18/12)*(1+$C$2+$C$2) -> 6416.6667 | AL18: =($D18/12)*(1+$C$2+$C$2) -> 6416.6667 | ... AP18: =($D18/12)*(1+$C$2+$C$2) -> 6416.6667 | AQ18: =($D18/12)*(1+$C$2+$C$2+$C$2) -> 6708.3333 | AR18: =($D18/12)*(1+$C$2+$C$2+$C$2) -> 6708.3333 | AS18: =($D18/12)*(1+$C$2+$C$2+$C$2) -> 6708.3333 | AT18: =($D18/12)*(1+$C$2+$C$2+$C$2) -> 6708.3333 | AU18: =($D18/12)*(1+$C$2+$C$2+$C$2) -> 6708.3333 | AV18: =($D18/12)*(1+$C$2+$C$2+$C$2) -> 6708.3333 | AW18: =($D18/12)*(1+$C$2+$C$2+$C$2) -> 6708.3333 | AX18: =($D18/12)*(1+$C$2+$C$2+$C$2) -> 6708.3333 | ... BB18: =($D18/12)*(1+$C$2+$C$2+$C$2) -> 6708.3333 | BC18: =($D18/12)*(1+$C$2+$C$2+$C$2+$C$2) -> 7000 | BD18: =($D18/12)*(1+$C$2+$C$2+$C$2+$C$2) -> 7000 | BE18: =($D18/12)*(1+$C$2+$C$2+$C$2+$C$2) -> 7000 | BF18: =($D18/12)*(1+$C$2+$C$2+$C$2+$C$2) -> 7000 | BG18: =($D18/12)*(1+$C$2+$C$2+$C$2+$C$2) -> 7000 | BH18: =($D18/12)*(1+$C$2+$C$2+$C$2+$C$2) -> 7000 | BI18: =($D18/12)*(1+$C$2+$C$2+$C$2+$C$2) -> 7000 | BJ18: =($D18/12)*(1+$C$2+$C$2+$C$2+$C$2) -> 7000 | ... CL18: =($D18/12)*(1+$C$2+$C$2+$C$2+$C$2) -> 7000
B19: Software Developer | C19: Charles | D19: 60000 | E19: conversion de pharmacien en developpeur | T19: =($D19/12)*(1+$C$2) -> 5250 | U19: =($D19/12)*(1+$C$2) -> 5250 | V19: =($D19/12)*(1+$C$2) -> 5250 | W19: =($D19/12)*(1+$C$2) -> 5250 | X19: =($D19/12)*(1+$C$2) -> 5250 | Y19: =($D19/12)*(1+$C$2) -> 5250 | Z19: =($D19/12)*(1+$C$2) -> 5250 | AA19: =($D19/12)*(1+$C$2) -> 5250 | ... AD19: =($D19/12)*(1+$C$2) -> 5250 | AE19: =($D19/12)*(1+$C$2+$C$2) -> 5500 | AF19: =($D19/12)*(1+$C$2+$C$2) -> 5500 | AG19: =($D19/12)*(1+$C$2+$C$2) -> 5500 | AH19: =($D19/12)*(1+$C$2+$C$2) -> 5500 | AI19: =($D19/12)*(1+$C$2+$C$2) -> 5500 | AJ19: =($D19/12)*(1+$C$2+$C$2) -> 5500 | AK19: =($D19/12)*(1+$C$2+$C$2) -> 5500 | AL19: =($D19/12)*(1+$C$2+$C$2) -> 5500 | ... AP19: =($D19/12)*(1+$C$2+$C$2) -> 5500 | AQ19: =($D19/12)*(1+$C$2+$C$2+$C$2) -> 5750 | AR19: =($D19/12)*(1+$C$2+$C$2+$C$2) -> 5750 | AS19: =($D19/12)*(1+$C$2+$C$2+$C$2) -> 5750 | AT19: =($D19/12)*(1+$C$2+$C$2+$C$2) -> 5750 | AU19: =($D19/12)*(1+$C$2+$C$2+$C$2) -> 5750 | AV19: =($D19/12)*(1+$C$2+$C$2+$C$2) -> 5750 | AW19: =($D19/12)*(1+$C$2+$C$2+$C$2) -> 5750 | AX19: =($D19/12)*(1+$C$2+$C$2+$C$2) -> 5750 | ... BB19: =($D19/12)*(1+$C$2+$C$2+$C$2) -> 5750 | BC19: =($D19/12)*(1+$C$2+$C$2+$C$2+$C$2) -> 6000 | BD19: =($D19/12)*(1+$C$2+$C$2+$C$2+$C$2) -> 6000 | BE19: =($D19/12)*(1+$C$2+$C$2+$C$2+$C$2) -> 6000 | BF19: =($D19/12)*(1+$C$2+$C$2+$C$2+$C$2) -> 6000 | BG19: =($D19/12)*(1+$C$2+$C$2+$C$2+$C$2) -> 6000 | BH19: =($D19/12)*(1+$C$2+$C$2+$C$2+$C$2) -> 6000 | BI19: =($D19/12)*(1+$C$2+$C$2+$C$2+$C$2) -> 6000 | BJ19: =($D19/12)*(1+$C$2+$C$2+$C$2+$C$2) -> 6000 | ... CL19: =($D19/12)*(1+$C$2+$C$2+$C$2+$C$2) -> 6000
B20: Software Developer | C20: TBH | D20: 120000 | AB20: =($D20/12)*(1+$C$2) -> 10500 | AC20: =($D20/12)*(1+$C$2) -> 10500 | AD20: =($D20/12)*(1+$C$2) -> 10500 | AE20: =($D20/12)*(1+$C$2+$C$2) -> 11000 | AF20: =($D20/12)*(1+$C$2+$C$2) -> 11000 | AG20: =($D20/12)*(1+$C$2+$C$2) -> 11000 | AH20: =($D20/12)*(1+$C$2+$C$2) -> 11000 | AI20: =($D20/12)*(1+$C$2+$C$2) -> 11000 | AJ20: =($D20/12)*(1+$C$2+$C$2) -> 11000 | AK20: =($D20/12)*(1+$C$2+$C$2) -> 11000 | AL20: =($D20/12)*(1+$C$2+$C$2) -> 11000 | ... AP20: =($D20/12)*(1+$C$2+$C$2) -> 11000 | AQ20: =($D20/12)*(1+$C$2+$C$2+$C$2) -> 11500 | AR20: =($D20/12)*(1+$C$2+$C$2+$C$2) -> 11500 | AS20: =($D20/12)*(1+$C$2+$C$2+$C$2) -> 11500 | AT20: =($D20/12)*(1+$C$2+$C$2+$C$2) -> 11500 | AU20: =($D20/12)*(1+$C$2+$C$2+$C$2) -> 11500 | AV20: =($D20/12)*(1+$C$2+$C$2+$C$2) -> 11500 | AW20: =($D20/12)*(1+$C$2+$C$2+$C$2) -> 11500 | AX20: =($D20/12)*(1+$C$2+$C$2+$C$2) -> 11500 | ... BB20: =($D20/12)*(1+$C$2+$C$2+$C$2) -> 11500 | BC20: =($D20/12)*(1+$C$2+$C$2+$C$2+$C$2) -> 12000 | BD20: =($D20/12)*(1+$C$2+$C$2+$C$2+$C$2) -> 12000 | BE20: =($D20/12)*(1+$C$2+$C$2+$C$2+$C$2) -> 12000 | BF20: =($D20/12)*(1+$C$2+$C$2+$C$2+$C$2) -> 12000 | BG20: =($D20/12)*(1+$C$2+$C$2+$C$2+$C$2) -> 12000 | BH20: =($D20/12)*(1+$C$2+$C$2+$C$2+$C$2) -> 12000 | BI20: =($D20/12)*(1+$C$2+$C$2+$C$2+$C$2) -> 12000 | BJ20: =($D20/12)*(1+$C$2+$C$2+$C$2+$C$2) -> 12000 | ... CL20: =($D20/12)*(1+$C$2+$C$2+$C$2+$C$2) -> 12000
B21: Software Developer | C21: TBH | D21: 80000 | O21: =$D21/12 -> 6666.6667 | P21: =$D21/12 -> 6666.6667 | Q21: =$D21/12 -> 6666.6667 | R21: =$D21/12 -> 6666.6667 | AJ21: =($D21/12)*(1+$C$2+$C$2) -> 7333.3333 | AK21: =($D21/12)*(1+$C$2+$C$2) -> 7333.3333 | AL21: =($D21/12)*(1+$C$2+$C$2) -> 7333.3333 | AM21: =($D21/12)*(1+$C$2+$C$2) -> 7333.3333 | AN21: =($D21/12)*(1+$C$2+$C$2) -> 7333.3333 | AO21: =($D21/12)*(1+$C$2+$C$2) -> 7333.3333 | AP21: =($D21/12)*(1+$C$2+$C$2) -> 7333.3333 | AQ21: =($D21/12)*(1+$C$2+$C$2+$C$2) -> 7666.6667 | AR21: =($D21/12)*(1+$C$2+$C$2+$C$2) -> 7666.6667 | AS21: =($D21/12)*(1+$C$2+$C$2+$C$2) -> 7666.6667 | AT21: =($D21/12)*(1+$C$2+$C$2+$C$2) -> 7666.6667 | AU21: =($D21/12)*(1+$C$2+$C$2+$C$2) -> 7666.6667 | AV21: =($D21/12)*(1+$C$2+$C$2+$C$2) -> 7666.6667 | AW21: =($D21/12)*(1+$C$2+$C$2+$C$2) -> 7666.6667 | AX21: =($D21/12)*(1+$C$2+$C$2+$C$2) -> 7666.6667 | ... BB21: =($D21/12)*(1+$C$2+$C$2+$C$2) -> 7666.6667 | BC21: =($D21/12)*(1+$C$2+$C$2+$C$2+$C$2) -> 8000 | BD21: =($D21/12)*(1+$C$2+$C$2+$C$2+$C$2) -> 8000 | BE21: =($D21/12)*(1+$C$2+$C$2+$C$2+$C$2) -> 8000 | BF21: =($D21/12)*(1+$C$2+$C$2+$C$2+$C$2) -> 8000 | BG21: =($D21/12)*(1+$C$2+$C$2+$C$2+$C$2) -> 8000 | BH21: =($D21/12)*(1+$C$2+$C$2+$C$2+$C$2) -> 8000 | BI21: =($D21/12)*(1+$C$2+$C$2+$C$2+$C$2) -> 8000 | BJ21: =($D21/12)*(1+$C$2+$C$2+$C$2+$C$2) -> 8000 | ... CL21: =($D21/12)*(1+$C$2+$C$2+$C$2+$C$2) -> 8000
B22: Software Developer | C22: TBH | D22: 85000 | AJ22: =D22/12 -> 7083.3333 | AK22: =AJ22 -> 7083.3333 | AL22: =AK22 -> 7083.3333 | AM22: =AL22 -> 7083.3333 | AN22: =AM22 -> 7083.3333 | AO22: =AN22 -> 7083.3333 | AP22: =AO22 -> 7083.3333 | AQ22: =AP22*(1+C2) -> 7437.5 | AR22: =AQ22 -> 7437.5 | AS22: =AR22 -> 7437.5 | AT22: =AS22 -> 7437.5 | AU22: =AT22 -> 7437.5 | AV22: =AU22 -> 7437.5 | AW22: =AV22 -> 7437.5 | AX22: =AW22 -> 7437.5 | AY22: =AX22 -> 7437.5 | ... BB22: =BA22 -> 7437.5 | BC22: =($D22/12)*(1+$C$2+$C$2+$C$2+$C$2) -> 8500 | BD22: =($D22/12)*(1+$C$2+$C$2+$C$2+$C$2) -> 8500 | BE22: =($D22/12)*(1+$C$2+$C$2+$C$2+$C$2) -> 8500 | BF22: =($D22/12)*(1+$C$2+$C$2+$C$2+$C$2) -> 8500 | BG22: =($D22/12)*(1+$C$2+$C$2+$C$2+$C$2) -> 8500 | BH22: =($D22/12)*(1+$C$2+$C$2+$C$2+$C$2) -> 8500 | BI22: =($D22/12)*(1+$C$2+$C$2+$C$2+$C$2) -> 8500 | BJ22: =($D22/12)*(1+$C$2+$C$2+$C$2+$C$2) -> 8500 | ... CL22: =($D22/12)*(1+$C$2+$C$2+$C$2+$C$2) -> 8500
B23: Software Developer | C23: TBH | D23: 85000 | AQ23: =D23/12 -> 7083.3333 | AR23: =AQ23 -> 7083.3333 | AS23: =AR23 -> 7083.3333 | AT23: =AS23 -> 7083.3333 | AU23: =AT23 -> 7083.3333 | AV23: =AU23 -> 7083.3333 | AW23: =AV23 -> 7083.3333 | AX23: =AW23 -> 7083.3333 | AY23: =AX23 -> 7083.3333 | ... BB23: =BA23 -> 7083.3333 | BC23: =($D23/12)*(1+$C$2+$C$2+$C$2+$C$2) -> 8500 | BD23: =($D23/12)*(1+$C$2+$C$2+$C$2+$C$2) -> 8500 | BE23: =($D23/12)*(1+$C$2+$C$2+$C$2+$C$2) -> 8500 | BF23: =($D23/12)*(1+$C$2+$C$2+$C$2+$C$2) -> 8500 | BG23: =($D23/12)*(1+$C$2+$C$2+$C$2+$C$2) -> 8500 | BH23: =($D23/12)*(1+$C$2+$C$2+$C$2+$C$2) -> 8500 | BI23: =($D23/12)*(1+$C$2+$C$2+$C$2+$C$2) -> 8500 | BJ23: =($D23/12)*(1+$C$2+$C$2+$C$2+$C$2) -> 8500 | ... CL23: =($D23/12)*(1+$C$2+$C$2+$C$2+$C$2) -> 8500
B24: Developer AI | C24: William Intern | D24: 125000 | S24: =8*4*32 -> 1024 | T24: =S24 -> 1024 | AQ24: =D24/12 -> 10416.667 | AR24: =AQ24 -> 10416.667 | AS24: =AR24 -> 10416.667 | AT24: =AS24 -> 10416.667 | AU24: =AT24 -> 10416.667 | AV24: =AU24 -> 10416.667 | AW24: =AV24 -> 10416.667 | AX24: =AW24 -> 10416.667 | AY24: =AX24 -> 10416.667 | ... BB24: =BA24 -> 10416.667 | BC24: =($D24/12)*(1+$C$2+$C$2+$C$2+$C$2) -> 12500 | BD24: =($D24/12)*(1+$C$2+$C$2+$C$2+$C$2) -> 12500 | BE24: =($D24/12)*(1+$C$2+$C$2+$C$2+$C$2) -> 12500 | BF24: =($D24/12)*(1+$C$2+$C$2+$C$2+$C$2) -> 12500 | BG24: =($D24/12)*(1+$C$2+$C$2+$C$2+$C$2) -> 12500 | BH24: =($D24/12)*(1+$C$2+$C$2+$C$2+$C$2) -> 12500 | BI24: =($D24/12)*(1+$C$2+$C$2+$C$2+$C$2) -> 12500 | BJ24: =($D24/12)*(1+$C$2+$C$2+$C$2+$C$2) -> 12500 | ... CL24: =($D24/12)*(1+$C$2+$C$2+$C$2+$C$2) -> 12500
B26: Soft Dev FS - Intern | C26: TBH | D26: =4.33*40*30 -> 5196 | E26: per week (60k/year) | W26: =D26 -> 5196 | X26: =W26 -> 5196 | Y26: =X26 -> 5196 | Z26: =Y26 -> 5196
B27: Soft Dev AI - Intern | C27: TBH | D27: =4.33*40*30 -> 5196 | E27: per week (60k/year) | W27: =D27 -> 5196 | X27: =W27 -> 5196 | Y27: =X27 -> 5196 | Z27: =Y27 -> 5196
B29: TOTAL | G29: =SUM(G8:G28) -> 0 | H29: =SUM(H8:H28) -> 0 | I29: =SUM(I8:I28) -> 0 | J29: =SUM(J8:J28) -> 0 | K29: =SUM(K8:K28) -> 0 | L29: =SUM(L8:L28) -> 0 | M29: =SUM(M8:M28) -> 0 | N29: =SUM(N8:N28) -> 0 | ... S29: =SUM(S8:S28) -> 70542.75 | T29: =SUM(T9:T28) -> 81917.75 | U29: =SUM(U9:U28) -> 80893.75 | V29: =SUM(V9:V28) -> 80893.75 | W29: =SUM(W9:W28) -> 76854.5 | X29: =SUM(X9:X28) -> 76854.5 | Y29: =SUM(Y9:Y28) -> 76854.5 | Z29: =SUM(Z9:Z28) -> 76854.5 | AA29: =SUM(AA9:AA28) -> 66462.5 | ... CL29: =SUM(CL9:CL28) -> 124350
B32: Sales & Marketing
B33: CRO | C33: Simon | D33: 175000 | O33: =$D33/12 -> 14583.333 | P33: =$D33/12 -> 14583.333 | Q33: =$D33/12 -> 14583.333 | R33: =$D33/12 -> 14583.333 | W33: =($D33/12)*(1+$C$2) -> 15312.5 | X33: =($D33/12)*(1+$C$2) -> 15312.5 | Y33: =($D33/12)*(1+$C$2) -> 15312.5 | Z33: =($D33/12)*(1+$C$2) -> 15312.5 | AA33: =($D33/12)*(1+$C$2) -> 15312.5
B34: Data Analyst | C34: TBH | D34: 100000 | AL34: =($D34/12)*(1+$C$2+$C$2) -> 9166.6667 | AM34: =($D34/12)*(1+$C$2+$C$2) -> 9166.6667 | AN34: =($D34/12)*(1+$C$2+$C$2) -> 9166.6667 | AO34: =($D34/12)*(1+$C$2+$C$2) -> 9166.6667 | AP34: =($D34/12)*(1+$C$2+$C$2) -> 9166.6667 | AQ34: =($D34/12)*(1+$C$2+$C$2+$C$2) -> 9583.3333 | AR34: =($D34/12)*(1+$C$2+$C$2+$C$2) -> 9583.3333 | AS34: =($D34/12)*(1+$C$2+$C$2+$C$2) -> 9583.3333 | AT34: =($D34/12)*(1+$C$2+$C$2+$C$2) -> 9583.3333 | AU34: =($D34/12)*(1+$C$2+$C$2+$C$2) -> 9583.3333 | AV34: =($D34/12)*(1+$C$2+$C$2+$C$2) -> 9583.3333 | AW34: =($D34/12)*(1+$C$2+$C$2+$C$2) -> 9583.3333 | AX34: =($D34/12)*(1+$C$2+$C$2+$C$2) -> 9583.3333 | ... CL34: =($D34/12)*(1+$C$2+$C$2+$C$2) -> 9583.3333
B35: Biz Dev | C35: Karine | D35: 150000 | AI35: =($D35/12)*(1+$C$2+$C$2) -> 13750 | AJ35: =AI35 -> 13750 | AK35: =AJ35 -> 13750 | AL35: =AK35 -> 13750 | AM35: =AL35 -> 13750 | AN35: =AM35 -> 13750 | AO35: =AN35 -> 13750 | AP35: =AO35 -> 13750 | AQ35: =AP35*(1+$C$2) -> 14437.5 | AR35: =AQ35 -> 14437.5 | AS35: =AR35 -> 14437.5 | AT35: =AS35 -> 14437.5 | AU35: =AT35 -> 14437.5 | AV35: =AU35 -> 14437.5 | AW35: =AV35 -> 14437.5 | AX35: =AW35 -> 14437.5 | AY35: =AX35 -> 14437.5 | ... BB35: =BA35 -> 14437.5 | BC35: =BB35*(1+$C$2) -> 15159.375 | BD35: =BC35 -> 15159.375 | BE35: =BD35 -> 15159.375 | BF35: =BE35 -> 15159.375 | BG35: =BF35 -> 15159.375 | BH35: =BG35 -> 15159.375 | BI35: =BH35 -> 15159.375 | BJ35: =BI35 -> 15159.375 | BK35: =BJ35 -> 15159.375 | ... BN35: =BM35 -> 15159.375 | BO35: =BN35*(1+$C$2) -> 15917.344 | BP35: =BO35 -> 15917.344 | BQ35: =BP35 -> 15917.344 | BR35: =BQ35 -> 15917.344 | BS35: =BR35 -> 15917.344 | BT35: =BS35 -> 15917.344 | BU35: =BT35 -> 15917.344 | BV35: =BU35 -> 15917.344 | BW35: =BV35 -> 15917.344 | ... BZ35: =BY35 -> 15917.344 | CA35: =BZ35*(1+$C$2) -> 16713.211 | CB35: =CA35 -> 16713.211 | CC35: =CB35 -> 16713.211 | CD35: =CC35 -> 16713.211 | CE35: =CD35 -> 16713.211 | CF35: =CE35 -> 16713.211 | CG35: =CF35 -> 16713.211 | CH35: =CG35 -> 16713.211 | CI35: =CH35 -> 16713.211 | ... CL35: =CK35 -> 16713.211
B36: Product Owner | C36: Gabriel | D36: 92000 | O36: =$D36/12 -> 7666.6667 | P36: =$D36/12 -> 7666.6667 | Q36: =$D36/12 -> 7666.6667 | R36: =$D36/12 -> 7666.6667 | S36: =($D36/12)*(1+$C$2) -> 8050 | T36: =($D36/12)*(1+$C$2) -> 8050 | U36: =($D36/12)*(1+$C$2) -> 8050 | V36: =($D36/12)*(1+$C$2) -> 8050 | W36: =($D36/12)*(1+$C$2) -> 8050 | X36: =($D36/12)*(1+$C$2) -> 8050 | AE36: =($D36/12)*(1+$C$2+$C$2) -> 8433.3333 | AF36: =($D36/12)*(1+$C$2+$C$2) -> 8433.3333 | AG36: =($D36/12)*(1+$C$2+$C$2) -> 8433.3333 | AH36: =($D36/12)*(1+$C$2+$C$2) -> 8433.3333 | AI36: =($D36/12)*(1+$C$2+$C$2) -> 8433.3333 | AJ36: =($D36/12)*(1+$C$2+$C$2) -> 8433.3333 | AK36: =($D36/12)*(1+$C$2+$C$2) -> 8433.3333 | AL36: =($D36/12)*(1+$C$2+$C$2) -> 8433.3333 | ... AP36: =($D36/12)*(1+$C$2+$C$2) -> 8433.3333 | AQ36: =($D36/12)*(1+$C$2+$C$2+$C$2) -> 8816.6667 | AR36: =($D36/12)*(1+$C$2+$C$2+$C$2) -> 8816.6667 | AS36: =($D36/12)*(1+$C$2+$C$2+$C$2) -> 8816.6667 | AT36: =($D36/12)*(1+$C$2+$C$2+$C$2) -> 8816.6667 | AU36: =($D36/12)*(1+$C$2+$C$2+$C$2) -> 8816.6667 | AV36: =($D36/12)*(1+$C$2+$C$2+$C$2) -> 8816.6667 | AW36: =($D36/12)*(1+$C$2+$C$2+$C$2) -> 8816.6667 | AX36: =($D36/12)*(1+$C$2+$C$2+$C$2) -> 8816.6667 | ... CL36: =($D36/12)*(1+$C$2+$C$2+$C$2) -> 8816.6667
B37: Marketing Manager | C37: TBH | D37: 90000 | O37: =$D37/12 -> 7500 | P37: =$D37/12 -> 7500 | Q37: =$D37/12 -> 7500 | R37: =$D37/12 -> 7500 | AE37: =($D37/12)*(1+$C$2+$C$2) -> 8250 | AF37: =($D37/12)*(1+$C$2+$C$2) -> 8250 | AG37: =($D37/12)*(1+$C$2+$C$2) -> 8250 | AH37: =($D37/12)*(1+$C$2+$C$2) -> 8250 | AI37: =($D37/12)*(1+$C$2+$C$2) -> 8250 | AJ37: =($D37/12)*(1+$C$2+$C$2) -> 8250 | AK37: =($D37/12)*(1+$C$2+$C$2) -> 8250 | AL37: =($D37/12)*(1+$C$2+$C$2) -> 8250 | ... AP37: =($D37/12)*(1+$C$2+$C$2) -> 8250 | AQ37: =($D37/12)*(1+$C$2+$C$2+$C$2) -> 8625 | AR37: =($D37/12)*(1+$C$2+$C$2+$C$2) -> 8625 | AS37: =($D37/12)*(1+$C$2+$C$2+$C$2) -> 8625 | AT37: =($D37/12)*(1+$C$2+$C$2+$C$2) -> 8625 | AU37: =($D37/12)*(1+$C$2+$C$2+$C$2) -> 8625 | AV37: =($D37/12)*(1+$C$2+$C$2+$C$2) -> 8625 | AW37: =($D37/12)*(1+$C$2+$C$2+$C$2) -> 8625 | AX37: =($D37/12)*(1+$C$2+$C$2+$C$2) -> 8625 | ... CL37: =($D37/12)*(1+$C$2+$C$2+$C$2) -> 8625
B38: Channel Manager | C38: TBH | D38: 90000 | AL38: =($D38/12)*(1+$C$2+$C$2) -> 8250 | AM38: =AL38 -> 8250 | AN38: =AM38 -> 8250 | AO38: =AN38 -> 8250 | AP38: =AO38 -> 8250 | AQ38: =AP38*(1+$C$2) -> 8662.5 | AR38: =AQ38 -> 8662.5 | AS38: =AR38 -> 8662.5 | AT38: =AS38 -> 8662.5 | AU38: =AT38 -> 8662.5 | AV38: =AU38 -> 8662.5 | AW38: =AV38 -> 8662.5 | AX38: =AW38 -> 8662.5 | AY38: =AX38 -> 8662.5 | ... BB38: =BA38 -> 8662.5 | BC38: =BB38*(1+$C$2) -> 9095.625 | BD38: =BC38 -> 9095.625 | BE38: =BD38 -> 9095.625 | BF38: =BE38 -> 9095.625 | BG38: =BF38 -> 9095.625 | BH38: =BG38 -> 9095.625 | BI38: =BH38 -> 9095.625 | BJ38: =BI38 -> 9095.625 | BK38: =BJ38 -> 9095.625 | ... BN38: =BM38 -> 9095.625 | BO38: =BN38*(1+$C$2) -> 9550.4062 | BP38: =BO38 -> 9550.4062 | BQ38: =BP38 -> 9550.4062 | BR38: =BQ38 -> 9550.4062 | BS38: =BR38 -> 9550.4062 | BT38: =BS38 -> 9550.4062 | BU38: =BT38 -> 9550.4062 | BV38: =BU38 -> 9550.4062 | BW38: =BV38 -> 9550.4062 | ... BZ38: =BY38 -> 9550.4062 | CA38: =BZ38*(1+$C$2) -> 10027.927 | CB38: =CA38 -> 10027.927 | CC38: =CB38 -> 10027.927 | CD38: =CC38 -> 10027.927 | CE38: =CD38 -> 10027.927 | CF38: =CE38 -> 10027.927 | CG38: =CF38 -> 10027.927 | CH38: =CG38 -> 10027.927 | CI38: =CH38 -> 10027.927 | ... CL38: =CK38 -> 10027.927
B39: Channel Manager | C39: TBH | D39: 90000 | AQ39: =D39/12 -> 7500 | AR39: =AQ39 -> 7500 | AS39: =AR39 -> 7500 | AT39: =AS39 -> 7500 | AU39: =AT39 -> 7500 | AV39: =AU39 -> 7500 | AW39: =AV39 -> 7500 | AX39: =AW39 -> 7500 | AY39: =AX39 -> 7500 | ... BB39: =BA39 -> 7500 | BC39: =BB39*(1+O2) -> 7500 | BD39: =BC39 -> 7500 | BE39: =BD39 -> 7500 | BF39: =BE39 -> 7500 | BG39: =BF39 -> 7500 | BH39: =BG39 -> 7500 | BI39: =BH39 -> 7500 | BJ39: =BI39 -> 7500 | BK39: =BJ39 -> 7500 | ... BN39: =BM39 -> 7500 | BO39: =BN39*(1+AA2) -> 7500 | BP39: =BO39 -> 7500 | BQ39: =BP39 -> 7500 | BR39: =BQ39 -> 7500 | BS39: =BR39 -> 7500 | BT39: =BS39 -> 7500 | BU39: =BT39 -> 7500 | BV39: =BU39 -> 7500 | BW39: =BV39 -> 7500 | ... BZ39: =BY39 -> 7500 | CA39: =BZ39*(1+AM2) -> 7500 | CB39: =CA39 -> 7500 | CC39: =CB39 -> 7500 | CD39: =CC39 -> 7500 | CE39: =CD39 -> 7500 | CF39: =CE39 -> 7500 | CG39: =CF39 -> 7500 | CH39: =CG39 -> 7500 | CI39: =CH39 -> 7500 | ... CL39: =CK39 -> 7500
B40: Marketing & Product Manager | C40: Sarah | D40: 105000 | R40: 0 | S40: 0 | Y40: =($D40/12) -> 8750 | Z40: =($D40/12) -> 8750 | AA40: =($D40/12) -> 8750 | AB40: =($D40/12) -> 8750 | AC40: =($D40/12) -> 8750 | AD40: =($D40/12) -> 8750 | AE40: =AD40*(1+$C$2) -> 9187.5 | AF40: =AE40 -> 9187.5 | AS40: =D40/12 -> 8750 | AT40: =AS40 -> 8750 | AU40: =AT40 -> 8750 | AV40: =AU40 -> 8750 | AW40: =AV40 -> 8750 | AX40: =AW40 -> 8750 | AY40: =AX40 -> 8750 | AZ40: =AY40 -> 8750 | BA40: =AZ40 -> 8750 | BB40: =BA40 -> 8750 | BC40: =BB40*(1+$C$2) -> 9187.5 | BD40: =BC40 -> 9187.5 | BE40: =BD40 -> 9187.5 | BF40: =BE40 -> 9187.5 | BG40: =BF40 -> 9187.5 | BH40: =BG40 -> 9187.5 | BI40: =BH40 -> 9187.5 | BJ40: =BI40 -> 9187.5 | BK40: =BJ40 -> 9187.5 | ... BN40: =BM40 -> 9187.5 | BO40: =BN40*(1+$C$2) -> 9646.875 | BP40: =BO40 -> 9646.875 | BQ40: =BP40 -> 9646.875 | BR40: =BQ40 -> 9646.875 | BS40: =BR40 -> 9646.875 | BT40: =BS40 -> 9646.875 | BU40: =BT40 -> 9646.875 | BV40: =BU40 -> 9646.875 | BW40: =BV40 -> 9646.875 | ... BZ40: =BY40 -> 9646.875 | CA40: =BZ40*(1+$C$2) -> 10129.219 | CB40: =CA40 -> 10129.219 | CC40: =CB40 -> 10129.219 | CD40: =CC40 -> 10129.219 | CE40: =CD40 -> 10129.219 | CF40: =CE40 -> 10129.219 | CG40: =CF40 -> 10129.219 | CH40: =CG40 -> 10129.219 | CI40: =CH40 -> 10129.219 | ... CL40: =CK40 -> 10129.219
B41: Marketing Coordinator | C41: TBH | D41: 75000 | AM41: =D41/12 -> 6250 | AN41: =AM41 -> 6250 | AO41: =AN41 -> 6250 | AP41: =AO41 -> 6250 | AQ41: =AP41*(1+$C$2) -> 6562.5 | AR41: =AQ41 -> 6562.5 | AS41: =AR41 -> 6562.5 | AT41: =AS41 -> 6562.5 | AU41: =AT41 -> 6562.5 | AV41: =AU41 -> 6562.5 | AW41: =AV41 -> 6562.5 | AX41: =AW41 -> 6562.5 | AY41: =AX41 -> 6562.5 | ... BB41: =BA41 -> 6562.5 | BC41: =BB41*(1+$C$2) -> 6890.625 | BD41: =BC41 -> 6890.625 | BE41: =BD41 -> 6890.625 | BF41: =BE41 -> 6890.625 | BG41: =BF41 -> 6890.625 | BH41: =BG41 -> 6890.625 | BI41: =BH41 -> 6890.625 | BJ41: =BI41 -> 6890.625 | BK41: =BJ41 -> 6890.625 | ... BN41: =BM41 -> 6890.625 | BO41: =BN41*(1+$C$2) -> 7235.1562 | BP41: =BO41 -> 7235.1562 | BQ41: =BP41 -> 7235.1562 | BR41: =BQ41 -> 7235.1562 | BS41: =BR41 -> 7235.1562 | BT41: =BS41 -> 7235.1562 | BU41: =BT41 -> 7235.1562 | BV41: =BU41 -> 7235.1562 | BW41: =BV41 -> 7235.1562 | ... BZ41: =BY41 -> 7235.1562 | CA41: =BZ41*(1+$C$2) -> 7596.9141 | CB41: =CA41 -> 7596.9141 | CC41: =CB41 -> 7596.9141 | CD41: =CC41 -> 7596.9141 | CE41: =CD41 -> 7596.9141 | CF41: =CE41 -> 7596.9141 | CG41: =CF41 -> 7596.9141 | CH41: =CG41 -> 7596.9141 | CI41: =CH41 -> 7596.9141 | ... CL41: =CK41 -> 7596.9141
B42: Client acquisition Specialist | C42: TBH | D42: 115000 | AJ42: =D42/12 -> 9583.3333 | AK42: =AJ42 -> 9583.3333 | AL42: =AK42 -> 9583.3333 | AM42: =AL42 -> 9583.3333 | AN42: =AM42 -> 9583.3333 | AO42: =AN42 -> 9583.3333 | AP42: =AO42 -> 9583.3333 | AQ42: =AP42*(1+$C$2) -> 10062.5 | AR42: =AQ42 -> 10062.5 | AS42: =AR42 -> 10062.5 | AT42: =AS42 -> 10062.5 | AU42: =AT42 -> 10062.5 | AV42: =AU42 -> 10062.5 | AW42: =AV42 -> 10062.5 | AX42: =AW42 -> 10062.5 | AY42: =AX42 -> 10062.5 | ... BB42: =BA42 -> 10062.5 | BC42: =BB42*(1+$C$2) -> 10565.625 | BD42: =BC42 -> 10565.625 | BE42: =BD42 -> 10565.625 | BF42: =BE42 -> 10565.625 | BG42: =BF42 -> 10565.625 | BH42: =BG42 -> 10565.625 | BI42: =BH42 -> 10565.625 | BJ42: =BI42 -> 10565.625 | BK42: =BJ42 -> 10565.625 | ... BN42: =BM42 -> 10565.625 | BO42: =BN42*(1+$C$2) -> 11093.906 | BP42: =BO42 -> 11093.906 | BQ42: =BP42 -> 11093.906 | BR42: =BQ42 -> 11093.906 | BS42: =BR42 -> 11093.906 | BT42: =BS42 -> 11093.906 | BU42: =BT42 -> 11093.906 | BV42: =BU42 -> 11093.906 | BW42: =BV42 -> 11093.906 | ... BZ42: =BY42 -> 11093.906 | CA42: =BZ42*(1+$C$2) -> 11648.602 | CB42: =CA42 -> 11648.602 | CC42: =CB42 -> 11648.602 | CD42: =CC42 -> 11648.602 | CE42: =CD42 -> 11648.602 | CF42: =CE42 -> 11648.602 | CG42: =CF42 -> 11648.602 | CH42: =CG42 -> 11648.602 | CI42: =CH42 -> 11648.602 | ... CL42: =CK42 -> 11648.602
B44: TOTAL | G44: =SUM(G33:G42) -> 0 | H44: =SUM(H33:H42) -> 0 | I44: =SUM(I33:I42) -> 0 | J44: =SUM(J33:J42) -> 0 | K44: =SUM(K33:K42) -> 0 | L44: =SUM(L33:L42) -> 0 | M44: =SUM(M33:M42) -> 0 | N44: =SUM(N33:N42) -> 0 | ... CL44: =SUM(CL33:CL42) -> 90640.872
B46: Operation
B47: CEO | D47: 250000 | O47: 0 | P47: 0 | Q47: 0 | R47: 0 | AJ47: =($D47/12)*(1+$C$2+$C$2) -> 22916.667 | AK47: =($D47/12)*(1+$C$2+$C$2) -> 22916.667 | AL47: =($D47/12)*(1+$C$2+$C$2) -> 22916.667 | AM47: =($D47/12)*(1+$C$2+$C$2) -> 22916.667 | AN47: =($D47/12)*(1+$C$2+$C$2) -> 22916.667 | AO47: =($D47/12)*(1+$C$2+$C$2) -> 22916.667 | AP47: =($D47/12)*(1+$C$2+$C$2) -> 22916.667 | AQ47: =($D47/12)*(1+$C$2+$C$2+$C$2) -> 23958.333 | AR47: =($D47/12)*(1+$C$2+$C$2+$C$2) -> 23958.333 | AS47: =($D47/12)*(1+$C$2+$C$2+$C$2) -> 23958.333 | AT47: =($D47/12)*(1+$C$2+$C$2+$C$2) -> 23958.333 | AU47: =($D47/12)*(1+$C$2+$C$2+$C$2) -> 23958.333 | AV47: =($D47/12)*(1+$C$2+$C$2+$C$2) -> 23958.333 | AW47: =($D47/12)*(1+$C$2+$C$2+$C$2) -> 23958.333 | AX47: =($D47/12)*(1+$C$2+$C$2+$C$2) -> 23958.333 | ... CL47: =($D47/12)*(1+$C$2+$C$2+$C$2) -> 23958.333
B48: CFO | C48: TBH | D48: 100000 | AQ48: =AP48*(1+C3) -> 0 | AR48: =AQ48 -> 0 | AS48: =AR48 -> 0 | AT48: =AS48 -> 0 | AU48: =AT48 -> 0 | AV48: =AU48 -> 0 | AW48: =AV48 -> 0 | AX48: =AW48 -> 0 | AY48: =AX48 -> 0 | ... BB48: =BA48 -> 0 | BC48: =BB48*(1+O3) -> 0 | BD48: =BC48 -> 0 | BE48: =BD48 -> 0 | BF48: =BE48 -> 0 | BG48: =BF48 -> 0 | BH48: =BG48 -> 0 | BI48: =BH48 -> 0 | BJ48: =BI48 -> 0 | BK48: =BJ48 -> 0 | ... BN48: =BM48 -> 0 | BO48: =BN48*(1+AA3) -> 0 | BP48: =BO48 -> 0 | BQ48: =BP48 -> 0 | BR48: =BQ48 -> 0 | BS48: =BR48 -> 0 | BT48: =BS48 -> 0 | BU48: =BT48 -> 0 | BV48: =BU48 -> 0 | BW48: =BV48 -> 0 | ... BZ48: =BY48 -> 0 | CA48: =BZ48*(1+AM3) -> 0 | CB48: =CA48 -> 0 | CC48: =CB48 -> 0 | CD48: =CC48 -> 0 | CE48: =CD48 -> 0 | CF48: =CE48 -> 0 | CG48: =CF48 -> 0 | CH48: =CG48 -> 0 | CI48: =CH48 -> 0 | ... CL48: =CK48 -> 0
B49: Controller | C49: Meryam | D49: 100000 | AA49: =($D49/12)*(1+$C$2) -> 8750 | AB49: =($D49/12)*(1+$C$2) -> 8750 | AC49: =($D49/12)*(1+$C$2) -> 8750 | AD49: =($D49/12)*(1+$C$2) -> 8750 | AE49: =($D49/12)*(1+$C$2+$C$2) -> 9166.6667 | AF49: =($D49/12)*(1+$C$2+$C$2) -> 9166.6667 | AG49: =($D49/12)*(1+$C$2+$C$2) -> 9166.6667 | AH49: =($D49/12)*(1+$C$2+$C$2) -> 9166.6667 | AI49: =($D49/12)*(1+$C$2+$C$2) -> 9166.6667 | AJ49: =($D49/12)*(1+$C$2+$C$2) -> 9166.6667 | AK49: =($D49/12)*(1+$C$2+$C$2) -> 9166.6667 | AL49: =($D49/12)*(1+$C$2+$C$2) -> 9166.6667 | ... AP49: =($D49/12)*(1+$C$2+$C$2) -> 9166.6667 | AQ49: =($D49/12)*(1+$C$2+$C$2+$C$2) -> 9583.3333 | AR49: =($D49/12)*(1+$C$2+$C$2+$C$2) -> 9583.3333 | AS49: =($D49/12)*(1+$C$2+$C$2+$C$2) -> 9583.3333 | AT49: =($D49/12)*(1+$C$2+$C$2+$C$2) -> 9583.3333 | AU49: =($D49/12)*(1+$C$2+$C$2+$C$2) -> 9583.3333 | AV49: =($D49/12)*(1+$C$2+$C$2+$C$2) -> 9583.3333 | AW49: =($D49/12)*(1+$C$2+$C$2+$C$2) -> 9583.3333 | AX49: =($D49/12)*(1+$C$2+$C$2+$C$2) -> 9583.3333 | ... CL49: =($D49/12)*(1+$C$2+$C$2+$C$2) -> 9583.3333
B50: HEAD of Production | C50: TBH | D50: 100000 | AL50: =($D50/12)*(1+$C$2+$C$2) -> 9166.6667 | AM50: =($D50/12)*(1+$C$2+$C$2) -> 9166.6667 | AN50: =($D50/12)*(1+$C$2+$C$2) -> 9166.6667 | AO50: =($D50/12)*(1+$C$2+$C$2) -> 9166.6667 | AP50: =($D50/12)*(1+$C$2+$C$2) -> 9166.6667 | AQ50: =($D50/12)*(1+$C$2+$C$2+$C$2) -> 9583.3333 | AR50: =($D50/12)*(1+$C$2+$C$2+$C$2) -> 9583.3333 | AS50: =($D50/12)*(1+$C$2+$C$2+$C$2) -> 9583.3333 | AT50: =($D50/12)*(1+$C$2+$C$2+$C$2) -> 9583.3333 | AU50: =($D50/12)*(1+$C$2+$C$2+$C$2) -> 9583.3333 | AV50: =($D50/12)*(1+$C$2+$C$2+$C$2) -> 9583.3333 | AW50: =($D50/12)*(1+$C$2+$C$2+$C$2) -> 9583.3333 | AX50: =($D50/12)*(1+$C$2+$C$2+$C$2) -> 9583.3333 | ... CL50: =($D50/12)*(1+$C$2+$C$2+$C$2) -> 9583.3333
B51: HEAD of Pharmacy Operations | C51: Anthony | D51: 150000 | V51: 0 | W51: =($D51/12)*(1+$C$2) -> 13125 | X51: =($D51/12)*(1+$C$2) -> 13125 | Y51: =($D51/12)*(1+$C$2) -> 13125 | Z51: =($D51/12)*(1+$C$2) -> 13125 | AA51: =($D51/12)*(1+$C$2) -> 13125 | AB51: =($D51/12)*(1+$C$2) -> 13125 | AC51: =($D51/12)*(1+$C$2) -> 13125 | AD51: =($D51/12)*(1+$C$2) -> 13125 | AE51: =($D51/12)*(1+$C$2+$C$2) -> 13750 | AF51: =($D51/12)*(1+$C$2+$C$2) -> 13750 | AG51: =($D51/12)*(1+$C$2+$C$2) -> 13750 | AH51: =($D51/12)*(1+$C$2+$C$2) -> 13750 | AI51: =($D51/12)*(1+$C$2+$C$2) -> 13750 | AJ51: =($D51/12)*(1+$C$2+$C$2) -> 13750 | AK51: =($D51/12)*(1+$C$2+$C$2) -> 13750 | AL51: =($D51/12)*(1+$C$2+$C$2) -> 13750 | ... AP51: =($D51/12)*(1+$C$2+$C$2) -> 13750 | AQ51: =($D51/12)*(1+$C$2+$C$2+$C$2) -> 14375 | AR51: =($D51/12)*(1+$C$2+$C$2+$C$2) -> 14375 | AS51: =($D51/12)*(1+$C$2+$C$2+$C$2) -> 14375 | AT51: =($D51/12)*(1+$C$2+$C$2+$C$2) -> 14375 | AU51: =($D51/12)*(1+$C$2+$C$2+$C$2) -> 14375 | AV51: =($D51/12)*(1+$C$2+$C$2+$C$2) -> 14375 | AW51: =($D51/12)*(1+$C$2+$C$2+$C$2) -> 14375 | AX51: =($D51/12)*(1+$C$2+$C$2+$C$2) -> 14375 | ... CL51: =($D51/12)*(1+$C$2+$C$2+$C$2) -> 14375
B52: HR Manager | C52: TBH | D52: 125000 | AM52: =($D52/12)*(1+$C$2+$C$2) -> 11458.333 | AN52: =($D52/12)*(1+$C$2+$C$2) -> 11458.333 | AO52: =($D52/12)*(1+$C$2+$C$2) -> 11458.333 | AP52: =($D52/12)*(1+$C$2+$C$2) -> 11458.333 | AQ52: =($D52/12)*(1+$C$2+$C$2+$C$2) -> 11979.167 | AR52: =($D52/12)*(1+$C$2+$C$2+$C$2) -> 11979.167 | AS52: =($D52/12)*(1+$C$2+$C$2+$C$2) -> 11979.167 | AT52: =($D52/12)*(1+$C$2+$C$2+$C$2) -> 11979.167 | AU52: =($D52/12)*(1+$C$2+$C$2+$C$2) -> 11979.167 | AV52: =($D52/12)*(1+$C$2+$C$2+$C$2) -> 11979.167 | AW52: =($D52/12)*(1+$C$2+$C$2+$C$2) -> 11979.167 | AX52: =($D52/12)*(1+$C$2+$C$2+$C$2) -> 11979.167 | ... CL52: =($D52/12)*(1+$C$2+$C$2+$C$2) -> 11979.167
B53: Data Analyst - Intern | C53: TBH | D53: =4.33*40*35 -> 6062 | E53: per week (70k/year) | W53: =D53 -> 6062 | X53: =W53 -> 6062 | Y53: =X53 -> 6062 | Z53: =Y53 -> 6062
B54: Office Manager | C54: TBH | D54: 75000 | AO54: =D54/12 -> 6250 | AP54: =AO54 -> 6250 | AQ54: =AP54*(1+C2) -> 6562.5 | AR54: =AQ54 -> 6562.5 | AS54: =AR54 -> 6562.5 | AT54: =AS54 -> 6562.5 | AU54: =AT54 -> 6562.5 | AV54: =AU54 -> 6562.5 | AW54: =AV54 -> 6562.5 | AX54: =AW54 -> 6562.5 | AY54: =AX54 -> 6562.5 | ... BB54: =BA54 -> 6562.5 | BC54: =BB54*(1+O2) -> 6562.5 | BD54: =BC54 -> 6562.5 | BE54: =BD54 -> 6562.5 | BF54: =BE54 -> 6562.5 | BG54: =BF54 -> 6562.5 | BH54: =BG54 -> 6562.5 | BI54: =BH54 -> 6562.5 | BJ54: =BI54 -> 6562.5 | BK54: =BJ54 -> 6562.5 | ... BN54: =BM54 -> 6562.5 | BO54: =BN54*(1+AA2) -> 6562.5 | BP54: =BO54 -> 6562.5 | BQ54: =BP54 -> 6562.5 | BR54: =BQ54 -> 6562.5 | BS54: =BR54 -> 6562.5 | BT54: =BS54 -> 6562.5 | BU54: =BT54 -> 6562.5 | BV54: =BU54 -> 6562.5 | BW54: =BV54 -> 6562.5 | ... BZ54: =BY54 -> 6562.5 | CA54: =BZ54*(1+AM2) -> 6562.5 | CB54: =CA54 -> 6562.5 | CC54: =CB54 -> 6562.5 | CD54: =CC54 -> 6562.5 | CE54: =CD54 -> 6562.5 | CF54: =CE54 -> 6562.5 | CG54: =CF54 -> 6562.5 | CH54: =CG54 -> 6562.5 | CI54: =CH54 -> 6562.5 | ... CL54: =CK54 -> 6562.5
B57: TOTAL | G57: =SUM(G47:G54) -> 0 | H57: =SUM(H47:H54) -> 0 | I57: =SUM(I47:I54) -> 0 | J57: =SUM(J47:J54) -> 0 | K57: =SUM(K47:K54) -> 0 | L57: =SUM(L47:L54) -> 0 | M57: =SUM(M47:M54) -> 0 | N57: =SUM(N47:N54) -> 0 | ... CL57: =SUM(CL47:CL54) -> 76041.667
B60: TOTAL SALARIES
A64: Contractor
B66: Stagiaire AI Ulaval | C66: Ndongo | E66: Mitac | U66: 15000
B67: Lead DS and AI | C67: Nico | E67: Momentum and direct | T67: =4.33*8*125 -> 4330 | U67: =4.33*8*125 -> 4330 | V67: =4.33*8*125 -> 4330
B68: Software Developer | C68: Naomi | S68: =40*4.33*33 -> 5715.6 | T68: =40*4.33*33 -> 5715.6 | U68: =40*4.33*33 -> 5715.6 | V68: =40*4.33*33 -> 5715.6
B71: Contractual Tech Total | S71: =SUM(S66:S70) -> 5715.6 | T71: =SUM(T66:T70) -> 10045.6 | U71: =SUM(U66:U70) -> 25045.6 | V71: =SUM(V66:V70) -> 10045.6 | W71: =SUM(W66:W70) -> 0 | X71: =SUM(X66:X70) -> 0 | Y71: =SUM(Y66:Y70) -> 0 | Z71: =SUM(Z66:Z70) -> 0 | ... CL71: =SUM(CL66:CL70) -> 0
B74: CEO | D74: 180000 | O74: 0 | P74: 0 | Q74: 0 | R74: 0 | S74: =($D74/12)*(1+$C$2) -> 15750 | T74: =($D74/12)*(1+$C$2) -> 15750 | U74: =($D74/12)*(1+$C$2) -> 15750 | V74: =($D74/12)*(1+$C$2) -> 15750
B75: CRO | C75: Simon | D75: 175000 | S75: =D75/12 -> 14583.333 | T75: =S75 -> 14583.333 | U75: =T75 -> 14583.333 | V75: =U75 -> 14583.333
B76: Data Analyst | C76: Yasser | D76: 80000 | S76: =($D76/12)*(1+$C$2) -> 7000 | T76: =($D76/12)*(1+$C$2) -> 7000 | U76: =($D76/12)*(1+$C$2) -> 7000
B77: Project Owner | C77: TG - Véro | D77: 108000 | S77: 0 | T77: 0 | U77: 0 | Y77: =863*4 -> 3452 | Z77: =863*4 -> 3452 | AA77: =863*4 -> 3452
B78: Marketing Manager | C78: TG - Isabelle | D78: =5000*12 -> 60000 | R78: 0
B79: Controller Temporaire | U79: 7500 | V79: 7500 | W79: 7500 | X79: 7500 | Y79: 7500 | Z79: 7500
B80: CFO Fractional | C80: TBH | D80: =250*200 -> 50000 | E80: 250h/année_200$/h | O80: 5000 | P80: 5000 | Q80: 5000 | R80: 10000 | V80: =40000/12 -> 3333.3333 | W80: =40000/12 -> 3333.3333 | X80: =40000/12 -> 3333.3333 | Y80: =40000/12 -> 3333.3333 | Z80: =40000/12 -> 3333.3333 | AA80: =40000/12 -> 3333.3333 | AB80: =40000/12 -> 3333.3333
B82: Contractual Operations Total | S82: =SUM(S74:S81) -> 37333.333 | T82: =SUM(T74:T81) -> 37333.333 | U82: =SUM(U74:U81) -> 44833.333 | V82: =SUM(V74:V81) -> 41166.667 | W82: =SUM(W74:W81) -> 10833.333 | X82: =SUM(X74:X81) -> 10833.333 | Y82: =SUM(Y74:Y81) -> 14285.333 | Z82: =SUM(Z74:Z81) -> 14285.333 | ... CL82: =SUM(CL74:CL81) -> 0
B85: Consultants - TOTAL | S85: =+S71+S82 -> 43048.933 | T85: =+T71+T82 -> 47378.933 | U85: =+U71+U82 -> 69878.933 | V85: =+V71+V82 -> 51212.267 | W85: =+W71+W82 -> 10833.333 | X85: =+X71+X82 -> 10833.333 | Y85: =+Y71+Y82 -> 14285.333 | Z85: =+Z71+Z82 -> 14285.333 | ... CL85: =+CL71+CL82 -> 0

Sheet Loans & Grants
B3: LOAN | G3: 2022 | S3: 2023 | AE3: 2024 | AQ3: 2025 | BC3: 2026 | BO3: 2027 | CA3: 2028
G4: 44562 | H4: 44593 | I4: 44621 | J4: 44652 | K4: 44682 | L4: 44713 | M4: 44743 | N4: 44774 | O4: 44805 | P4: 44835 | Q4: 44866 | R4: 44896 | S4: 44927 | T4: 44958 | U4: 44986 | V4: 45017 | W4: 45047 | X4: 45078 | Y4: 45108 | Z4: 45139 | AA4: 45170 | AB4: 45200 | AC4: 45231 | AD4: 45261 | AE4: 45292 | AF4: 45323 | AG4: 45352 | AH4: 45383 | AI4: 45413 | AJ4: 45444 | AK4: 45474 | AL4: 45505 | AM4: 45536 | AN4: 45566 | AO4: 45597 | AP4: 45627 | AQ4: 45658 | AR4: 45689 | AS4: 45717 | AT4: 45748 | AU4: 45778 | AV4: 45809 | AW4: 45839 | AX4: 45870 | AY4: 45901 | AZ4: 45931 | BA4: 45962 | BB4: 45992 | BC4: 45658 | BD4: 45689 | BE4: 45717 | BF4: 45748 | BG4: 45778 | BH4: 45809 | BI4: 45839 | BJ4: 45870 | BK4: 45901 | BL4: 45931 | BM4: 45962 | BN4: 45992 | BO4: 45658 | BP4: 45689 | BQ4: 45717 | BR4: 45748 | BS4: 45778 | BT4: 45809 | BU4: 45839 | BV4: 45870 | BW4: 45901 | BX4: 45931 | BY4: 45962 | BZ4: 45992 | CA4: 45658 | CB4: 45689 | CC4: 45717 | CD4: 45748 | CE4: 45778 | CF4: 45809 | CG4: 45839 | CH4: 45870 | CI4: 45901 | CJ4: 45931 | CK4: 45962 | CL4: 45992
B7: Creditor | C7: Value | D7: Rate | E7: Period (no of months)
B9: BDC | C9: 185000 | D9: 0.087 | E9: 60
E10: Solde | Q10: 185000 | R10: 185000 | S10: 185000 | T10: 185000 | U10: 185000 | V10: 185000 | W10: 185000 | X10: =+W10+W11 -> 185000 | Y10: =+X10+X11 -> 185000 | Z10: =+Y10+Y11 -> 185000 | AA10: =+Z10+Z11 -> 185000 | AB10: =+AA10+AA11 -> 185000 | AC10: =+AB10+AB11 -> 185000 | AD10: =+AC10+AC11 -> 185000 | AE10: =+AD10+AD11 -> 185000 | ... BP10: =+BO10+BO11 -> 3000
E11: Capital | Q11: 0 | R11: 0 | S11: 0 | T11: 0 | U11: 0 | V11: 0 | W11: 0 | X11: =W11 -> 0 | Y11: =X11 -> 0 | Z11: =Y11 -> 0 | AA11: =Z11 -> 0 | AB11: =AA11 -> 0 | AC11: =AB11 -> 0 | AD11: =AC11 -> 0 | AE11: =AD11 -> 0 | AF11: =AE11 -> 0 | AG11: -5200 | AH11: =AG11 -> -5200 | AI11: =AH11 -> -5200 | AJ11: =AI11 -> -5200 | AK11: =AJ11 -> -5200 | AL11: =AK11 -> -5200 | AM11: =AL11 -> -5200 | AN11: =AM11 -> -5200 | AO11: =AN11 -> -5200 | ... BO11: =BN11 -> -5200 | BP11: 3000
E12: Interest | Q12: -1560 | R12: -1560 | S12: -1560 | T12: -1560 | U12: -1560 | V12: -1560 | W12: =-(W10+W11)*$D$9/12 -> -1341.25 | X12: =-(X10+X11)*$D$9/12 -> -1341.25 | Y12: =-(Y10+Y11)*$D$9/12 -> -1341.25 | Z12: =-(Z10+Z11)*$D$9/12 -> -1341.25 | AA12: =-(AA10+AA11)*$D$9/12 -> -1341.25 | AB12: =-(AB10+AB11)*$D$9/12 -> -1341.25 | AC12: =-(AC10+AC11)*$D$9/12 -> -1341.25 | AD12: =-(AD10+AD11)*$D$9/12 -> -1341.25 | ... BO12: =-(BO10+BO11)*$D$9/12 -> -21.75 | BP12: 0
B15: PME Montreal | C15: 216000 | D15: 0.09 | E15: 48
C16: Divided into 4 loans | E16: Solde | Q16: 236000 | R16: 236000 | S16: 236000 | T16: 236000 | U16: 236000 | V16: 236000 | W16: 236000 | X16: =+W16+W17 -> 230800 | Y16: =+X16+X17 -> 225600 | Z16: =+Y16+Y17 -> 220400 | AA16: =+Z16+Z17 -> 215200 | AB16: =+AA16+AA17 -> 210000 | AC16: =+AB16+AB17 -> 204800 | AD16: =+AC16+AC17 -> 199600 | AE16: =+AD16+AD17 -> 194400 | ... BP16: =+BO16+BO17 -> 2000
E17: Capital | Q17: 0 | R17: 0 | S17: 0 | T17: 0 | U17: 0 | V17: 0 | W17: -5200 | X17: =W17 -> -5200 | Y17: =X17 -> -5200 | Z17: =Y17 -> -5200 | AA17: =Z17 -> -5200 | AB17: =AA17 -> -5200 | AC17: =AB17 -> -5200 | AD17: =AC17 -> -5200 | AE17: =AD17 -> -5200 | ... BO17: =BN17 -> -5200 | BP17: 2000
E18: Interest | Q18: =Q16*$D15/12 -> 1770 | R18: -1560 | S18: -1560 | T18: -1560 | U18: -1560 | V18: -1560 | W18: =-(W16+W17)*$D$15/12 -> -1731 | X18: =-(X16+X17)*$D$15/12 -> -1692 | Y18: =-(Y16+Y17)*$D$15/12 -> -1653 | Z18: =-(Z16+Z17)*$D$15/12 -> -1614 | AA18: =-(AA16+AA17)*$D$15/12 -> -1575 | AB18: =-(AB16+AB17)*$D$15/12 -> -1536 | AC18: =-(AC16+AC17)*$D$15/12 -> -1497 | AD18: =-(AD16+AD17)*$D$15/12 -> -1458 | ... BO18: =-(BO16+BO17)*$D$15/12 -> -15 | BP18: 0
B20: Other | C20: 0 | D20: 0.12 | E20: 60
E21: Solde
E22: Capital
E23: Interest
E27: Capital Balance | Q27: =+Q10+Q16+Q21 -> 421000 | R27: =+R10+R16+R21 -> 421000 | S27: =+S10+S16+S21 -> 421000 | T27: =+T10+T16+T21 -> 421000 | U27: =+U10+U16+U21 -> 421000 | V27: =+V10+V16+V21 -> 421000 | W27: =+W10+W16+W21 -> 421000 | X27: =+X10+X16+X21 -> 415800 | ... CL27: =+CL10+CL16+CL21 -> 0
E28: Capital Payments | Q28: =+Q11+Q17+Q22 -> 0 | R28: =+R11+R17+R22 -> 0 | S28: =+S11+S17+S22 -> 0 | T28: =+T11+T17+T22 -> 0 | U28: =+U11+U17+U22 -> 0 | V28: =+V11+V17+V22 -> 0 | W28: =+W11+W17+W22 -> -5200 | X28: =+X11+X17+X22 -> -5200 | ... CL28: =+CL11+CL17+CL22 -> 0
E29: Interest Payments | Q29: =+Q12+Q18+Q23 -> 210 | R29: =+R12+R18+R23 -> -3120 | S29: =+S12+S18+S23 -> -3120 | T29: =+T12+T18+T23 -> -3120 | U29: =+U12+U18+U23 -> -3120 | V29: =+V12+V18+V23 -> -3120 | W29: =+W12+W18+W23 -> -3072.25 | X29: =+X12+X18+X23 -> -3033.25 | ... CL29: =+CL12+CL18+CL23 -> 0
B31: TOTAL | N31: =SUM(N9:N24) -> 0 | O31: =SUM(O9:O24) -> 0 | P31: =SUM(P9:P24) -> 0 | Q31: =SUM(Q9:Q24) -> 421210 | R31: =SUM(R9:R24) -> 417880 | S31: =SUM(S9:S24) -> 417880 | T31: =SUM(T9:T24) -> 417880 | U31: =SUM(U9:U24) -> 417880 | ... CL31: =SUM(CL9:CL24) -> 0
B34: GRANTS | G34: 2022 | S34: 2023 | AE34: 2024 | AQ34: 2025 | BC34: 2026 | BO34: 2027 | CA34: 2028
G35: 44562 | H35: 44593 | I35: 44621 | J35: 44652 | K35: 44682 | L35: 44713 | M35: 44743 | N35: 44774 | O35: 44805 | P35: 44835 | Q35: 44866 | R35: 44896 | S35: 44927 | T35: 44958 | U35: 44986 | V35: 45017 | W35: 45047 | X35: 45078 | Y35: 45108 | Z35: 45139 | AA35: 45170 | AB35: 45200 | AC35: 45231 | AD35: 45261 | AE35: 45292 | AF35: 45323 | AG35: 45352 | AH35: 45383 | AI35: 45413 | AJ35: 45444 | AK35: 45474 | AL35: 45505 | AM35: 45536 | AN35: 45566 | AO35: 45597 | AP35: 45627 | AQ35: 45658 | AR35: 45689 | AS35: 45717 | AT35: 45748 | AU35: 45778 | AV35: 45809 | AW35: 45839 | AX35: 45870 | AY35: 45901 | AZ35: 45931 | BA35: 45962 | BB35: 45992 | BC35: 45658 | BD35: 45689 | BE35: 45717 | BF35: 45748 | BG35: 45778 | BH35: 45809 | BI35: 45839 | BJ35: 45870 | BK35: 45901 | BL35: 45931 | BM35: 45962 | BN35: 45992 | BO35: 45658 | BP35: 45689 | BQ35: 45717 | BR35: 45748 | BS35: 45778 | BT35: 45809 | BU35: 45839 | BV35: 45870 | BW35: 45901 | BX35: 45931 | BY35: 45962 | BZ35: 45992 | CA35: 45658 | CB35: 45689 | CC35: 45717 | CD35: 45748 | CE35: 45778 | CF35: 45809 | CG35: 45839 | CH35: 45870 | CI35: 45901 | CJ35: 45931 | CK35: 45962 | CL35: 45992
B38: Grant | C38: Value
B40: PARI | C40: 150000 | D40: 75% chance
B41: SRED (estimate) - could finance | C41: 0 | D41: in process | S41: 37000 | X41: 70169 | AH41: ='RSDE-CDAE Estimation'!D104 -> 185033.19 | AT41: =AH41 -> 185033.19 | BF41: =AT41 -> 185033.19 | BR41: =BF41 -> 185033.19 | CD41: =BR41 -> 185033.19
B42: CDAE (estimate) - could finance | C42: 0 | D42: in process | AK42: ='RSDE-CDAE Estimation'!D105 -> 230699.4 | AW42: ='RSDE-CDAE Estimation'!D105 -> 230699.4 | BI42: ='RSDE-CDAE Estimation'!D105 -> 230699.4 | BR42: =BF42 -> 0 | CD42: =BR42 -> 0
B43: MEI AI | C43: 150000 | D43: approved | Q43: 105000 | AG43: 45000
B44: Scale AI | C44: 500000 | D44: 90% chance | AO44: 250000 | AU44: 250000
B45: MEI-AI (2) | C45: 350000 | D45: 75% chance | AU45: 175000 | BA45: 175000
B46: PSCE - 2 | C46: 250000 | D46: in approval process | AJ46: 25000 | AK46: 25000 | AL46: 25000 | AM46: 25000 | AN46: 25000 | AO46: 25000 | AP46: 25000 | AQ46: 25000 | AR46: 25000 | AS46: 25000 | AT46: 25000
B47: PCAN | C47: 100000 | D47: in approval process 90% chance | AJ47: 100000
B48: Medteq | C48: 500000 | D48: 35% chance | AL48: 150000 | AR48: 150000
B50: TOTAL | C50: =SUM(C40:C45) -> 1150000 | N50: =SUM(N40:N48) -> 0 | O50: =SUM(O40:O48) -> 0 | P50: =SUM(P40:P48) -> 0 | Q50: =SUM(Q40:Q48) -> 105000 | R50: =SUM(R40:R48) -> 0 | S50: =SUM(S40:S48) -> 37000 | T50: =SUM(T40:T48) -> 0 | U50: =SUM(U40:U48) -> 0 | ... CL50: =SUM(CL40:CL48) -> 0

Sheet RSDE-CDAE Estimation
B2: Projections de crédits d'impôt à recevoir
B3: Medzy Inc.
B4: Exercice financier se terminant le 31 octobre 2023 - 2024 - 2025
J7: Calcul salaire | Q7: Calcul RS&DE | S7: Calcul CDAE
A8: No | B8: Nom de l'employé | C8: Employé déterminé? | D8: Titre du poste | F8: CDAE | G8: Date début | H8: Date fin | I8: RS&DE provinciale | J8: Jours admissibles | K8: Salaire | L8: Avantages imposables | M8: Bonis | N8: Salaire total | O8: Heures travaillées | P8: Subventions | Q8: Pourcentage RS&DE | R8: Dépense admissible | S8: Limite annuelle | T8: Salaire admissible sans R&D
A9: 1 | B9: Total | C9: NON | D9: Tech Salaries | F9: x | G9: 44866 | H9: 45230 | I9: OUI | J9: =IF(F9="",0,(H9-G9+1)) -> 365 | K9: 175000 | N9: =+K9+L9+M9 -> 175000 | Q9: 0.35 | R9: =Q9*N9 -> 61250 | S9: =((J9/365)*83333) -> 83333 | T9: =MIN(S9,N9-P9) -> 83333
A10: 1 | F10: x | G10: 44866 | H10: 45230 | I10: OUI | J10: =IF(F10="",0,(H10-G10+1)) -> 365 | K10: 145000 | N10: =+K10+L10+M10 -> 145000 | Q10: 0.35 | R10: =Q10*N10 -> 50750 | S10: =((J10/365)*83333) -> 83333 | T10: =MIN(S10,N10-P10) -> 83333
A11: 2 | F11: x | G11: 44866 | H11: 45230 | I11: OUI | J11: =IF(F11="",0,(H11-G11+1)) -> 365 | K11: 118000 | N11: =+K11+L11+M11 -> 118000 | Q11: 0.35 | R11: =Q11*N11 -> 41300 | S11: =((J11/365)*83333) -> 83333 | T11: =MIN(S11,N11-P11) -> 83333
A12: 3 | F12: x | G12: 44866 | H12: 45230 | I12: OUI | J12: =IF(F12="",0,(H12-G12+1)) -> 365 | K12: 117500 | N12: =+K12+L12+M12 -> 117500 | Q12: 0.35 | R12: =Q12*N12 -> 41125 | S12: =((J12/365)*83333) -> 83333 | T12: =MIN(S12,N12-P12) -> 83333
A13: 4 | F13: x | G13: 44866 | H13: 45230 | I13: OUI | J13: =IF(F13="",0,(H13-G13+1)) -> 365 | K13: 110000 | N13: =+K13+L13+M13 -> 110000 | Q13: 0.35 | R13: =Q13*N13 -> 38500 | S13: =((J13/365)*83333) -> 83333 | T13: =MIN(S13,N13-P13) -> 83333
A14: 5 | F14: x | G14: 44866 | H14: 45230 | I14: OUI | J14: =IF(F14="",0,(H14-G14+1)) -> 365 | K14: 100000 | N14: =+K14+L14+M14 -> 100000 | Q14: 0.35 | R14: =Q14*N14 -> 35000 | S14: =((J14/365)*83333) -> 83333 | T14: =MIN(S14,N14-P14) -> 83333
A15: 6 | F15: x | G15: 44866 | H15: 45230 | I15: OUI | J15: =IF(F15="",0,(H15-G15+1)) -> 365 | K15: 81000 | N15: =+K15+L15+M15 -> 81000 | Q15: 0.35 | R15: =Q15*N15 -> 28350 | S15: =((J15/365)*83333) -> 83333 | T15: =MIN(S15,N15-P15) -> 81000
A16: 7 | F16: x | G16: 44866 | H16: 45230 | I16: OUI | J16: =IF(F16="",0,(H16-G16+1)) -> 365 | K16: 58000 | N16: =+K16+L16+M16 -> 58000 | Q16: 0.35 | R16: =Q16*N16 -> 20300 | S16: =((J16/365)*83333) -> 83333 | T16: =MIN(S16,N16-P16) -> 58000
A17: 8 | F17: x | G17: 44866 | H17: 45230 | I17: OUI | J17: =IF(F17="",0,(H17-G17+1)) -> 365 | K17: 70000 | N17: =+K17+L17+M17 -> 70000 | Q17: 0.35 | R17: =Q17*N17 -> 24500 | S17: =((J17/365)*83333) -> 83333 | T17: =MIN(S17,N17-P17) -> 70000
A18: 9 | F18: x | G18: 44866 | H18: 45230 | I18: OUI | J18: =IF(F18="",0,(H18-G18+1)) -> 365 | K18: 60000 | N18: =+K18+L18+M18 -> 60000 | Q18: 0.35 | R18: =Q18*N18 -> 21000 | S18: =((J18/365)*83333) -> 83333 | T18: =MIN(S18,N18-P18) -> 60000
A19: 10 | F19: x | G19: 44866 | H19: 45230 | I19: OUI | J19: =IF(F19="",0,(H19-G19+1)) -> 365 | N19: =+K19+L19+M19 -> 0 | Q19: 0.35 | R19: =Q19*N19 -> 0 | S19: =((J19/365)*83333) -> 83333 | T19: =MIN(S19,N19-P19) -> 0
A20: 11 | F20: x | G20: 44866 | H20: 45230 | I20: OUI | J20: =IF(F20="",0,(H20-G20+1)) -> 365 | N20: =+K20+L20+M20 -> 0 | Q20: 0.35 | R20: =Q20*N20 -> 0 | S20: =((J20/365)*83333) -> 83333 | T20: =MIN(S20,N20-P20) -> 0
A21: 12
A22: 12
A23: 10 | I23: =IF(F23="X","NON","OUI") -> OUI | J23: =IF(F23="",0,(H23-G23+1)) -> 0 | N23: =+K23+L23+M23 -> 0 | R23: =Q23*N23 -> 0 | S23: =((J23/365)*83333) -> 0 | T23: =MIN(S23,N23-P23) -> 0
A24: 11 | I24: =IF(F24="X","NON","OUI") -> OUI | J24: =IF(F24="",0,(H24-G24+1)) -> 0 | N24: =+K24+L24+M24 -> 0 | R24: =Q24*N24 -> 0 | S24: =((J24/365)*83333) -> 0 | T24: =MIN(S24,N24-P24) -> 0
A25: 12 | I25: =IF(F25="X","NON","OUI") -> OUI | J25: =IF(F25="",0,(H25-G25+1)) -> 0 | N25: =+K25+L25+M25 -> 0 | R25: =Q25*N25 -> 0 | S25: =((J25/365)*83333) -> 0 | T25: =MIN(S25,N25-P25) -> 0
A26: 13 | I26: =IF(F26="X","NON","OUI") -> OUI | J26: =IF(F26="",0,(H26-G26+1)) -> 0 | N26: =+K26+L26+M26 -> 0 | R26: =Q26*N26 -> 0 | S26: =((J26/365)*83333) -> 0 | T26: =MIN(S26,N26-P26) -> 0
A27: 14 | I27: =IF(F27="X","NON","OUI") -> OUI | J27: =IF(F27="",0,(H27-G27+1)) -> 0 | N27: =+K27+L27+M27 -> 0 | R27: =Q27*N27 -> 0 | S27: =((J27/365)*83333) -> 0 | T27: =MIN(S27,N27-P27) -> 0
A28: 15 | I28: =IF(F28="X","NON","OUI") -> OUI | J28: =IF(F28="",0,(H28-G28+1)) -> 0 | N28: =+K28+L28+M28 -> 0 | R28: =Q28*N28 -> 0 | S28: =((J28/365)*83333) -> 0 | T28: =MIN(S28,N28-P28) -> 0
A29: 16 | I29: =IF(F29="X","NON","OUI") -> OUI | J29: =IF(F29="",0,(H29-G29+1)) -> 0 | N29: =+K29+L29+M29 -> 0 | R29: =Q29*N29 -> 0 | S29: =((J29/365)*83333) -> 0 | T29: =MIN(S29,N29-P29) -> 0
A30: 17 | I30: =IF(F30="X","NON","OUI") -> OUI | J30: =IF(F30="",0,(H30-G30+1)) -> 0 | N30: =+K30+L30+M30 -> 0 | R30: =Q30*N30 -> 0 | S30: =((J30/365)*83333) -> 0 | T30: =MIN(S30,N30-P30) -> 0
A31: 18 | I31: =IF(F31="X","NON","OUI") -> OUI | J31: =IF(F31="",0,(H31-G31+1)) -> 0 | N31: =+K31+L31+M31 -> 0 | R31: =Q31*N31 -> 0 | S31: =((J31/365)*83333) -> 0 | T31: =MIN(S31,N31-P31) -> 0
A32: 19 | I32: =IF(F32="X","NON","OUI") -> OUI | J32: =IF(F32="",0,(H32-G32+1)) -> 0 | N32: =+K32+L32+M32 -> 0 | R32: =Q32*N32 -> 0 | S32: =((J32/365)*83333) -> 0 | T32: =MIN(S32,N32-P32) -> 0
A33: 20 | I33: =IF(F33="X","NON","OUI") -> OUI | J33: =IF(F33="",0,(H33-G33+1)) -> 0 | N33: =+K33+L33+M33 -> 0 | R33: =Q33*N33 -> 0 | S33: =((J33/365)*83333) -> 0 | T33: =MIN(S33,N33-P33) -> 0
A34: 21 | I34: =IF(F34="X","NON","OUI") -> OUI | J34: =IF(F34="",0,(H34-G34+1)) -> 0 | N34: =+K34+L34+M34 -> 0 | R34: =Q34*N34 -> 0 | S34: =((J34/365)*83333) -> 0 | T34: =MIN(S34,N34-P34) -> 0
... A88: 75 | I88: =IF(F88="X","NON","OUI") -> OUI | J88: =IF(F88="",0,(H88-G88+1)) -> 0 | N88: =+K88+L88+M88 -> 0 | R88: =Q88*N88 -> 0 | S88: =((J88/365)*83333) -> 0 | T88: =MIN(S88,N88-P88) -> 0
B89: Totaux | F89: =SUM(F9:F22) -> 0 | G89: =SUM(G9:G22) -> 538392 | H89: =SUM(H9:H22) -> 542760 | I89: =SUM(I9:I22) -> 0 | J89: =SUM(J9:J22) -> 4380 | K89: =SUM(K9:K22) -> 1034500 | L89: =SUM(L9:L22) -> 0 | M89: =SUM(M9:M22) -> 0 | N89: =SUM(N9:N22) -> 1034500 | R89: =SUM(R9:R88) -> 362075 | T89: =SUM(T9:T88) -> 768998
B92: Calcul du crédit RS&DE :
B93: Dépenses admissibles :
B94: Crédit d'impôt RS&DE (provincial) : | D94: ='[1]Calcul des CRÉDITS'!H18 -> 0
B95: Crédit d'impôt RS&DE (fédéral) : | D95: ='[1]Calcul des CRÉDITS'!H36 -> 185033.19
B96: Crédit total : | D96: =D95+D94 -> 185033.19
B97: Calcul du crédit CDAE :
B98: Dépenses admissibles : | D98: =T89 -> 768998
B99: Crédit d'impôt CDAE (remboursable) : | D99: =D98*0.24 -> 184559.52
B100: Crédit d'impôt CDAE (non-remboursable) : | D100: =D98*0.06 -> 46139.88
B102: Crédit total : | D102: =D100+D99 -> 230699.4
B103: Total des crédits :
B104: RS&DE : | D104: =D96 -> 185033.19
B105: CDAE : | D105: =D102 -> 230699.4
B106: Crédits totaux : | D106: =D105+D104 -> 415732.59
B113: IRAP | D113: ='Loans & Grants'!C40 -> 150000
B115: Validation
B116: Total CDAE + RSDE + IRAP + MEI AI | D116: =+D113+D106+'Loans & Grants'!C43 -> 715732.59
B117: Total en %age salaires | D117: =+D116/K89 -> 0.6918633 | E117: Max 65%-70%

Sheet Marketing and Sales
B2: TOTAL | F2: 2022 | R2: 2023 | AD2: 2024 | AP2: 2025 | BB2: 2026 | BN2: 2027 | BZ2: 2028
F3: 1 | G3: 2 | H3: 3 | I3: 4 | J3: 5 | K3: 6 | L3: 7 | M3: 8 | N3: 9 | O3: 10 | P3: 44866 | Q3: 44896 | R3: 44927 | S3: 44958 | T3: 44986 | U3: 45017 | V3: 45047 | W3: 45078 | X3: 45108 | Y3: 45139 | Z3: 45170 | AA3: 45200 | AB3: 45231 | AC3: 45261 | AD3: 45292 | AE3: 45323 | AF3: 45352 | AG3: 45383 | AH3: 45413 | AI3: 45444 | AJ3: 45474 | AK3: 45505 | AL3: 45536 | AM3: 45566 | AN3: 45597 | AO3: 45627 | AP3: 45658 | AQ3: 45689 | AR3: 45717 | AS3: 45748 | AT3: 45778 | AU3: 45809 | AV3: 45839 | AW3: 45870 | AX3: 45901 | AY3: 45931 | AZ3: 45962 | BA3: 45992 | BB3: 45658 | BC3: 45689 | BD3: 45717 | BE3: 45748 | BF3: 45778 | BG3: 45809 | BH3: 45839 | BI3: 45870 | BJ3: 45901 | BK3: 45931 | BL3: 45962 | BM3: 45992 | BN3: 45658 | BO3: 45689 | BP3: 45717 | BQ3: 45748 | BR3: 45778 | BS3: 45809 | BT3: 45839 | BU3: 45870 | BV3: 45901 | BW3: 45931 | BX3: 45962 | BY3: 45992 | BZ3: 45658 | CA3: 45689 | CB3: 45717 | CC3: 45748 | CD3: 45778 | CE3: 45809 | CF3: 45839 | CG3: 45870 | CH3: 45901 | CI3: 45931 | CJ3: 45962 | CK3: 45992
B5: New Clients | R5: =R32+R42+R54+R66+R78+R91+R104+R116+R128 -> 103.47826 | S5: =S32+S42+S54+S66+S78+S91+S104+S116+S128 -> 83.478261 | T5: =T32+T42+T54+T66+T78+T91+T104+T116+T128 -> 61.73913 | U5: =U32+U42+U54+U66+U78+U91+U104+U116+U128 -> 62.727273 | V5: =V32+V42+V54+V66+V78+V91+V104+V116+V128 -> 102.72727 | W5: =W32+W42+W54+W66+W78+W91+W104+W116+W128 -> 106.72727 | X5: =X32+X42+X54+X66+X78+X91+X104+X116+X128 -> 129.80952 | Y5: =Y32+Y42+Y54+Y66+Y78+Y91+Y104+Y116+Y128 -> 151.80952 | ... BA5: =BA32+BA42+BA54+BA66+BA78+BA91+BA104+BA116+BA128 -> 3361.0667 | BB5: =BB32+BB42+BB54+BB66+BB78+BB91+BB104+BB116+BB128+BB176 -> 3745.2706 | BC5: =BC32+BC42+BC54+BC66+BC78+BC91+BC104+BC116+BC128+BC176 -> 3879.6706 | BD5: =BD32+BD42+BD54+BD66+BD78+BD91+BD104+BD116+BD128+BD176 -> 4037.6 | BE5: =BE32+BE42+BE54+BE66+BE78+BE91+BE104+BE116+BE128+BE176 -> 4172 | BF5: =BF32+BF42+BF54+BF66+BF78+BF91+BF104+BF116+BF128+BF176 -> 4306.4 | BG5: =BG32+BG42+BG54+BG66+BG78+BG91+BG104+BG116+BG128+BG176 -> 4440.8 | BH5: =BH32+BH42+BH54+BH66+BH78+BH91+BH104+BH116+BH128+BH176 -> 4601.8667 | BI5: =BI32+BI42+BI54+BI66+BI78+BI91+BI104+BI116+BI128+BI176 -> 4736.2667 | ... CK5: =CK32+CK42+CK54+CK66+CK78+CK91+CK104+CK116+CK128+CK176 -> 8499.4667
B6: Churn | R6: =R33+R43+R55+R67+R79+R92+R105+R117 -> 72.388092 | S6: =S33+S43+S55+S67+S79+S92+S105+S117 -> 75.442686 | T6: =T33+T43+T55+T67+T79+T92+T105+T117 -> 75.992903 | U6: =U33+U43+U55+U67+U79+U92+U105+U117 -> 75.758976 | V6: =V33+V43+V55+V67+V79+V92+V105+V117 -> 75.539271 | W6: =W33+W43+W55+W67+W79+W92+W105+W117 -> 75.323141 | X6: =X33+X43+X55+X67+X79+X92+X105+X117 -> 75.810648 | Y6: =Y33+Y43+Y55+Y67+Y79+Y92+Y105+Y117 -> 76.320674 | ... BA6: =BA33+BA43+BA55+BA67+BA79+BA92+BA105+BA117 -> 638.47378 | BB6: =BB33+BB43+BB55+BB67+BB79+BB92+BB105+BB117+BB177 -> 737.66671 | BC6: =BC33+BC43+BC55+BC67+BC79+BC92+BC105+BC117+BC177 -> 792.98955 | BD6: =BD33+BD43+BD55+BD67+BD79+BD92+BD105+BD117+BD177 -> 849.74593 | BE6: =BE33+BE43+BE55+BE67+BE79+BE92+BE105+BE117+BE177 -> 908.3086 | BF6: =BF33+BF43+BF55+BF67+BF79+BF92+BF105+BF117+BF177 -> 968.22106 | BG6: =BG33+BG43+BG55+BG67+BG79+BG92+BG105+BG117+BG177 -> 1029.4472 | BH6: =BH33+BH43+BH55+BH67+BH79+BH92+BH105+BH117+BH177 -> 1091.9523 | BI6: =BI33+BI43+BI55+BI67+BI79+BI92+BI105+BI117+BI177 -> 1156.1694 | ... CK6: =CK33+CK43+CK55+CK67+CK79+CK92+CK105+CK117+CK177 -> 3345.2054
B7: Total Clients | R7: =R34+R44+R56+R68+R80+R93+R106+R118 -> 4362.6939 | S7: =S34+S44+S56+S68+S80+S93+S106+S118 -> 4370.7295 | T7: =T34+T44+T56+T68+T80+T93+T106+T118 -> 4356.4757 | U7: =U34+U44+U56+U68+U80+U93+U106+U118 -> 4343.444 | V7: =V34+V44+V56+V68+V80+V93+V106+V118 -> 4370.632 | W7: =W34+W44+W56+W68+W80+W93+W106+W118 -> 4398.0362 | X7: =X34+X44+X56+X68+X80+X93+X106+X118 -> 4446.035 | Y7: =Y34+Y44+Y56+Y68+Y80+Y93+Y106+Y118 -> 4513.5239 | ... CK7: =CK34+CK44+CK56+CK68+CK80+CK93+CK106+CK118 -> 177380.24
B8: Sales (Pharmacy) | P8: 375747.67 | Q8: 359175 | R8: 401284.28 | S8: =S36+S46+S58+S70+S82+S95+S108+S120+S132+S144+S156+S168 -> 395821.8 | T8: =T36+T46+T58+T70+T82+T95+T108+T120+T132+T144+T156+T168 -> 393096.67 | U8: 436144.26 | V8: 429750.16 | W8: 407798.21 | X8: 462265.2 | Y8: 385375.48 | Z8: 387962.24 | AA8: 503641.78 | AB8: 450193.95 | AC8: 460150.73 | AD8: 426918.17 | AE8: =AE36+AE46+AE58+AE70+AE82+AE95+AE108+AE120+AE132+AE144+AE156+AE168 -> 434143.85 | AF8: =AF36+AF46+AF58+AF70+AF82+AF95+AF108+AF120+AF132+AF144+AF156+AF168 -> 448390.13 | AG8: =AG36+AG46+AG58+AG70+AG82+AG95+AG108+AG120+AG132+AG144+AG156+AG168 -> 504042.4 | AH8: =AH36+AH46+AH58+AH70+AH82+AH95+AH108+AH120+AH132+AH144+AH156+AH168 -> 568991.43 | AI8: =AI36+AI46+AI58+AI70+AI82+AI95+AI108+AI120+AI132+AI144+AI156+AI168 -> 641535.19 | AJ8: =AJ36+AJ46+AJ58+AJ70+AJ82+AJ95+AJ108+AJ120+AJ132+AJ144+AJ156+AJ168 -> 719126.79 | AK8: =AK36+AK46+AK58+AK70+AK82+AK95+AK108+AK120+AK132+AK144+AK156+AK168 -> 803880.82 | AL8: =AL36+AL46+AL58+AL70+AL82+AL95+AL108+AL120+AL132+AL144+AL156+AL168 -> 919714.97 | ... AR8: =AR36+AR46+AR58+AR70+AR82+AR95+AR108+AR120+AR132+AR144+AR156+AR168 -> 1747082.7 | AS8: =AS36+AS46+AS58+AS70+AS82+AS95+AS108+AS120+AS132 -> 1825455.2 | AT8: =AT36+AT46+AT58+AT70+AT82+AT95+AT108+AT120+AT132 -> 1976168.7 | AU8: =AU36+AU46+AU58+AU70+AU82+AU95+AU108+AU120+AU132 -> 2131703.3 | AV8: =AV36+AV46+AV58+AV70+AV82+AV95+AV108+AV120+AV132 -> 2294654.6 | AW8: =AW36+AW46+AW58+AW70+AW82+AW95+AW108+AW120+AW132 -> 2462239.6 | AX8: =AX36+AX46+AX58+AX70+AX82+AX95+AX108+AX120+AX132 -> 2634390.8 | AY8: =AY36+AY46+AY58+AY70+AY82+AY95+AY108+AY120+AY132 -> 2811041.7 | AZ8: =AZ36+AZ46+AZ58+AZ70+AZ82+AZ95+AZ108+AZ120+AZ132 -> 2992126.9 | BA8: =BA36+BA46+BA58+BA70+BA82+BA95+BA108+BA120+BA132 -> 3177582.5 | BB8: =BB36+BB46+BB58+BB70+BB82+BB95+BB108+BB120+BB132+BB180 -> 3209963.4 | BC8: =BC36+BC46+BC58+BC70+BC82+BC95+BC108+BC120+BC132+BC180 -> 3695823.9 | BD8: =BD36+BD46+BD58+BD70+BD82+BD95+BD108+BD120+BD132+BD180 -> 3912317.2 | BE8: =BE36+BE46+BE58+BE70+BE82+BE95+BE108+BE120+BE132+BE180 -> 4133464.9 | BF8: =BF36+BF46+BF58+BF70+BF82+BF95+BF108+BF120+BF132+BF180 -> 4359182 | BG8: =BG36+BG46+BG58+BG70+BG82+BG95+BG108+BG120+BG132+BG180 -> 4589385.8 | BH8: =BH36+BH46+BH58+BH70+BH82+BH95+BH108+BH120+BH132+BH180 -> 4826662.4 | BI8: =BI36+BI46+BI58+BI70+BI82+BI95+BI108+BI120+BI132+BI180 -> 5068220.4 | ... CK8: =CK36+CK46+CK58+CK70+CK82+CK95+CK108+CK120+CK132+CK180 -> 13279308
B9: Marketing Expenses (acquisition) | R9: =R20+R49+R61+R73+R85+R98+R111+R123+R135+R147+R159+R171 -> 7409.447 | S9: =S20+S49+S61+S73+S85+S98+S111+S123+S135+S147+S159+S171 -> 7489.9951 | T9: =T20+T49+T61+T73+T85+T98+T111+T123+T135+T147+T159+T171 -> 5067.9047 | U9: =U20+U49+U61+U73+U85+U98+U111+U123+U135+U147+U159+U171 -> 5144.4044 | V9: =V20+V49+V61+V73+V85+V98+V111+V123+V135+V147+V159+V171 -> 5339.5404 | W9: =W20+W49+W61+W73+W85+W98+W111+W123+W135+W147+W159+W171 -> 5545.3372 | X9: =X20+X49+X61+X73+X85+X98+X111+X123+X135+X147+X159+X171 -> 5813.7187 | Y9: =Y20+Y49+Y61+Y73+Y85+Y98+Y111+Y123+Y135+Y147+Y159+Y171 -> 6144.5885 | ... BA9: =BA20+BA49+BA61+BA73+BA85+BA98+BA111+BA123+BA135+BA147+BA159+BA171 -> 159350.71 | BB9: =BB20+BB49+BB61+BB73+BB85+BB98+BB111+BB123+BB135+BB147+BB159+BB171+BB183 -> 174429.79 | BC9: =BC20+BC49+BC61+BC73+BC85+BC98+BC111+BC123+BC135+BC147+BC159+BC171+BC183 -> 185673.47 | BD9: =BD20+BD49+BD61+BD73+BD85+BD98+BD111+BD123+BD135+BD147+BD159+BD171+BD183 -> 197250.55 | BE9: =BE20+BE49+BE61+BE73+BE85+BE98+BE111+BE123+BE135+BE147+BE159+BE171+BE183 -> 209153.91 | BF9: =BF20+BF49+BF61+BF73+BF85+BF98+BF111+BF123+BF135+BF147+BF159+BF171+BF183 -> 221376.62 | BG9: =BG20+BG49+BG61+BG73+BG85+BG98+BG111+BG123+BG135+BG147+BG159+BG171+BG183 -> 233911.99 | BH9: =BH20+BH49+BH61+BH73+BH85+BH98+BH111+BH123+BH135+BH147+BH159+BH171+BH183 -> 246753.52 | BI9: =BI20+BI49+BI61+BI73+BI85+BI98+BI111+BI123+BI135+BI147+BI159+BI171+BI183 -> 259894.88 | ... CK9: =CK20+CK49+CK61+CK73+CK85+CK98+CK111+CK123+CK135+CK147+CK159+CK171+CK183 -> 728771.6
B10: Platform Fee Medzy | P10: =P37+P48+P60+P72+P84+P97+P110+P122 -> 67254.145 | Q10: =Q37+Q48+Q60+Q72+Q84+Q97+Q110+Q122 -> 69258.154 | R10: 70328.32 | S10: =S37+S48+S60+S72+S84+S97+S110+S122 -> 69268.814 | T10: =T37+T48+T60+T72+T84+T97+T110+T122 -> 68791.918 | U10: =U37+U48+U60+U72+U84+U97+U110+U122 -> 68340.521 | V10: =V37+V48+V60+V72+V84+V97+V110+V122 -> 68246.948 | W10: =W37+W48+W60+W72+W84+W97+W110+W122 -> 68161.064 | X10: =X37+X48+X60+X72+X84+X97+X110+X122 -> 68270.551 | Y10: =Y37+Y48+Y60+Y72+Y84+Y97+Y110+Y122 -> 68556.006 | Z10: =Z37+Z48+Z60+Z72+Z84+Z97+Z110+Z122 -> 68839.351 | ... BA10: =BA37+BA48+BA60+BA72+BA84+BA97+BA110+BA122 -> 514018.21 | BB10: =BB37+BB48+BB60+BB72+BB84+BB97+BB110+BB122+BB182 -> 619610.73 | BC10: =BC37+BC48+BC60+BC72+BC84+BC97+BC110+BC122+BC182 -> 718812.76 | BD10: =BD37+BD48+BD60+BD72+BD84+BD97+BD110+BD122+BD182 -> 771236.23 | BE10: =BE37+BE48+BE60+BE72+BE84+BE97+BE110+BE122+BE182 -> 824813.23 | BF10: =BF37+BF48+BF60+BF72+BF84+BF97+BF110+BF122+BF182 -> 879508.33 | BG10: =BG37+BG48+BG60+BG72+BG84+BG97+BG110+BG122+BG182 -> 935287.64 | BH10: =BH37+BH48+BH60+BH72+BH84+BH97+BH110+BH122+BH182 -> 992585.35 | BI10: =BI37+BI48+BI60+BI72+BI84+BI97+BI110+BI122+BI182 -> 1050895.6 | ... CK10: =CK37+CK48+CK60+CK72+CK84+CK97+CK110+CK122+CK182 -> 2996024.2
B12: DIRECT ACQUISITION | F12: 2022 | R12: 2023 | AD12: 2024 | AP12: 2025 | BB12: 2026 | BN12: 2026 | BZ12: 2026
F13: 1 | G13: 2 | H13: 3 | I13: 4 | J13: 5 | K13: 6 | L13: 7 | M13: 8 | N13: 9 | O13: 10 | P13: 44866 | Q13: 44896 | R13: 44927 | S13: 44958 | T13: 44986 | U13: 45017 | V13: 45047 | W13: 45078 | X13: 45108 | Y13: 45139 | Z13: 45170 | AA13: 45200 | AB13: 45231 | AC13: 45261 | AD13: 45292 | AE13: 45323 | AF13: 45352 | AG13: 45383 | AH13: 45413 | AI13: 45444 | AJ13: 45474 | AK13: 45505 | AL13: 45536 | AM13: 45566 | AN13: 45597 | AO13: 45627 | AP13: 45658 | AQ13: 45689 | AR13: 45717 | AS13: 45748 | AT13: 45778 | AU13: 45809 | AV13: 45839 | AW13: 45870 | AX13: 45901 | AY13: 45931 | AZ13: 45962 | BA13: 45992 | BB13: 45658 | BC13: 45689 | BD13: 45717 | BE13: 45748 | BF13: 45778 | BG13: 45809 | BH13: 45839 | BI13: 45870 | BJ13: 45901 | BK13: 45931 | BL13: 45962 | BM13: 45992 | BN13: 45658 | BO13: 45689 | BP13: 45717 | BQ13: 45748 | BR13: 45778 | BS13: 45809 | BT13: 45839 | BU13: 45870 | BV13: 45901 | BW13: 45931 | BX13: 45962 | BY13: 45992 | BZ13: 45658 | CA13: 45689 | CB13: 45717 | CC13: 45748 | CD13: 45778 | CE13: 45809 | CF13: 45839 | CG13: 45870 | CH13: 45901 | CI13: 45931 | CJ13: 45962 | CK13: 45992
B15: Online Marketing Budget
B16: Adwords (search engines) | N16: 8000 | O16: 8000 | P16: 5000 | Q16: 5000 | R16: 5000 | S16: 5000 | T16: 2500 | U16: 2500 | V16: 2500 | W16: 2500 | X16: 2500 | Y16: 2500 | Z16: 2500 | AA16: 2500 | AB16: 2500 | AC16: 2500 | AD16: 2500 | AE16: 2500 | AF16: 4000 | AG16: 30000 | AH16: 30000 | AI16: 30000 | AJ16: 30000 | AK16: 30000 | AL16: 30000 | AM16: 30000 | AN16: 30000 | AO16: 15000 | AP16: 20000 | AQ16: 20000 | AR16: 20000 | AS16: 20000 | AT16: 20000 | AU16: 20000 | AV16: 20000 | AW16: 20000 | AX16: 20000 | AY16: 20000 | AZ16: 20000 | BA16: 20000 | BB16: 20000 | BC16: 20000 | BD16: 20000 | BE16: 20000 | BF16: 20000 | BG16: 20000 | BH16: 20000 | BI16: 20000 | BJ16: 20000 | BK16: 20000 | BL16: 20000 | BM16: 20000 | BN16: 20000 | BO16: 20000 | BP16: 20000 | BQ16: 20000 | BR16: 20000 | BS16: 20000 | BT16: 20000 | BU16: 20000 | BV16: 20000 | BW16: 20000 | BX16: 20000 | BY16: 20000 | BZ16: 20000 | CA16: 20000 | CB16: 20000 | CC16: 20000 | CD16: 20000 | CE16: 20000 | CF16: 20000 | CG16: 20000 | CH16: 20000 | CI16: 20000 | CJ16: 20000 | CK16: 20000
B17: Content Marketing | N17: 2000 | O17: 2000 | P17: 3500 | Q17: 4000 | X17: 0 | Y17: 0 | Z17: 0 | AA17: 0 | AB17: 0 | AG17: 8000 | AH17: 8000 | AI17: 8000 | AJ17: 8000 | AK17: 8000 | AL17: 8000 | AM17: 8000 | AN17: 8000 | AO17: 8000 | AP17: 9000 | AQ17: 9000 | AR17: 9000 | AS17: 9000 | AT17: 9000 | AU17: 9000 | AV17: 9000 | AW17: 9000 | AX17: 9000 | AY17: 9000 | AZ17: 9000 | BA17: 9000 | BB17: 9000 | BC17: 9000 | BD17: 9000 | BE17: 9000 | BF17: 9000 | BG17: 9000 | BH17: 9000 | BI17: 9000 | BJ17: 9000 | BK17: 9000 | BL17: 9000 | BM17: 9000 | BN17: 9000 | BO17: 9000 | BP17: 9000 | BQ17: 9000 | BR17: 9000 | BS17: 9000 | BT17: 9000 | BU17: 9000 | BV17: 9000 | BW17: 9000 | BX17: 9000 | BY17: 9000 | BZ17: 9000 | CA17: 9000 | CB17: 9000 | CC17: 9000 | CD17: 9000 | CE17: 9000 | CF17: 9000 | CG17: 9000 | CH17: 9000 | CI17: 9000 | CJ17: 9000 | CK17: 9000
B18: Other | N18: 200 | O18: 200 | P18: 200 | Q18: 200 | X18: 0 | Y18: 0 | Z18: 0 | AA18: 0 | AB18: 0 | AG18: 2000 | AH18: 2000 | AI18: 2000 | AJ18: 2000 | AK18: 2000 | AL18: 2000 | AM18: 2000 | AN18: 2000 | AO18: 2000 | AP18: 3000 | AQ18: 3000 | AR18: 3000 | AS18: 3000 | AT18: 3000 | AU18: 3000 | AV18: 3000 | AW18: 3000 | AX18: 3000 | AY18: 3000 | AZ18: 3000 | BA18: 3000 | BB18: 3000 | BC18: 3000 | BD18: 3000 | BE18: 3000 | BF18: 3000 | BG18: 3000 | BH18: 3000 | BI18: 3000 | BJ18: 3000 | BK18: 3000 | BL18: 3000 | BM18: 3000 | BN18: 3000 | BO18: 3000 | BP18: 3000 | BQ18: 3000 | BR18: 3000 | BS18: 3000 | BT18: 3000 | BU18: 3000 | BV18: 3000 | BW18: 3000 | BX18: 3000 | BY18: 3000 | BZ18: 3000 | CA18: 3000 | CB18: 3000 | CC18: 3000 | CD18: 3000 | CE18: 3000 | CF18: 3000 | CG18: 3000 | CH18: 3000 | CI18: 3000 | CJ18: 3000 | CK18: 3000
B20: TOTAL | L20: =SUM(L16:L18) -> 0 | M20: =SUM(M16:M18) -> 0 | N20: =SUM(N16:N18) -> 10200 | O20: =SUM(O16:O18) -> 10200 | P20: =SUM(P16:P18) -> 8700 | Q20: =SUM(Q16:Q18) -> 9200 | R20: =SUM(R16:R18) -> 5000 | S20: =SUM(S16:S18) -> 5000 | ... CK20: =SUM(CK16:CK18) -> 32000
F22: 2022 | R22: 2023 | AD22: 2024 | AP22: 2025 | BB22: 2026 | BN22: 2026 | BZ22: 2026
F23: 1 | G23: 2 | H23: 3 | I23: 4 | J23: 5 | K23: 6 | L23: 7 | M23: 8 | N23: 9 | O23: 10 | P23: 44866 | Q23: 44896 | R23: 44927 | S23: 44958 | T23: 44986 | U23: 45017 | V23: 45047 | W23: 45078 | X23: 45108 | Y23: 45139 | Z23: 45170 | AA23: 45200 | AB23: 45231 | AC23: 45261 | AD23: 45292 | AE23: 45323 | AF23: 45352 | AG23: 45383 | AH23: 45413 | AI23: 45444 | AJ23: 45474 | AK23: 45505 | AL23: 45536 | AM23: 45566 | AN23: 45597 | AO23: 45627 | AP23: 45658 | AQ23: 45689 | AR23: 45717 | AS23: 45748 | AT23: 45778 | AU23: 45809 | AV23: 45839 | AW23: 45870 | AX23: 45901 | AY23: 45931 | AZ23: 45962 | BA23: 45992 | BB23: 45658 | BC23: 45689 | BD23: 45717 | BE23: 45748 | BF23: 45778 | BG23: 45809 | BH23: 45839 | BI23: 45870 | BJ23: 45901 | BK23: 45931 | BL23: 45962 | BM23: 45992 | BN23: 45658 | BO23: 45689 | BP23: 45717 | BQ23: 45748 | BR23: 45778 | BS23: 45809 | BT23: 45839 | BU23: 45870 | BV23: 45901 | BW23: 45931 | BX23: 45962 | BY23: 45992 | BZ23: 45658 | CA23: 45689 | CB23: 45717 | CC23: 45748 | CD23: 45778 | CE23: 45809 | CF23: 45839 | CG23: 45870 | CH23: 45901 | CI23: 45931 | CJ23: 45962 | CK23: 45992
B25: Trade activities
B26: Tradeshows | N26: 0 | O26: 0 | P26: 0 | Q26: 0 | R26: 0 | S26: 0 | T26: 0 | U26: 7000 | V26: 0 | W26: 0 | X26: 0 | Y26: 0 | Z26: 0 | AA26: 0 | AB26: 0 | AC26: 0 | AD26: 0 | AE26: 0 | AF26: 0 | AG26: 0 | AH26: 0 | AI26: 0 | AJ26: 0 | AK26: 0 | AL26: 0 | AM26: 0 | AN26: 0 | AO26: 0 | AP26: 0 | AQ26: 0 | AR26: 0 | AS26: 0 | AT26: 0 | AU26: 0 | AV26: 0 | AW26: 0 | AX26: 0 | AY26: 0 | AZ26: 0 | BA26: 0 | BB26: 0 | BC26: 0 | BD26: 0 | BE26: 0 | BF26: 0 | BG26: 0 | BH26: 0 | BI26: 0 | BJ26: 0 | BK26: 0 | BL26: 0 | BM26: 0 | BN26: 0 | BO26: 0 | BP26: 0 | BQ26: 0 | BR26: 0 | BS26: 0 | BT26: 0 | BU26: 0 | BV26: 0 | BW26: 0 | BX26: 0 | BY26: 0 | BZ26: 0 | CA26: 0 | CB26: 0 | CC26: 0 | CD26: 0 | CE26: 0 | CF26: 0 | CG26: 0 | CH26: 0 | CI26: 0 | CJ26: 0 | CK26: 0
B27: Events | N27: 0 | O27: 0 | P27: 0 | Q27: 0 | R27: 0 | S27: 0 | T27: 0 | U27: 0 | V27: 0 | W27: 0 | X27: 0 | Y27: 0 | Z27: 0 | AA27: 0 | AB27: 0 | AC27: 0 | AD27: 0 | AH27: 5000 | AI27: 5000 | AJ27: 5000 | AK27: 5000 | AL27: 5000 | AM27: 5000 | AN27: 5000 | AO27: 5000 | AP27: 7500 | AQ27: 7500 | AR27: 7500 | AS27: 7500 | AT27: 7500 | AU27: 7500 | AV27: 7500 | AW27: 7500 | AX27: 7500 | AY27: 7500 | AZ27: 7500 | BA27: 7500 | BB27: 7500 | BC27: 7500 | BD27: 7500 | BE27: 7500 | BF27: 7500 | BG27: 7500 | BH27: 7500 | BI27: 7500 | BJ27: 7500 | BK27: 7500 | BL27: 7500 | BM27: 7500 | BN27: 7500 | BO27: 7500 | BP27: 7500 | BQ27: 7500 | BR27: 7500 | BS27: 7500 | BT27: 7500 | BU27: 7500 | BV27: 7500 | BW27: 7500 | BX27: 7500 | BY27: 7500 | BZ27: 7500 | CA27: 7500 | CB27: 7500 | CC27: 7500 | CD27: 7500 | CE27: 7500 | CF27: 7500 | CG27: 7500 | CH27: 7500 | CI27: 7500 | CJ27: 7500 | CK27: 7500
B29: TOTAL | M29: =SUM(M26:M27) -> 0 | N29: =SUM(N26:N27) -> 0 | O29: =SUM(O26:O27) -> 0 | P29: =SUM(P26:P27) -> 0 | Q29: =SUM(Q26:Q27) -> 0 | R29: =SUM(R26:R27) -> 0 | S29: =SUM(S26:S27) -> 0 | T29: =SUM(T26:T27) -> 0 | ... CK29: =SUM(CK26:CK27) -> 7500
B31: CPA (estimated) | N31: 125 | O31: 115 | P31: 115 | Q31: 115 | R31: 115 | S31: 115 | T31: 115 | U31: 110 | V31: 110 | W31: 110 | X31: 105 | Y31: 105 | Z31: 105 | AA31: 105 | AB31: 100 | AC31: 100 | AD31: 95 | AE31: 95 | AF31: 95 | AG31: 95 | AH31: 95 | AI31: 90 | AJ31: 90 | AK31: 90 | AL31: 90 | AM31: 90 | AN31: 85 | AO31: 85 | AP31: 85 | AQ31: 85 | AR31: 80 | AS31: 80 | AT31: 80 | AU31: 80 | AV31: 75 | AW31: 75 | AX31: 75 | AY31: 75 | AZ31: 75 | BA31: 75 | BB31: 85 | BC31: 85 | BD31: 80 | BE31: 80 | BF31: 80 | BG31: 80 | BH31: 75 | BI31: 75 | BJ31: 75 | BK31: 75 | BL31: 75 | BM31: 75 | BN31: 85 | BO31: 85 | BP31: 80 | BQ31: 80 | BR31: 80 | BS31: 80 | BT31: 75 | BU31: 75 | BV31: 75 | BW31: 75 | BX31: 75 | BY31: 75 | BZ31: 85 | CA31: 85 | CB31: 80 | CC31: 80 | CD31: 80 | CE31: 80 | CF31: 75 | CG31: 75 | CH31: 75 | CI31: 75 | CJ31: 75 | CK31: 75
B32: New Clients Direct | N32: =(N20+N29)/N31 -> 81.6 | O32: =(O20+O29)/O31 -> 88.695652 | P32: =(P20+P29)/P31 -> 75.652174 | Q32: =(Q20+Q29)/Q31 -> 80 | R32: =R20/R31 -> 43.478261 | S32: =S20/S31 -> 43.478261 | T32: =T20/T31 -> 21.73913 | U32: =U20/U31 -> 22.727273 | V32: =V20/V31 -> 22.727273 | W32: =W20/W31 -> 22.727273 | X32: =X20/X31 -> 23.809524 | Y32: =Y20/Y31 -> 23.809524 | ... CK32: =CK20/CK31 -> 426.66667
B33: Churn | C33: 0.0175 | M33: 3500 | N33: =M33*C33 -> 61.25 | O33: =N34*$C33 -> 61.606125 | P33: =O34*$C33 -> 62.080192 | Q33: =P34*$C33 -> 62.317701 | R33: =Q34*$C33 -> 62.627142 | S33: =R34*$C33 -> 62.292036 | T33: =S34*$C33 -> 61.962795 | U33: =T34*$C33 -> 61.258881 | V33: =U34*$C33 -> 60.584578 | ... CK33: =CJ34*$C33 -> 278.64262
B34: TOTAL NEW CLIENTS DIRECT | N34: =M33+N32-N33 -> 3520.35 | O34: =N34+O32-O33 -> 3547.4395 | P34: =O34+P32-P33 -> 3561.0115 | Q34: =P34+Q32-Q33 -> 3578.6938 | R34: =Q34+R32-R33 -> 3559.5449 | S34: =R34+S32-S33 -> 3540.7312 | T34: =S34+T32-T33 -> 3500.5075 | U34: =T34+U32-U33 -> 3461.9759 | V34: =U34+V32-V33 -> 3424.1186 | ... CK34: =CJ34+CK32-CK33 -> 16070.459
B36: Total Pharmacy Revenus | C36: =350000/M33 -> 100 | N36: =N34*$C36 -> 352035 | O36: =O34*$C36 -> 354743.95 | P36: =P34*$C36 -> 356101.15 | Q36: =Q34*$C36 -> 357869.38 | R36: =R34*$C36 -> 355954.49 | S36: =S34*$C36 -> 354073.12 | T36: =T34*$C36 -> 350050.75 | U36: =U34*$C36 -> 346197.59 | ... CK36: =CK34*$C36 -> 1607045.9
B37: Rev Share to Medzy | C37: 0.175 | N37: =N36*$C37 -> 61606.125 | O37: =O36*$C37 -> 62080.192 | P37: =P36*$C37 -> 62317.701 | Q37: =Q36*$C37 -> 62627.142 | R37: =R36*$C37 -> 62292.036 | S37: =S36*$C37 -> 61962.795 | T37: =T36*$C37 -> 61258.881 | U37: =U36*$C37 -> 60584.578 | ... CK37: =CK36*$C37 -> 281233.04
B39: Tootelo
B41: New clients per day | N41: 8 | O41: 10 | P41: 10 | Q41: 10 | R41: 3 | S41: 2 | T41: 2 | U41: 2 | V41: =U41+2 -> 4 | W41: 4 | X41: 5 | Y41: 6 | Z41: 6 | AA41: 6 | AB41: 7 | AC41: 7 | AD41: 7 | AE41: =AD41+2 -> 9 | AF41: =AE41+2 -> 11 | AG41: =AF41+2 -> 13 | AH41: =AG41+2 -> 15 | AI41: =AH41+2 -> 17 | AJ41: =AI41+2 -> 19 | AK41: =AJ41+2 -> 21 | AL41: =AK41+2 -> 23 | ... CK41: =CJ41+2 -> 125
B42: New clients per month | C42: 20 | D42: days | N42: =N41*$C42 -> 160 | O42: =O41*$C42 -> 200 | P42: =P41*$C42 -> 200 | Q42: =Q41*$C42 -> 200 | R42: =R41*$C42 -> 60 | S42: =S41*$C42 -> 40 | T42: =T41*$C42 -> 40 | U42: =U41*$C42 -> 40 | ... CK42: =CK41*$C42 -> 2500
B43: Churn | C43: 0.0175 | P43: =N44*$C43 -> 2.8 | Q43: =O44*$C43 -> 6.3 | R43: =P44*$C43 -> 9.751 | S43: =Q44*$C43 -> 13.14075 | T43: =R44*$C43 -> 14.020108 | U43: =S44*$C43 -> 14.490144 | V43: =T44*$C43 -> 14.944792 | W43: =U44*$C43 -> 15.391215 | ... CK43: =CI44*$C43 -> 966.57744
B44: Total Clients | M44: 0 | N44: =M44+N42 -> 160 | O44: =N44+O42 -> 360 | P44: =O44+P42-P43 -> 557.2 | Q44: =P44+Q42-Q43 -> 750.9 | R44: =Q44+R42-R43 -> 801.149 | S44: =R44+S42-S43 -> 828.00825 | T44: =S44+T42-T43 -> 853.98814 | U44: =T44+U42-U43 -> 879.498 | V44: =U44+V42-V43 -> 944.55321 | W44: =V44+W42-W43 -> 1009.162 | ... CK44: =CJ44+CK42-CK43 -> 58286.194
B45: Avg Order per client | C45: 50
B46: TOTAL pharmacy revenus | N46: =$C45*N44 -> 8000 | O46: =$C45*O44 -> 18000 | P46: =$C45*P44 -> 27860 | Q46: =$C45*Q44 -> 37545 | R46: =$C45*R44 -> 40057.45 | S46: =$C45*S44 -> 41400.413 | T46: =$C45*T44 -> 42699.407 | U46: =$C45*U44 -> 43974.9 | ... CK46: =$C45*CK44 -> 2914309.7
B48: Rev share to Medzy | C48: 0.175 | N48: =N46*$C48 -> 1400 | O48: =O46*$C48 -> 3150 | P48: =P46*$C48 -> 4875.5 | Q48: =Q46*$C48 -> 6570.375 | R48: =R46*$C48 -> 7010.0538 | S48: =S46*$C48 -> 7245.0722 | T48: =T46*$C48 -> 7472.3962 | U48: =U46*$C48 -> 7695.6075 | ... CK48: =CK46*$C48 -> 510004.2
B49: Marketing Fees | C49: 3 | N49: =N44*$C49 -> 480 | O49: =O44*$C49 -> 1080 | P49: =P44*$C49 -> 1671.6 | Q49: =Q44*$C49 -> 2252.7 | R49: =R44*$C49 -> 2403.447 | S49: =S44*$C49 -> 2484.0248 | T49: =T44*$C49 -> 2561.9644 | U49: =U44*$C49 -> 2638.494 | ... CK49: =CK44*$C49 -> 174858.58
B51: Clinique Spécialitée
B53: New clients per day | N53: 0.2 | O53: =N53+0.1 -> 0.3 | P53: 0 | Q53: 0 | R53: 0 | S53: 0 | T53: 0 | U53: 0 | V53: 0 | W53: 0 | X53: 0 | Y53: 0 | Z53: 0 | AA53: 0 | AB53: 0 | AC53: 0 | AD53: 0 | AG53: =AF53+0.2 -> 0.2 | AH53: =AG53+0.2 -> 0.4 | AI53: =AH53+0.2 -> 0.6 | AJ53: =AI53+0.2 -> 0.8 | AK53: =AJ53+0.2 -> 1 | AL53: =AK53+0.2 -> 1.2 | AM53: =AL53+0.2 -> 1.4 | AN53: =AM53+0.2 -> 1.6 | ... CK53: =CJ53+0.2 -> 11.4
B54: New clients per month | C54: 12 | D54: days | N54: 0 | O54: 0 | P54: =P53*$C54 -> 0 | Q54: =Q53*$C54 -> 0 | R54: =R53*$C54 -> 0 | S54: =S53*$C54 -> 0 | T54: =T53*$C54 -> 0 | U54: =U53*$C54 -> 0 | V54: =V53*$C54 -> 0 | W54: =W53*$C54 -> 0 | ... CK54: =CK53*$C54 -> 136.8
B55: Churn | C55: 0.005 | P55: =N56*$C55 -> 0.01 | Q55: =O56*$C55 -> 0.01 | R55: =P56*$C55 -> 0.00995 | S55: =Q56*$C55 -> 0.0099 | T55: =R56*$C55 -> 0.01 | U55: =S56*$C55 -> 0.0099505 | V55: =T56*$C55 -> 0.0099005 | W55: =U56*$C55 -> 0.0098507475 | ... CK55: =CI56*$C55 -> 17.003683
B56: Total Clients | M56: 2 | N56: =M56+N54 -> 2 | O56: =N56+O54 -> 2 | P56: =O56+P54-P55 -> 1.99 | Q56: =P56+Q54-Q55 -> 1.98 | R56: 2 | S56: =R56+S54-S55 -> 1.9901 | T56: =S56+T54-T55 -> 1.9801 | U56: =T56+U54-U55 -> 1.9701495 | V56: =U56+V54-V55 -> 1.960249 | W56: =V56+W54-W55 -> 1.9503983 | X56: =W56+X54-X55 -> 1.940597 | Y56: =X56+Y54-Y55 -> 1.930845 | Z56: =Y56+Z54-Z55 -> 1.921142 | ... CK56: =CJ56+CK54-CK55 -> 3638.5101
B57: Avg Order per client | C57: 175
B58: TOTAL pharmacy revenus | N58: =$C57*N56 -> 350 | O58: =$C57*O56 -> 350 | P58: =$C57*P56 -> 348.25 | Q58: =$C57*Q56 -> 346.5 | R58: 345 | S58: =$C57*S56 -> 348.2675 | T58: =$C57*T56 -> 346.5175 | U58: =$C57*U56 -> 344.77616 | V58: =$C57*V56 -> 343.04357 | W58: =$C57*W56 -> 341.31969 | X58: =$C57*X56 -> 339.60448 | Y58: =$C57*Y56 -> 337.89788 | Z58: =$C57*Z56 -> 336.19986 | ... CK58: =$C57*CK56 -> 636739.26
B60: Rev share to Medzy | C60: 0.175 | N60: =N58*$C60 -> 61.25 | O60: =O58*$C60 -> 61.25 | P60: =P58*$C60 -> 60.94375 | Q60: =Q58*$C60 -> 60.6375 | R60: 60 | S60: =S58*$C60 -> 60.946812 | T60: =T58*$C60 -> 60.640562 | U60: =U58*$C60 -> 60.335828 | V60: =V58*$C60 -> 60.032626 | W60: =W58*$C60 -> 59.730946 | X60: =X58*$C60 -> 59.430783 | Y60: =Y58*$C60 -> 59.132129 | Z60: =Z58*$C60 -> 58.834975 | ... CK60: =CK58*$C60 -> 111429.37
B61: Marketing Fees | C61: 3 | N61: =N56*$C61 -> 6 | O61: =O56*$C61 -> 6 | P61: =P56*$C61 -> 5.97 | Q61: =Q56*$C61 -> 5.94 | R61: =R56*$C61 -> 6 | S61: =S56*$C61 -> 5.9703 | T61: =T56*$C61 -> 5.9403 | U61: =U56*$C61 -> 5.9104485 | ... CK61: =CK56*$C61 -> 10915.53
B63: Marketplace (Segic+Preventia)
B65: New clients per day | N65: 0 | O65: 0 | P65: 0 | Q65: 0 | R65: 0 | S65: 0 | T65: 0 | U65: 0 | V65: 0 | W65: 0 | X65: 0 | Y65: 0 | Z65: 0 | AA65: 0 | AB65: 0 | AF65: =AE65+0.5 -> 0.5 | AG65: =AF65+0.5 -> 1 | AH65: =AG65+0.5 -> 1.5 | AI65: =AH65+0.5 -> 2 | AJ65: =AI65+0.5 -> 2.5 | AK65: =AJ65+0.5 -> 3 | AL65: =AK65+0.5 -> 3.5 | AM65: =AL65+0.5 -> 4 | ... CK65: =CJ65+0.5 -> 29
B66: New clients per month | C66: 20 | D66: days | N66: =N65*$C66 -> 0 | O66: =O65*$C66 -> 0 | P66: =P65*$C66 -> 0 | Q66: =Q65*$C66 -> 0 | R66: =R65*$C66 -> 0 | S66: =S65*$C66 -> 0 | T66: =T65*$C66 -> 0 | U66: =U65*$C66 -> 0 | ... CK66: =CK65*$C66 -> 580
B67: Churn | C67: 0.0175 | P67: =N68*$C67 -> 0 | Q67: =O68*$C67 -> 0 | R67: =P68*$C67 -> 0 | S67: =Q68*$C67 -> 0 | T67: =R68*$C67 -> 0 | U67: =S68*$C67 -> 0 | V67: =T68*$C67 -> 0 | W67: =U68*$C67 -> 0 | ... CK67: =CI68*$C67 -> 210.0612
B68: Total Clients | M68: 0 | N68: =M68+N66 -> 0 | O68: =N68+O66 -> 0 | P68: =O68+P66-P67 -> 0 | Q68: =P68+Q66-Q67 -> 0 | R68: =Q68+R66-R67 -> 0 | S68: =R68+S66-S67 -> 0 | T68: =S68+T66-T67 -> 0 | U68: =T68+U66-U67 -> 0 | V68: =U68+V66-V67 -> 0 | W68: =V68+W66-W67 -> 0 | ... CK68: =CJ68+CK66-CK67 -> 12739.719
B69: Avg Order per client | C69: 75
B70: TOTAL pharmacy revenus | N70: =$C69*N68 -> 0 | O70: =$C69*O68 -> 0 | P70: =$C69*P68 -> 0 | Q70: =$C69*Q68 -> 0 | R70: =$C69*R68 -> 0 | S70: =$C69*S68 -> 0 | T70: =$C69*T68 -> 0 | U70: =$C69*U68 -> 0 | ... CK70: =$C69*CK68 -> 955478.95
B72: Rev share to Medzy | C72: 0.175 | N72: =N70*$C72 -> 0 | O72: =O70*$C72 -> 0 | P72: =P70*$C72 -> 0 | Q72: =Q70*$C72 -> 0 | R72: =R70*$C72 -> 0 | S72: =S70*$C72 -> 0 | T72: =T70*$C72 -> 0 | U72: =U70*$C72 -> 0 | ... CK72: =CK70*$C72 -> 167208.82
B73: Marketing Fees | C73: 3 | R73: =R68*$C$73 -> 0 | S73: =S68*$C$73 -> 0 | T73: =T68*$C$73 -> 0 | U73: =U68*$C$73 -> 0 | V73: =V68*$C$73 -> 0 | W73: =W68*$C$73 -> 0 | X73: =X68*$C$73 -> 0 | Y73: =Y68*$C$73 -> 0 | ... CK73: =CK68*$C$73 -> 38219.158
B75: Greenshield
B77: New clients per day | N77: 0 | O77: 0 | P77: 0 | Q77: 0 | R77: 0 | S77: 0 | T77: 0 | U77: 0 | V77: 0 | W77: 0 | X77: 0 | Y77: 0 | Z77: 0 | AA77: 0 | AB77: 0 | AC77: 0 | AD77: 0 | AE77: 0 | AH77: =AG77+1 -> 1 | AI77: =AH77+1 -> 2 | AJ77: =AI77+1 -> 3 | AK77: =AJ77+1 -> 4 | AL77: 20 | AM77: 20 | AN77: 20 | AO77: 20 | AP77: 20 | AQ77: 20 | AR77: 20 | AS77: 20 | AT77: 20 | AU77: 20 | AV77: 20 | AW77: 20 | AX77: 20 | AY77: 20 | AZ77: 20 | BA77: 20 | BB77: 20 | BC77: 20 | BD77: 20 | BE77: 20 | BF77: 20 | BG77: 20 | BH77: 20 | BI77: 20 | BJ77: 20 | BK77: 20 | BL77: 20 | BM77: 20 | BN77: 20 | BO77: 20 | BP77: 20 | BQ77: 20 | BR77: 20 | BS77: 20 | BT77: 20 | BU77: 20 | BV77: 20 | BW77: 20 | BX77: 20 | BY77: 20 | BZ77: 20 | CA77: 20 | CB77: 20 | CC77: 20 | CD77: 20 | CE77: 20 | CF77: 20 | CG77: 20 | CH77: 20 | CI77: 20 | CJ77: 20 | CK77: 20
B78: New clients per month | C78: 20 | D78: days | N78: =N77*$C78 -> 0 | O78: =O77*$C78 -> 0 | P78: =P77*$C78 -> 0 | Q78: =Q77*$C78 -> 0 | R78: =R77*$C78 -> 0 | S78: =S77*$C78 -> 0 | T78: =T77*$C78 -> 0 | U78: =U77*$C78 -> 0 | ... CK78: =CK77*$C78 -> 400
B79: Churn | C79: 0.0175 | P79: =N80*$C79 -> 0 | Q79: =O80*$C79 -> 0 | R79: =P80*$C79 -> 0 | S79: =Q80*$C79 -> 0 | T79: =R80*$C79 -> 0 | U79: =S80*$C79 -> 0 | V79: =T80*$C79 -> 0 | W79: =U80*$C79 -> 0 | ... CK79: =CI80*$C79 -> 238.56565
B80: Total Clients | M80: 0 | N80: =M80+N78 -> 0 | O80: =N80+O78 -> 0 | P80: =O80+P78-P79 -> 0 | Q80: =P80+Q78-Q79 -> 0 | R80: =Q80+R78-R79 -> 0 | S80: =R80+S78-S79 -> 0 | T80: =S80+T78-T79 -> 0 | U80: =T80+U78-U79 -> 0 | V80: =U80+V78-V79 -> 0 | W80: =V80+W78-W79 -> 0 | ... CK80: =CJ80+CK78-CK79 -> 13958.12
B81: Avg Order per client | C81: 75
B82: TOTAL pharmacy revenus | N82: =$C81*N80 -> 0 | O82: =$C81*O80 -> 0 | P82: =$C81*P80 -> 0 | Q82: =$C81*Q80 -> 0 | R82: =$C81*R80 -> 0 | S82: =$C81*S80 -> 0 | T82: =$C81*T80 -> 0 | U82: =$C81*U80 -> 0 | ... CK82: =$C81*CK80 -> 1046859
B84: Rev share to Medzy | C84: 0.175 | N84: =N82*$C84 -> 0 | O84: =O82*$C84 -> 0 | P84: =P82*$C84 -> 0 | Q84: =Q82*$C84 -> 0 | R84: =R82*$C84 -> 0 | S84: =S82*$C84 -> 0 | T84: =T82*$C84 -> 0 | U84: =U82*$C84 -> 0 | ... CK84: =CK82*$C84 -> 183200.33
B85: Marketing Fees | C85: 3 | N85: =N80*$C85 -> 0 | O85: =O80*$C85 -> 0 | P85: =P80*$C85 -> 0 | Q85: =Q80*$C85 -> 0 | R85: =R80*$C85 -> 0 | S85: =S80*$C85 -> 0 | T85: =T80*$C85 -> 0 | U85: =U80*$C85 -> 0 | ... CK85: =CK80*$C85 -> 41874.36
B88: Rexall
B90: New clients per day | N90: 0 | O90: 0 | P90: 0 | Q90: 0 | R90: 0 | S90: 0 | T90: 0 | U90: 0 | V90: 0 | W90: 0 | X90: 0 | Y90: 0 | Z90: 0 | AA90: 0 | AB90: 0 | AC90: 0 | AD90: 0 | AL90: =AK90+1 -> 1 | AM90: =AL90+1 -> 2 | AN90: =AM90+1 -> 3 | AO90: =AN90+1 -> 4 | AP90: =AO90+1 -> 5 | AQ90: =AP90+1 -> 6 | AR90: =AQ90+1 -> 7 | AS90: =AR90+1 -> 8 | ... CK90: =CJ90+1 -> 52
B91: New clients per month | C91: 20 | D91: days | N91: =N90*$C91 -> 0 | O91: =O90*$C91 -> 0 | P91: =P90*$C91 -> 0 | Q91: =Q90*$C91 -> 0 | R91: =R90*$C91 -> 0 | S91: =S90*$C91 -> 0 | T91: =T90*$C91 -> 0 | U91: =U90*$C91 -> 0 | ... CK91: =CK90*$C91 -> 1040
B92: Churn | C92: 0.02 | P92: =N93*$C92 -> 0 | Q92: =O93*$C92 -> 0 | R92: =P93*$C92 -> 0 | S92: =Q93*$C92 -> 0 | T92: =R93*$C92 -> 0 | U92: =S93*$C92 -> 0 | V92: =T93*$C92 -> 0 | W92: =U93*$C92 -> 0 | ... CK92: =CI93*$C92 -> 382.24465
B93: Total Clients | M93: 0 | N93: =M93+N91 -> 0 | O93: =N93+O91 -> 0 | P93: =O93+P91-P92 -> 0 | Q93: =P93+Q91-Q92 -> 0 | R93: =Q93+R91-R92 -> 0 | S93: =R93+S91-S92 -> 0 | T93: =S93+T91-T92 -> 0 | U93: =T93+U91-U92 -> 0 | V93: =U93+V91-V92 -> 0 | W93: =V93+W91-W92 -> 0 | ... CK93: =CJ93+CK91-CK92 -> 20420.61
B94: Avg Order per client | C94: 75
B95: TOTAL pharmacy revenus | N95: =$C94*N93 -> 0 | O95: =$C94*O93 -> 0 | P95: =$C94*P93 -> 0 | Q95: =$C94*Q93 -> 0 | R95: =$C94*R93 -> 0 | S95: =$C94*S93 -> 0 | T95: =$C94*T93 -> 0 | U95: =$C94*U93 -> 0 | ... CK95: =$C94*CK93 -> 1531545.8
B97: Rev share to Medzy | C97: 0.175 | N97: =N95*$C97 -> 0 | O97: =O95*$C97 -> 0 | P97: =P95*$C97 -> 0 | Q97: =Q95*$C97 -> 0 | R97: =R95*$C97 -> 0 | S97: =S95*$C97 -> 0 | T97: =T95*$C97 -> 0 | U97: =U95*$C97 -> 0 | ... CK97: =CK95*$C97 -> 268020.51
B98: Marketing Fees | C98: 3 | N98: =N93*$C98 -> 0 | O98: =O93*$C98 -> 0 | P98: =P93*$C98 -> 0 | Q98: =Q93*$C98 -> 0 | R98: =R93*$C98 -> 0 | S98: =S93*$C98 -> 0 | T98: =T93*$C98 -> 0 | U98: =U93*$C98 -> 0 | ... CK98: =CK93*$C98 -> 61261.831
B101: Mondou
B103: New clients per day | N103: 0 | O103: 0 | P103: 0 | Q103: 0 | R103: 0 | S103: 0 | T103: 0 | U103: 0 | V103: 0 | W103: 0 | X103: 0 | Y103: 0 | Z103: 0 | AA103: 0 | AB103: 0 | AC103: 0 | AD103: 0 | AE103: 0 | AF103: 0 | AH103: 5 | AI103: =AH103+1 -> 6 | AJ103: =AI103+1 -> 7 | AK103: =AJ103+1 -> 8 | AL103: =AK103+1 -> 9 | AM103: =AL103+1 -> 10 | AN103: =AM103+1 -> 11 | AO103: =AN103+1 -> 12 | AP103: =AO103+1 -> 13 | ... CK103: =CJ103+1 -> 60
B104: New clients per month | C104: 20 | D104: days | N104: =N103*$C104 -> 0 | O104: =O103*$C104 -> 0 | P104: =P103*$C104 -> 0 | Q104: =Q103*$C104 -> 0 | R104: =R103*$C104 -> 0 | S104: =S103*$C104 -> 0 | T104: =T103*$C104 -> 0 | U104: =U103*$C104 -> 0 | ... CK104: =CK103*$C104 -> 1200
B105: Churn | C105: 0.02 | P105: =N106*$C105 -> 0 | Q105: =O106*$C105 -> 0 | R105: =P106*$C105 -> 0 | S105: =Q106*$C105 -> 0 | T105: =R106*$C105 -> 0 | U105: =S106*$C105 -> 0 | V105: =T106*$C105 -> 0 | W105: =U106*$C105 -> 0 | ... CK105: =CI106*$C105 -> 488.86584
B106: Total Clients | M106: 0 | N106: =M106+N104 -> 0 | O106: =N106+O104 -> 0 | P106: =O106+P104-P105 -> 0 | Q106: =P106+Q104-Q105 -> 0 | R106: =Q106+R104-R105 -> 0 | S106: =R106+S104-S105 -> 0 | T106: =S106+T104-T105 -> 0 | U106: =T106+U104-U105 -> 0 | V106: =U106+V104-V105 -> 0 | W106: =V106+W104-W105 -> 0 | ... CK106: =CJ106+CK104-CK105 -> 25859.54
B107: Avg Order per client | C107: 50
B108: TOTAL pharmacy revenus | N108: =$C107*N106 -> 0 | O108: =$C107*O106 -> 0 | P108: =$C107*P106 -> 0 | Q108: =$C107*Q106 -> 0 | R108: =$C107*R106 -> 0 | S108: =$C107*S106 -> 0 | T108: =$C107*T106 -> 0 | U108: =$C107*U106 -> 0 | ... BA108: =$C107*BA106 -> 256235.97 | BB108: 0 | BC108: =$C107*BC106 -> 297379.5 | BD108: =$C107*BD106 -> 318849.42 | BE108: =$C107*BE106 -> 340901.83 | BF108: =$C107*BF106 -> 363524.84 | BG108: =$C107*BG106 -> 386706.81 | BH108: =$C107*BH106 -> 410436.31 | BI108: =$C107*BI106 -> 434702.17 | BJ108: =$C107*BJ106 -> 459493.45 | ... CK108: =$C107*CK106 -> 1292977
B110: Rev share to Medzy | C110: 0.175 | N110: =N108*$C110 -> 0 | O110: =O108*$C110 -> 0 | P110: =P108*$C110 -> 0 | Q110: =Q108*$C110 -> 0 | R110: =R108*$C110 -> 0 | S110: =S108*$C110 -> 0 | T110: =T108*$C110 -> 0 | U110: =U108*$C110 -> 0 | ... CK110: =CK108*$C110 -> 226270.97
B111: Marketing Fees | C111: 5 | N111: =N106*$C111 -> 0 | O111: =O106*$C111 -> 0 | P111: =P106*$C111 -> 0 | Q111: =Q106*$C111 -> 0 | R111: =R106*$C111 -> 0 | S111: =S106*$C111 -> 0 | T111: =T106*$C111 -> 0 | U111: =U106*$C111 -> 0 | ... CK111: =CK106*$C111 -> 129297.7
B113: MedFar
B115: New clients per day | N115: 0 | O115: 0 | P115: 0 | Q115: 0 | R115: 0 | S115: 0 | T115: 0 | U115: 0 | V115: 0 | W115: 0 | X115: 0 | Y115: 0 | Z115: 0 | AA115: 0 | AB115: 0 | AC115: 0 | AD115: 0 | AE115: 0 | AF115: 0 | AK115: =AJ115+1 -> 1 | AL115: =AK115+1 -> 2 | AM115: =AL115+1 -> 3 | AN115: =AM115+1 -> 4 | AO115: =AN115+1 -> 5 | AP115: =AO115+1 -> 6 | AQ115: =AP115+1 -> 7 | AR115: =AQ115+1 -> 8 | ... CK115: =CJ115+1 -> 53
B116: New clients per month | C116: 20 | D116: days | N116: =N115*$C116 -> 0 | O116: =O115*$C116 -> 0 | P116: =P115*$C116 -> 0 | Q116: =Q115*$C116 -> 0 | R116: =R115*$C116 -> 0 | S116: =S115*$C116 -> 0 | T116: =T115*$C116 -> 0 | U116: =U115*$C116 -> 0 | ... CK116: =CK115*$C116 -> 1060
B117: Churn | C117: 0.005 | P117: =N118*$C117 -> 0 | Q117: =O118*$C117 -> 0 | R117: =P118*$C117 -> 0 | S117: =Q118*$C117 -> 0 | T117: =R118*$C117 -> 0 | U117: =S118*$C117 -> 0 | V117: =T118*$C117 -> 0 | W117: =U118*$C117 -> 0 | ... CK117: =CI118*$C117 -> 122.74016
B118: Total Clients | M118: 0 | N118: =M118+N116 -> 0 | O118: =N118+O116 -> 0 | P118: =O118+P116-P117 -> 0 | Q118: =P118+Q116-Q117 -> 0 | R118: =Q118+R116-R117 -> 0 | S118: =R118+S116-S117 -> 0 | T118: =S118+T116-T117 -> 0 | U118: =T118+U116-U117 -> 0 | V118: =U118+V116-V117 -> 0 | W118: =V118+W116-W117 -> 0 | ... CK118: =CJ118+CK116-CK117 -> 26407.083
B119: Avg Order per client | C119: 50
B120: TOTAL pharmacy revenus | N120: =$C119*N118 -> 0 | O120: =$C119*O118 -> 0 | P120: =$C119*P118 -> 0 | Q120: =$C119*Q118 -> 0 | R120: =$C119*R118 -> 0 | S120: =$C119*S118 -> 0 | T120: =$C119*T118 -> 0 | U120: =$C119*U118 -> 0 | ... CK120: =$C119*CK118 -> 1320354.2
B122: Rev share to Medzy | C122: 0.175 | N122: =N120*$C122 -> 0 | O122: =O120*$C122 -> 0 | P122: =P120*$C122 -> 0 | Q122: =Q120*$C122 -> 0 | R122: =R120*$C122 -> 0 | S122: =S120*$C122 -> 0 | T122: =T120*$C122 -> 0 | U122: =U120*$C122 -> 0 | ... CK122: =CK120*$C122 -> 231061.98
B123: Marketing Fees | C123: 3 | N123: =N118*$C123 -> 0 | O123: =O118*$C123 -> 0 | P123: =P118*$C123 -> 0 | Q123: =Q118*$C123 -> 0 | R123: =R118*$C123 -> 0 | S123: =S118*$C123 -> 0 | T123: =T118*$C123 -> 0 | U123: =U118*$C123 -> 0 | ... CK123: =CK118*$C123 -> 79221.25
B125: Soprema
B127: New clients per day | N127: 0 | O127: 0 | P127: 0 | Q127: 0 | R127: 0 | S127: 0 | T127: 0 | U127: 0 | V127: 0 | W127: 0.2 | X127: =W127+0.1 -> 0.3 | Y127: =X127+0.1 -> 0.4 | Z127: =Y127+0.1 -> 0.5 | AA127: =Z127+0.1 -> 0.6 | AB127: =AA127+0.1 -> 0.7 | AC127: =AB127+0.1 -> 0.8 | AD127: =AC127+0.1 -> 0.9 | AE127: =AD127+0.1 -> 1 | ... CK127: =CJ127+0.1 -> 6.8
B128: New clients per month | C128: 20 | D128: days | N128: =N127*$C128 -> 0 | O128: =O127*$C128 -> 0 | P128: =P127*$C128 -> 0 | Q128: =Q127*$C128 -> 0 | R128: =R127*$C128 -> 0 | S128: =S127*$C128 -> 0 | T128: =T127*$C128 -> 0 | U128: =U127*$C128 -> 0 | ... CK128: =CK127*$C128 -> 136
B129: Churn | C129: 0.01 | P129: =N130*$C129 -> 0 | Q129: =O130*$C129 -> 0 | R129: =P130*$C129 -> 0 | S129: =Q130*$C129 -> 0 | T129: =R130*$C129 -> 0 | U129: =S130*$C129 -> 0 | V129: =T130*$C129 -> 0 | W129: =U130*$C129 -> 0 | ... CK129: =CI130*$C129 -> 36.271807
B130: Total Clients | M130: 0 | N130: =M130+N128 -> 0 | O130: =N130+O128 -> 0 | P130: =O130+P128-P129 -> 0 | Q130: =P130+Q128-Q129 -> 0 | R130: =Q130+R128-R129 -> 0 | S130: =R130+S128-S129 -> 0 | T130: =S130+T128-T129 -> 0 | U130: =T130+U128-U129 -> 0 | V130: =U130+V128-V129 -> 0 | W130: =V130+W128-W129 -> 4 | ... CK130: =CJ130+CK128-CK129 -> 3825.6138
B131: Avg Order per client | C131: 250
B132: TOTAL pharmacy revenus | N132: =$C131*N130 -> 0 | O132: =$C131*O130 -> 0 | P132: =$C131*P130 -> 0 | Q132: =$C131*Q130 -> 0 | R132: =$C131*R130 -> 0 | S132: =$C131*S130 -> 0 | T132: =$C131*T130 -> 0 | U132: =$C131*U130 -> 0 | ... CK132: =$C131*CK130 -> 956403.46
B134: Rev share to Medzy | C134: 1 | N134: =N132*$C134 -> 0 | O134: =O132*$C134 -> 0 | P134: =P132*$C134 -> 0 | Q134: =Q132*$C134 -> 0 | R134: =R132*$C134 -> 0 | S134: =S132*$C134 -> 0 | T134: =T132*$C134 -> 0 | U134: =U132*$C134 -> 0 | ... CK134: =CK132*$C134 -> 956403.46
B135: Marketing Fees | C135: 3 | N135: =N130*$C135 -> 0 | O135: =O130*$C135 -> 0 | P135: =P130*$C135 -> 0 | Q135: =Q130*$C135 -> 0 | R135: =R130*$C135 -> 0 | S135: =S130*$C135 -> 0 | T135: =T130*$C135 -> 0 | U135: =U130*$C135 -> 0 | ... CK135: =CK130*$C135 -> 11476.842
B137: CT
...

Sheet PSB-Summary
C1: Pharmacie Sonia Boutin Inc - Forecast
D3: Fiscal Year Ending on
D4: Oct 31 2023 | E4: Oct 31 2024 | F4: Oct 31 2025 | G4: Oct 31 2026
B5: REVENUES & KPIS
C6: New Clients | D6: =SUM('PSB-P&L '!P10:AA10) -> 1112.1156 | E6: =SUM('PSB-P&L '!AD10:AO10) -> 12909.77 | F6: =SUM('PSB-P&L '!AP10:BA10) -> 32575.341 | G6: =SUM('PSB-P&L '!AQ10:BB10) -> 34268.141
C7: Churn | D7: =SUM('PSB-P&L '!P11:AA11) -> 758.11151 | E7: =SUM('PSB-P&L '!AD11:AO11) -> 1557.4311 | F7: =SUM('PSB-P&L '!AP11:BA11) -> 5199.0281 | G7: =SUM('PSB-P&L '!AQ11:BB11) -> 5684.9535
C8: Total Clients | D8: ='PSB-P&L '!AA12 -> 4645.6078 | E8: ='PSB-P&L '!AO12 -> 15819.69 | F8: ='PSB-P&L '!BA12 -> 42560.003 | G8: ='PSB-P&L '!BB12 -> 45238.432
C10: Pharmacy Revenues | D10: =SUM('PSB-P&L '!P17:AA17) -> 4938062.7 | E10: =SUM('PSB-P&L '!AD17:AO17) -> 8978508.2 | F10: =SUM('PSB-P&L '!AP17:BA17) -> 27076732 | G10: =SUM('PSB-P&L '!AQ17:BB17) -> 28849108
C12: Cost of Goods | D12: =SUM('PSB-P&L '!P18:AA18) -> -3654166.4 | E12: =SUM('PSB-P&L '!AD18:AO18) -> -6554311 | F12: =SUM('PSB-P&L '!AP18:BA18) -> -19495247 | G12: =SUM('PSB-P&L '!AQ18:BB18) -> -20771358
C14: ='PSB-P&L '!B20 -> Professional Allocations | D14: =SUM('PSB-P&L '!P20:AA20) -> 131938.75 | E14: =SUM('PSB-P&L '!AB20:AM20) -> 148392.16 | F14: =SUM('PSB-P&L '!AN20:AY20) -> 467525.35 | G14: =SUM('PSB-P&L '!AO20:AZ20) -> 503880.36
C16: ='PSB-P&L '!B22 -> Distributor Savings | D16: =SUM('PSB-P&L '!P22:AA22) -> 0 | E16: =SUM('PSB-P&L '!AB22:AM22) -> 227824.21 | F16: =SUM('PSB-P&L '!AN22:AY22) -> 818169.36 | G16: =SUM('PSB-P&L '!AO22:AZ22) -> 881790.63
C17: ='PSB-P&L '!B23 -> Distributor Expenses | D17: =SUM('PSB-P&L '!P23:AA23) -> 0 | E17: =SUM('PSB-P&L '!AB23:AM23) -> -12500 | F17: =SUM('PSB-P&L '!AN23:AY23) -> -15000 | G17: =SUM('PSB-P&L '!AO23:AZ23) -> -15000
C19: ='PSB-P&L '!B25 -> OTC upsell PSB | D19: =SUM('PSB-P&L '!P25:AA25) -> 21822.394 | E19: =SUM('PSB-P&L '!AB25:AM25) -> 103291.29 | F19: =SUM('PSB-P&L '!AN25:AY25) -> 359380.72 | G19: =SUM('PSB-P&L '!AO25:AZ25) -> 390186.34
C21: NET REVENUES | D21: =SUM(D10:D20) -> 1437657.5 | E21: =SUM(E10:E20) -> 2891204.9 | F21: =SUM(F10:F20) -> 9211560.3 | G21: =SUM(G10:G20) -> 9838607.6
D23: =D4 -> Oct 31 2023 | E23: =E4 -> Oct 31 2024 | F23: =F4 -> Oct 31 2025 | G23: =G4 -> Oct 31 2026
B24: EXPENSES | C24: ='PSB-P&L '!B36 -> Salaries
C25: ='PSB-P&L '!B37 -> Pharmacists | D25: =SUM('PSB-P&L '!P37:AA37) -> 267987.4 | E25: =SUM('PSB-P&L '!AB37:AM37) -> 258774.6 | F25: =SUM('PSB-P&L '!AN37:AY37) -> 278237.87 | G25: =SUM('PSB-P&L '!AO37:AZ37) -> 279253.33
C26: ='PSB-P&L '!B38 -> ATP | D26: =SUM('PSB-P&L '!P38:AA38) -> 296292.08 | E26: =SUM('PSB-P&L '!AB38:AM38) -> 340046.95 | F26: =SUM('PSB-P&L '!AN38:AY38) -> 454037.65 | G26: =SUM('PSB-P&L '!AO38:AZ38) -> 464099.37
C27: ='PSB-P&L '!B39 -> SAC | D27: =SUM('PSB-P&L '!P39:AA39) -> 278122.28 | E27: =SUM('PSB-P&L '!AB39:AM39) -> 353855.03 | F27: =SUM('PSB-P&L '!AN39:AY39) -> 421239.23 | G27: =SUM('PSB-P&L '!AO39:AZ39) -> 429512.92
D28: =SUM(D25:D27) -> 842401.77 | E28: =SUM(E25:E27) -> 952676.58 | F28: =SUM(F25:F27) -> 1153514.8 | G28: =SUM(G25:G27) -> 1172865.6
D29: =SUM('PSB-P&L '!P40:AA40) -> 0 | E29: =SUM('PSB-P&L '!AB40:AM40) -> 0 | F29: =SUM('PSB-P&L '!AN40:AY40) -> 0 | G29: =SUM('PSB-P&L '!AO40:AZ40) -> 0
C30: ='PSB-P&L '!B41 -> Fringes + Bonus | D30: =SUM('PSB-P&L '!P41:AA41) -> 62379.023 | E30: =SUM('PSB-P&L '!AB41:AM41) -> 104794.42 | F30: =SUM('PSB-P&L '!AN41:AY41) -> 126886.62 | G30: =SUM('PSB-P&L '!AO41:AZ41) -> 129015.22
C32: ='PSB-P&L '!B43 -> Contractuals Pharmacy Total | D32: =SUM('PSB-P&L '!P43:AA43) -> 10000 | E32: =SUM('PSB-P&L '!AB43:AM43) -> 12000 | F32: =SUM('PSB-P&L '!AN43:AY43) -> 12000 | G32: =SUM('PSB-P&L '!AO43:AZ43) -> 12000
C34: ='PSB-P&L '!B45 -> Professionals | D34: =SUM('PSB-P&L '!P45:AA45) -> 0 | E34: =SUM('PSB-P&L '!AB45:AM45) -> 0 | F34: =SUM('PSB-P&L '!AN45:AY45) -> 0 | G34: =SUM('PSB-P&L '!AO45:AZ45) -> 0
C35: ='PSB-P&L '!B46 -> Accounting Fees | D35: =SUM('PSB-P&L '!P46:AA46) -> 23948.7 | E35: =SUM('PSB-P&L '!AB46:AM46) -> 24400 | F35: =SUM('PSB-P&L '!AN46:AY46) -> 19400 | G35: =SUM('PSB-P&L '!AO46:AZ46) -> 19400
C36: ='PSB-P&L '!B47 -> Legal Fees | D36: =SUM('PSB-P&L '!P47:AA47) -> 5000 | E36: =SUM('PSB-P&L '!AB47:AM47) -> 6000 | F36: =SUM('PSB-P&L '!AN47:AY47) -> 6000 | G36: =SUM('PSB-P&L '!AO47:AZ47) -> 6000
C37: ='PSB-P&L '!B48 -> Other | D37: =SUM('PSB-P&L '!P48:AA48) -> 0 | E37: =SUM('PSB-P&L '!AB48:AM48) -> 0 | F37: =SUM('PSB-P&L '!AN48:AY48) -> 0 | G37: =SUM('PSB-P&L '!AO48:AZ48) -> 0
C41: ='PSB-P&L '!B52 -> SubTotal Salaries
C42: ='PSB-P&L '!B53 -> 0 | D42: =SUM('PSB-P&L '!P53:AA53) -> 0 | E42: =SUM('PSB-P&L '!AB53:AM53) -> 0 | F42: =SUM('PSB-P&L '!AN53:AY53) -> 0 | G42: =SUM('PSB-P&L '!AO53:AZ53) -> 0
C43: ='PSB-P&L '!B54 -> Rent | D43: =SUM('PSB-P&L '!P54:AA54) -> 0 | E43: =SUM('PSB-P&L '!AB54:AM54) -> 0 | F43: =SUM('PSB-P&L '!AN54:AY54) -> 0 | G43: =SUM('PSB-P&L '!AO54:AZ54) -> 0
C44: ='PSB-P&L '!B55 -> Utiities | D44: =SUM('PSB-P&L '!P55:AA55) -> 0 | E44: =SUM('PSB-P&L '!AB55:AM55) -> 0 | F44: =SUM('PSB-P&L '!AN55:AY55) -> 0 | G44: =SUM('PSB-P&L '!AO55:AZ55) -> 0
C45: ='PSB-P&L '!B56 -> Insurance | D45: =SUM('PSB-P&L '!P56:AA56) -> 0 | E45: =SUM('PSB-P&L '!AB56:AM56) -> 7500 | F45: =SUM('PSB-P&L '!AN56:AY56) -> 9000 | G45: =SUM('PSB-P&L '!AO56:AZ56) -> 9000
C46: ='PSB-P&L '!B57 -> Meals and Entertainment | D46: =SUM('PSB-P&L '!P57:AA57) -> 3175 | E46: =SUM('PSB-P&L '!AB57:AM57) -> 3000 | F46: =SUM('PSB-P&L '!AN57:AY57) -> 3000 | G46: =SUM('PSB-P&L '!AO57:AZ57) -> 3000
C47: ='PSB-P&L '!B58 -> Travel Expenses | D47: =SUM('PSB-P&L '!P58:AA58) -> -160.55 | E47: =SUM('PSB-P&L '!AB58:AM58) -> 0 | F47: =SUM('PSB-P&L '!AN58:AY58) -> 0 | G47: =SUM('PSB-P&L '!AO58:AZ58) -> 0
C48: ='PSB-P&L '!B59 -> Depreciation | D48: =SUM('PSB-P&L '!P59:AA59) -> 0 | E48: =SUM('PSB-P&L '!AB59:AM59) -> 0 | F48: =SUM('PSB-P&L '!AN59:AY59) -> 0 | G48: =SUM('PSB-P&L '!AO59:AZ59) -> 0
C49: ='PSB-P&L '!B60 -> Telecommunication | D49: =SUM('PSB-P&L '!P60:AA60) -> 0 | E49: =SUM('PSB-P&L '!AB60:AM60) -> 0 | F49: =SUM('PSB-P&L '!AN60:AY60) -> 0 | G49: =SUM('PSB-P&L '!AO60:AZ60) -> 0
C50: ='PSB-P&L '!B61 -> Pharmacy Automation (robot) - rental to Medzy | D50: =SUM('PSB-P&L '!P61:AA61) -> 18000 | E50: =SUM('PSB-P&L '!AB61:AM61) -> 36000 | F50: =SUM('PSB-P&L '!AN61:AY61) -> 36000 | G50: =SUM('PSB-P&L '!AO61:AZ61) -> 36000
C51: ='PSB-P&L '!B62 -> License and Subscriptions | D51: =SUM('PSB-P&L '!P62:AA62) -> 3240.84 | E51: =SUM('PSB-P&L '!AB62:AM62) -> 3000 | F51: =SUM('PSB-P&L '!AN62:AY62) -> 3000 | G51: =SUM('PSB-P&L '!AO62:AZ62) -> 3000
C52: ='PSB-P&L '!B63 -> Repair and Maintenance | D52: =SUM('PSB-P&L '!P63:AA63) -> 0 | E52: =SUM('PSB-P&L '!AB63:AM63) -> 0 | F52: =SUM('PSB-P&L '!AN63:AY63) -> 0 | G52: =SUM('PSB-P&L '!AO63:AZ63) -> 0
C53: ='PSB-P&L '!B64 -> Recruitment Charges | D53: =SUM('PSB-P&L '!P64:AA64) -> 0 | E53: =SUM('PSB-P&L '!AB64:AM64) -> 0 | F53: =SUM('PSB-P&L '!AN64:AY64) -> 0 | G53: =SUM('PSB-P&L '!AO64:AZ64) -> 0
... C60: ='PSB-P&L '!B71 -> Loans | D60: =SUM('PSB-P&L '!P71:AA71) -> 0 | E60: =SUM('PSB-P&L '!AB71:AM71) -> 0 | F60: =SUM('PSB-P&L '!AN71:AY71) -> 0 | G60: =SUM('PSB-P&L '!AO71:AZ71) -> 0
D61: =SUM('PSB-P&L '!P72:AA72) -> 0 | E61: =SUM('PSB-P&L '!AB72:AM72) -> 0 | F61: =SUM('PSB-P&L '!AN72:AY72) -> 0 | G61: =SUM('PSB-P&L '!AO72:AZ72) -> 0
D62: =SUM('PSB-P&L '!P73:AA73) -> 0 | E62: =SUM('PSB-P&L '!AB73:AM73) -> 0 | F62: =SUM('PSB-P&L '!AN73:AY73) -> 0 | G62: =SUM('PSB-P&L '!AO73:AZ73) -> 0
C63: ='PSB-P&L '!B74 -> Platform Fees - Medzy | D63: =SUM('PSB-P&L '!P74:AA74) -> 824433.3 | E63: =SUM('PSB-P&L '!AB74:AM74) -> 1190998.5 | F63: =SUM('PSB-P&L '!AN74:AY74) -> 3749421.8 | G63: =SUM('PSB-P&L '!AO74:AZ74) -> 4045709.6
C65: TOTAL EXPENSES | D65: =SUM(D28:D64) -> 2109687.4 | E65: =SUM(E28:E64) -> 2733158.9 | F65: =SUM(F28:F64) -> 6223877.7 | G65: =SUM(G28:G64) -> 6619389.6
B67: P&L | C67: P&L (Before Taxes Credits) | D67: =D21-D65 -> -672029.97 | E67: =E21-E65 -> 158045.93 | F67: =F21-F65 -> 2987682.7 | G67: =G21-G65 -> 3219218
C71: PSB STATS
C72: Break-Even PSB | D72: ='PSB-P&L '!AD5 -> 45292
C73: Pharmacy REV for Break-Even PSB | D73: ='PSB-P&L '!AD17 -> 426918.17 | E73: per month
C74: Revenues Increase Break-Even / Now | D74: =D73/'PSB-P&L '!R17 -> 1.0638796 | E74: times
C76: Lowest Cashflow (without paying Medzy) | D76: ='PSB-P&L '!T87 -> 9979.7286 | E76: ='PSB-P&L '!T85 -> 44986
C78: PSB owed to Medzy - highest | D78: ='PSB-P&L '!AC101 -> 2460316.1 | E78: ='PSB-P&L '!AC85 -> 45261
C79: PSB payback to Medzy - last payment | D79: ='PSB-P&L '!AQ85 -> 45689

Sheet PSB-P&L 
P3: ACTUALS | R3: Forecast | S3: Forecast | T3: Forecast | U3: Forecast | V3: Forecast | W3: Forecast | X3: Forecast | Y3: Forecast | Z3: Forecast | AA3: Forecast | AB3: Forecast | AC3: Forecast | AD3: Forecast | AE3: Forecast | AF3: Forecast | AG3: Forecast | AH3: Forecast | AI3: Forecast | AJ3: Forecast | AK3: Forecast | AL3: Forecast | AM3: Forecast | AN3: Forecast | AO3: Forecast | AP3: Forecast | AQ3: Forecast | AR3: Forecast | AS3: Forecast | AT3: Forecast | AU3: Forecast | AV3: Forecast | AW3: Forecast | AX3: Forecast | AY3: Forecast | AZ3: Forecast | BA3: Forecast | BB3: Forecast | BC3: Forecast | BD3: Forecast | BE3: Forecast | BF3: Forecast | BG3: Forecast | BH3: Forecast | BI3: Forecast | BJ3: Forecast | BK3: Forecast | BL3: Forecast | BM3: Forecast
B4: REVENUS | F4: 2022 | R4: 2023 | AD4: 2024 | AP4: 2025 | BB4: 2026
F5: 44562 | G5: 44593 | H5: 44621 | I5: 44652 | J5: 44682 | K5: 44713 | L5: 44743 | M5: 44774 | N5: 44805 | O5: 44835 | P5: 44866 | Q5: 44896 | R5: 44927 | S5: 44958 | T5: 44986 | U5: 45017 | V5: 45047 | W5: 45078 | X5: 45108 | Y5: 45139 | Z5: 45170 | AA5: 45200 | AB5: 45231 | AC5: 45261 | AD5: 45292 | AE5: 45323 | AF5: 45352 | AG5: 45383 | AH5: 45413 | AI5: 45444 | AJ5: 45474 | AK5: 45505 | AL5: 45536 | AM5: 45566 | AN5: 45597 | AO5: 45627 | AP5: 45658 | AQ5: 45689 | AR5: 45717 | AS5: 45748 | AT5: 45778 | AU5: 45809 | AV5: 45839 | AW5: 45870 | AX5: 45901 | AY5: 45931 | AZ5: 45962 | BA5: 45992 | BB5: 45658 | BC5: 45689 | BD5: 45717 | BE5: 45748 | BF5: 45778 | BG5: 45809 | BH5: 45839 | BI5: 45870 | BJ5: 45901 | BK5: 45931 | BL5: 45962 | BM5: 45992
B8: KPIS
B10: Churn | R10: ='Marketing and Sales'!R5 -> 103.47826 | S10: ='Marketing and Sales'!S5 -> 83.478261 | T10: ='Marketing and Sales'!T5 -> 61.73913 | U10: ='Marketing and Sales'!U5 -> 62.727273 | V10: ='Marketing and Sales'!V5 -> 102.72727 | W10: ='Marketing and Sales'!W5 -> 106.72727 | X10: ='Marketing and Sales'!X5 -> 129.80952 | Y10: ='Marketing and Sales'!Y5 -> 151.80952 | ... BM10: ='Marketing and Sales'!BM5 -> 5273.8667
B11: Total Clients | R11: ='Marketing and Sales'!R6 -> 72.388092 | S11: ='Marketing and Sales'!S6 -> 75.442686 | T11: ='Marketing and Sales'!T6 -> 75.992903 | U11: ='Marketing and Sales'!U6 -> 75.758976 | V11: ='Marketing and Sales'!V6 -> 75.539271 | W11: ='Marketing and Sales'!W6 -> 75.323141 | X11: ='Marketing and Sales'!X6 -> 75.810648 | Y11: ='Marketing and Sales'!Y6 -> 76.320674 | ... BM11: ='Marketing and Sales'!BM6 -> 1424.7808
B12: Sales (Pharmacy) | R12: ='Marketing and Sales'!R7 -> 4362.6939 | S12: ='Marketing and Sales'!S7 -> 4370.7295 | T12: ='Marketing and Sales'!T7 -> 4356.4757 | U12: ='Marketing and Sales'!U7 -> 4343.444 | V12: ='Marketing and Sales'!V7 -> 4370.632 | W12: ='Marketing and Sales'!W7 -> 4398.0362 | X12: ='Marketing and Sales'!X7 -> 4446.035 | Y12: ='Marketing and Sales'!Y7 -> 4513.5239 | ... BM12: ='Marketing and Sales'!BM7 -> 79459.878
B13: avg cost of shipping | R13: 8 | S13: 8 | T13: 8 | U13: 8 | V13: 8 | W13: 8 | X13: 8 | Y13: 8 | Z13: 8 | AA13: 8 | AB13: 8 | AC13: 8 | AD13: 7.5 | AE13: 7.5 | AF13: 7.5 | AG13: 7.5 | AH13: 7.5 | AI13: 7.5 | AJ13: 7 | AK13: 7 | AL13: 7 | AM13: 7 | AN13: 7 | AO13: 7 | AP13: 7 | AQ13: 7 | AR13: 7 | AS13: 7 | AT13: 7 | AU13: 7 | AV13: 7 | AW13: 7 | AX13: 7 | AY13: 7 | AZ13: 7 | BA13: 7 | BB13: 7 | BC13: 7 | BD13: 7 | BE13: 7 | BF13: 7 | BG13: 7 | BH13: 7 | BI13: 7 | BJ13: 7 | BK13: 7 | BL13: 7 | BM13: 7
B14: avg order | R14: 250 | S14: =R14+1 -> 251 | T14: =S14+1 -> 252 | U14: =T14+1 -> 253 | V14: =U14+1 -> 254 | W14: =V14+1 -> 255 | X14: =W14+1 -> 256 | Y14: =X14+1 -> 257 | Z14: =Y14+1 -> 258 | ... BM14: =BL14+1 -> 297
B15: no of shipments
B17: Pharmacy Revenues | P17: ='Marketing and Sales'!P8 -> 375747.67 | Q17: ='Marketing and Sales'!Q8 -> 359175 | R17: ='Marketing and Sales'!R8 -> 401284.28 | S17: ='Marketing and Sales'!S8 -> 395821.8 | T17: ='Marketing and Sales'!T8 -> 393096.67 | U17: ='Marketing and Sales'!U8 -> 436144.26 | V17: ='Marketing and Sales'!V8 -> 429750.16 | W17: ='Marketing and Sales'!W8 -> 407798.21 | ... BM17: ='Marketing and Sales'!BM8 -> 6075790.7
B18: Cost of Goods | C18: 74% now, 73% in 2024, 72% in 2025 | P18: =-P17*(1-0.26) -> -278053.28 | Q18: =-Q17*(1-0.26) -> -265789.5 | R18: =-R17*(1-0.26) -> -296950.37 | S18: =-S17*(1-0.26) -> -292908.13 | T18: =-T17*(1-0.26) -> -290891.54 | U18: =-U17*(1-0.26) -> -322746.75 | V18: =-V17*(1-0.26) -> -318015.12 | W18: =-W17*(1-0.26) -> -301770.68 | ... AC18: =-AC17*(1-0.26) -> -340511.54 | AD18: =-AD17*(1-0.27) -> -311650.26 | AE18: =-AE17*(1-0.27) -> -316925.01 | AF18: =-AF17*(1-0.27) -> -327324.8 | AG18: =-AG17*(1-0.27) -> -367950.95 | AH18: =-AH17*(1-0.27) -> -415363.74 | AI18: =-AI17*(1-0.27) -> -468320.69 | AJ18: =-AJ17*(1-0.27) -> -524962.56 | AK18: =-AK17*(1-0.27) -> -586833 | ... AO18: =-AO17*(1-0.27) -> -945254.07 | AP18: =-AP17*(1-0.28) -> -1035062.6 | AQ18: =-AQ17*(1-0.28) -> -1142423.1 | AR18: =-AR17*(1-0.28) -> -1257899.6 | AS18: =-AS17*(1-0.28) -> -1314327.8 | AT18: =-AT17*(1-0.28) -> -1422841.5 | AU18: =-AU17*(1-0.28) -> -1534826.3 | AV18: =-AV17*(1-0.28) -> -1652151.3 | AW18: =-AW17*(1-0.28) -> -1772812.5 | ... BM18: =-BM17*(1-0.28) -> -4374569.3
B20: Professional Allocations | C20: 0.02 | P20: 25611.24 | Q20: 22264.71 | R20: =+R17*$C$20 -> 8025.6856 | S20: =+S17*$C$20 -> 7916.4359 | T20: =+T17*$C$20 -> 7861.9335 | U20: =+U17*$C$20 -> 8722.8852 | V20: =+V17*$C$20 -> 8595.0032 | W20: =+W17*$C$20 -> 8155.9642 | X20: =+X17*$C$20 -> 9245.304 | Y20: =+Y17*$C$20 -> 7707.5096 | ... BM20: =+BM17*$C$20 -> 121515.81
B22: Distributor Savings | C22: -0.035 | AD22: =-$C$22*AD17 -> 14942.136 | AE22: =-$C$22*AE17 -> 15195.035 | AF22: =-$C$22*AF17 -> 15693.655 | AG22: =-$C$22*AG17 -> 17641.484 | AH22: =-$C$22*AH17 -> 19914.7 | AI22: =-$C$22*AI17 -> 22453.732 | AJ22: =-$C$22*AJ17 -> 25169.438 | AK22: =-$C$22*AK17 -> 28135.829 | ... BM22: =-$C$22*BM17 -> 212652.67
B23: Distributor Expenses | C23: 1250 | AD23: =-$C$23 -> -1250 | AE23: =-$C$23 -> -1250 | AF23: =-$C$23 -> -1250 | AG23: =-$C$23 -> -1250 | AH23: =-$C$23 -> -1250 | AI23: =-$C$23 -> -1250 | AJ23: =-$C$23 -> -1250 | AK23: =-$C$23 -> -1250 | ... BM23: =-$C$23 -> -1250
B25: OTC upsell PSB | C25: 40 | D25: avg | X25: =X12*$C25*$C26 -> 5335.242 | Y25: =Y12*$C25*$C26 -> 5416.2287 | Z25: =Z12*$C25*$C26 -> 5496.1941 | AA25: =AA12*$C25*$C26 -> 5574.7294 | AB25: =AB12*$C25*$C26 -> 5677.2811 | AC25: =AC12*$C25*$C26 -> 5778.4209 | AD25: =AD12*$C25*$C26 -> 5879.3332 | AE25: =AE12*$C25*$C26 -> 6026.4362 | ... BM25: =BM12*$C25*$C26 -> 95351.853
C26: 0.03 | D26: user base
B28: NET REVENUES | F28: =SUM(F8:F18) -> 0 | G28: =SUM(G8:G18) -> 0 | H28: =SUM(H8:H18) -> 0 | I28: =SUM(I8:I18) -> 0 | J28: =SUM(J8:J18) -> 0 | K28: =SUM(K8:K18) -> 0 | L28: =#REF! -> #REF! | P28: =SUM(P17:P27) -> 123305.63 | Q28: =SUM(Q17:Q27) -> 115650.21 | R28: =SUM(R17:R27) -> 112359.6 | S28: =SUM(S17:S27) -> 110830.1 | T28: =SUM(T17:T27) -> 110067.07 | U28: =SUM(U17:U27) -> 122120.39 | V28: =SUM(V17:V27) -> 120330.04 | W28: =SUM(W17:W27) -> 114183.5 | ... BM28: =SUM(BM17:BM27) -> 2129491.7
B29: CUMULATIVE REVENUES | F29: =F28 -> 0 | G29: =F29+G28 -> 0 | H29: =G29+H28 -> 0 | I29: =H29+I28 -> 0 | J29: =I29+J28 -> 0 | K29: =J29+K28 -> 0 | L29: =K29+L28 -> #REF! | P29: =O29+P28 -> 123305.63 | Q29: =P29+Q28 -> 238955.84 | R29: =Q29+R28 -> 351315.44 | S29: =R29+S28 -> 462145.55 | T29: =S29+T28 -> 572212.61 | U29: =T29+U28 -> 694333.01 | V29: =U29+V28 -> 814663.05 | W29: =V29+W28 -> 928846.55 | ... BM29: =BL29+BM28 -> 34036475
B33: Expenses | C33: Annual | F33: 2022 | R33: 2023 | AD33: 2024 | AP33: 2025 | BB33: 2025
C34: compensation | F34: 44562 | G34: 44593 | H34: 44621 | I34: 44652 | J34: 44682 | K34: 44713 | L34: 44743 | M34: 44774 | N34: 44805 | O34: 44835 | P34: 44866 | Q34: 44896 | R34: 44927 | S34: 44958 | T34: 44986 | U34: 45017 | V34: 45047 | W34: 45078 | X34: 45108 | Y34: 45139 | Z34: 45170 | AA34: 45200 | AB34: 45231 | AC34: 45261 | AD34: 45292 | AE34: 45323 | AF34: 45352 | AG34: 45383 | AH34: 45413 | AI34: 45444 | AJ34: 45474 | AK34: 45505 | AL34: 45536 | AM34: 45566 | AN34: 45597 | AO34: 45627 | AP34: 45658 | AQ34: 45689 | AR34: 45717 | AS34: 45748 | AT34: 45778 | AU34: 45809 | AV34: 45839 | AW34: 45870 | AX34: 45901 | AY34: 45931 | AZ34: 45962 | BA34: 45992 | BB34: 45658 | BC34: 45689 | BD34: 45717 | BE34: 45748 | BF34: 45778 | BG34: 45809 | BH34: 45839 | BI34: 45870 | BJ34: 45901 | BK34: 45931 | BL34: 45962 | BM34: 45992
B36: Salaries
B37: Pharmacists | P37: 36702.07 | Q37: 35882.28 | R37: 37886.35 | S37: ='PSB-Salaries & Contractuals'!T19 -> 39087.3 | T37: ='PSB-Salaries & Contractuals'!U19 -> 34719.3 | U37: ='PSB-Salaries & Contractuals'!V19 -> 21594.3 | V37: ='PSB-Salaries & Contractuals'!W19 -> 6685.9667 | W37: ='PSB-Salaries & Contractuals'!X19 -> 6685.9667 | X37: ='PSB-Salaries & Contractuals'!Y19 -> 6685.9667 | Y37: ='PSB-Salaries & Contractuals'!Z19 -> 6685.9667 | Z37: ='PSB-Salaries & Contractuals'!AA19 -> 17685.967 | ... BM37: ='PSB-Salaries & Contractuals'!BN19 -> 23355.733
B38: ATP | P38: 33298.98 | Q38: 33035.49 | R38: 33819.19 | S38: ='PSB-Salaries & Contractuals'!T36 -> 22854.125 | T38: ='PSB-Salaries & Contractuals'!U36 -> 22854.125 | U38: ='PSB-Salaries & Contractuals'!V36 -> 22854.125 | V38: ='PSB-Salaries & Contractuals'!W36 -> 22854.125 | W38: ='PSB-Salaries & Contractuals'!X36 -> 22854.125 | X38: ='PSB-Salaries & Contractuals'!Y36 -> 22854.125 | Y38: ='PSB-Salaries & Contractuals'!Z36 -> 18358.725 | Z38: ='PSB-Salaries & Contractuals'!AA36 -> 18358.725 | ... BM38: ='PSB-Salaries & Contractuals'!BN36 -> 41669.675
B39: SAC | P39: 18778.38 | Q39: 22958.5 | R39: 22958.5 | S39: ='PSB-Salaries & Contractuals'!T53 -> 24585.225 | T39: ='PSB-Salaries & Contractuals'!U53 -> 24585.225 | U39: ='PSB-Salaries & Contractuals'!V53 -> 23072.35 | V39: ='PSB-Salaries & Contractuals'!W53 -> 23072.35 | W39: ='PSB-Salaries & Contractuals'!X53 -> 23072.35 | X39: ='PSB-Salaries & Contractuals'!Y53 -> 23072.35 | Y39: ='PSB-Salaries & Contractuals'!Z53 -> 23072.35 | Z39: ='PSB-Salaries & Contractuals'!AA53 -> 23072.35 | ... BM39: ='PSB-Salaries & Contractuals'!BN53 -> 38494.717
B41: Fringes + Bonus | C41: 0.11 | R41: 0 | S41: =(SUM(S37:S39))*$C41 -> 9517.9315 | T41: =(SUM(T37:T39))*$C41 -> 9037.4515 | U41: =(SUM(U37:U39))*$C41 -> 7427.2852 | V41: =(SUM(V37:V39))*$C41 -> 5787.3686 | W41: =(SUM(W37:W39))*$C41 -> 5787.3686 | X41: =(SUM(X37:X39))*$C41 -> 5787.3686 | Y41: =(SUM(Y37:Y39))*$C41 -> 5292.8746 | Z41: =(SUM(Z37:Z39))*$C41 -> 6502.8746 | ... BM41: =(SUM(BM37:BM39))*$C41 -> 11387.214
B43: Contractuals Pharmacy Total | R43: ='PSB-Salaries & Contractuals'!S67 -> 1000 | S43: ='PSB-Salaries & Contractuals'!T67 -> 1000 | T43: ='PSB-Salaries & Contractuals'!U67 -> 1000 | U43: ='PSB-Salaries & Contractuals'!V67 -> 1000 | V43: ='PSB-Salaries & Contractuals'!W67 -> 1000 | W43: ='PSB-Salaries & Contractuals'!X67 -> 1000 | X43: ='PSB-Salaries & Contractuals'!Y67 -> 1000 | Y43: ='PSB-Salaries & Contractuals'!Z67 -> 1000 | ... BM43: ='PSB-Salaries & Contractuals'!BN67 -> 1000
B45: Professionals
B46: Accounting Fees | P46: 5202.7 | Q46: 1746 | R46: 1200 | S46: 1200 | T46: 1200 | U46: =5000+1200 -> 6200 | V46: 1200 | W46: 1200 | X46: 1200 | Y46: 1200 | Z46: 1200 | AA46: 1200 | AB46: 1200 | AC46: 1200 | AD46: 1200 | AE46: 1200 | AF46: 1200 | AG46: =5000+1200 -> 6200 | AH46: =5000+1200 -> 6200 | AI46: 1200 | AJ46: 1200 | AK46: 1200 | AL46: 1200 | AM46: 1200 | AN46: 1200 | AO46: 1200 | AP46: 1200 | AQ46: 1200 | AR46: 1200 | AS46: =5000+1200 -> 6200 | AT46: 1200 | AU46: 1200 | AV46: 1200 | AW46: 1200 | AX46: 1200 | AY46: 1200 | AZ46: 1200 | BA46: 1200 | BB46: 1200 | BC46: 1200 | BD46: 1200 | BE46: =5000+1200 -> 6200 | BF46: 1200 | BG46: 1200 | BH46: 1200 | BI46: 1200 | BJ46: 1200 | BK46: 1200 | BL46: 1200 | BM46: 1200
B47: Legal Fees | R47: 500 | S47: 500 | T47: 500 | U47: 500 | V47: 500 | W47: 500 | X47: 500 | Y47: 500 | Z47: 500 | AA47: 500 | AB47: 500 | AC47: 500 | AD47: 500 | AE47: 500 | AF47: 500 | AG47: 500 | AH47: 500 | AI47: 500 | AJ47: 500 | AK47: 500 | AL47: 500 | AM47: 500 | AN47: 500 | AO47: 500 | AP47: 500 | AQ47: 500 | AR47: 500 | AS47: 500 | AT47: 500 | AU47: 500 | AV47: 500 | AW47: 500 | AX47: 500 | AY47: 500 | AZ47: 500 | BA47: 500 | BB47: 500 | BC47: 500 | BD47: 500 | BE47: 500 | BF47: 500 | BG47: 500 | BH47: 500 | BI47: 500 | BJ47: 500 | BK47: 500 | BL47: 500 | BM47: 500
B48: Other
B52: SubTotal Salaries | F52: =SUM(F37:F49) -> 0 | G52: =SUM(G37:G49) -> 0 | H52: =SUM(H37:H49) -> 0 | I52: =SUM(I37:I49) -> 0 | J52: =SUM(J37:J49) -> 0 | K52: =SUM(K37:K49) -> 0 | L52: =SUM(L37:L49) -> 0 | M52: =SUM(M37:M49) -> 0 | ... BM52: =SUM(BM37:BM49) -> 117607.34
B54: Rent | P54: 0 | Q54: 0 | R54: 0 | S54: 0 | T54: 0 | U54: 0 | V54: 0 | W54: 0 | X54: 0 | Y54: 0 | Z54: 0 | AA54: 0 | AB54: 0 | AC54: 0 | AD54: 0 | AE54: 0 | AF54: 0 | AG54: 0 | AH54: 0 | AI54: 0 | AJ54: 0 | AK54: 0 | AL54: 0 | AM54: 0 | AN54: 0 | AO54: 0 | AP54: 0 | AQ54: 0 | AR54: 0 | AS54: 0 | AT54: 0 | AU54: 0 | AV54: 0 | AW54: 0 | AX54: 0 | AY54: 0 | AZ54: 0 | BA54: 0 | BB54: 0 | BC54: 0 | BD54: 0 | BE54: 0 | BF54: 0 | BG54: 0 | BH54: 0 | BI54: 0 | BJ54: 0 | BK54: 0 | BL54: 0 | BM54: 0
B55: Utiities | R55: 0 | S55: 0 | T55: 0 | U55: 0 | V55: 0 | W55: 0 | X55: 0 | Y55: 0 | Z55: 0 | AA55: 0 | AB55: 0 | AC55: 0 | AD55: 0 | AE55: 0 | AF55: 0 | AG55: 0 | AH55: 0 | AI55: 0 | AJ55: 0 | AK55: 0 | AL55: 0 | AM55: 0 | AN55: 0 | AO55: 0 | AP55: 0 | AQ55: 0 | AR55: 0 | AS55: 0 | AT55: 0 | AU55: 0 | AV55: 0 | AW55: 0 | AX55: 0 | AY55: 0 | AZ55: 0 | BA55: 0 | BB55: 0 | BC55: 0 | BD55: 0 | BE55: 0 | BF55: 0 | BG55: 0 | BH55: 0 | BI55: 0 | BJ55: 0 | BK55: 0 | BL55: 0 | BM55: 0
B56: Insurance | R56: 0 | S56: 0 | T56: 0 | U56: 0 | V56: 0 | W56: 0 | X56: 0 | Y56: 0 | Z56: 0 | AA56: 0 | AB56: 0 | AC56: 0 | AD56: 750 | AE56: 750 | AF56: 750 | AG56: 750 | AH56: 750 | AI56: 750 | AJ56: 750 | AK56: 750 | AL56: 750 | AM56: 750 | AN56: 750 | AO56: 750 | AP56: 750 | AQ56: 750 | AR56: 750 | AS56: 750 | AT56: 750 | AU56: 750 | AV56: 750 | AW56: 750 | AX56: 750 | AY56: 750 | AZ56: 750 | BA56: 750 | BB56: 750 | BC56: 750 | BD56: 750 | BE56: 750 | BF56: 750 | BG56: 750 | BH56: 750 | BI56: 750 | BJ56: 750 | BK56: 750 | BL56: 750 | BM56: 750
B57: Meals and Entertainment | P57: 675 | R57: 250 | S57: 250 | T57: 250 | U57: 250 | V57: 250 | W57: 250 | X57: 250 | Y57: 250 | Z57: 250 | AA57: 250 | AB57: 250 | AC57: 250 | AD57: 250 | AE57: 250 | AF57: 250 | AG57: 250 | AH57: 250 | AI57: 250 | AJ57: 250 | AK57: 250 | AL57: 250 | AM57: 250 | AN57: 250 | AO57: 250 | AP57: 250 | AQ57: 250 | AR57: 250 | AS57: 250 | AT57: 250 | AU57: 250 | AV57: 250 | AW57: 250 | AX57: 250 | AY57: 250 | AZ57: 250 | BA57: 250 | BB57: 250 | BC57: 250 | BD57: 250 | BE57: 250 | BF57: 250 | BG57: 250 | BH57: 250 | BI57: 250 | BJ57: 250 | BK57: 250 | BL57: 250 | BM57: 250
B58: Travel Expenses | P58: -82.62 | Q58: -77.93 | R58: 0 | S58: 0 | T58: 0 | U58: 0 | V58: 0 | W58: 0 | X58: 0 | Y58: 0 | Z58: 0 | AA58: 0 | AB58: 0 | AC58: 0 | AD58: 0 | AE58: 0 | AF58: 0 | AG58: 0 | AH58: 0 | AI58: 0 | AJ58: 0 | AK58: 0 | AL58: 0 | AM58: 0 | AN58: 0 | AO58: 0 | AP58: 0 | AQ58: 0 | AR58: 0 | AS58: 0 | AT58: 0 | AU58: 0 | AV58: 0 | AW58: 0 | AX58: 0 | AY58: 0 | AZ58: 0 | BA58: 0 | BB58: 0 | BC58: 0 | BD58: 0 | BE58: 0 | BF58: 0 | BG58: 0 | BH58: 0 | BI58: 0 | BJ58: 0 | BK58: 0 | BL58: 0 | BM58: 0
B59: Depreciation | R59: =Q59/7 -> 0 | S59: =R59/7 -> 0 | T59: =S59/7 -> 0 | U59: =T59/7 -> 0 | V59: =U59/7 -> 0 | W59: =V59/7 -> 0 | X59: =W59/7 -> 0 | Y59: =X59/7 -> 0 | ... BM59: =BL59/7 -> 0
B60: Telecommunication | R60: 0 | S60: 0 | T60: 0 | U60: 0 | V60: 0 | W60: 0 | X60: 0 | Y60: 0 | Z60: 0 | AA60: 0 | AB60: 0 | AC60: 0 | AD60: 0 | AE60: 0 | AF60: 0 | AG60: 0 | AH60: 0 | AI60: 0 | AJ60: 0 | AK60: 0 | AL60: 0 | AM60: 0 | AN60: 0 | AO60: 0 | AP60: 0 | AQ60: 0 | AR60: 0 | AS60: 0 | AT60: 0 | AU60: 0 | AV60: 0 | AW60: 0 | AX60: 0 | AY60: 0 | AZ60: 0 | BA60: 0 | BB60: 0 | BC60: 0 | BD60: 0 | BE60: 0 | BF60: 0 | BG60: 0 | BH60: 0 | BI60: 0 | BJ60: 0 | BK60: 0 | BL60: 0 | BM60: 0
B61: Pharmacy Automation (robot) - rental to Medzy | V61: 3000 | W61: 3000 | X61: 3000 | Y61: 3000 | Z61: 3000 | AA61: 3000 | AB61: 3000 | AC61: 3000 | AD61: 3000 | AE61: 3000 | AF61: 3000 | AG61: 3000 | AH61: 3000 | AI61: 3000 | AJ61: 3000 | AK61: 3000 | AL61: 3000 | AM61: 3000 | AN61: 3000 | AO61: 3000 | AP61: 3000 | AQ61: 3000 | AR61: 3000 | AS61: 3000 | AT61: 3000 | AU61: 3000 | AV61: 3000 | AW61: 3000 | AX61: 3000 | AY61: 3000 | AZ61: 3000 | BA61: 3000 | BB61: 3000 | BC61: 3000 | BD61: 3000 | BE61: 3000 | BF61: 3000 | BG61: 3000 | BH61: 3000 | BI61: 3000 | BJ61: 3000 | BK61: 3000 | BL61: 3000 | BM61: 3000
B62: License and Subscriptions | P62: 392 | Q62: 348.84 | R62: 250 | S62: 250 | T62: 250 | U62: 250 | V62: 250 | W62: 250 | X62: 250 | Y62: 250 | Z62: 250 | AA62: 250 | AB62: 250 | AC62: 250 | AD62: 250 | AE62: 250 | AF62: 250 | AG62: 250 | AH62: 250 | AI62: 250 | AJ62: 250 | AK62: 250 | AL62: 250 | AM62: 250 | AN62: 250 | AO62: 250 | AP62: 250 | AQ62: 250 | AR62: 250 | AS62: 250 | AT62: 250 | AU62: 250 | AV62: 250 | AW62: 250 | AX62: 250 | AY62: 250 | AZ62: 250 | BA62: 250 | BB62: 250 | BC62: 250 | BD62: 250 | BE62: 250 | BF62: 250 | BG62: 250 | BH62: 250 | BI62: 250 | BJ62: 250 | BK62: 250 | BL62: 250 | BM62: 250
B63: Repair and Maintenance | R63: 0 | S63: 0 | T63: 0 | U63: 0 | V63: 0 | W63: 0 | X63: 0 | Y63: 0 | Z63: 0 | AA63: 0 | AB63: 0 | AC63: 0 | AD63: 0 | AE63: 0 | AF63: 0 | AG63: 0 | AH63: 0 | AI63: 0 | AJ63: 0 | AK63: 0 | AL63: 0 | AM63: 0 | AN63: 0 | AO63: 0 | AP63: 0 | AQ63: 0 | AR63: 0 | AS63: 0 | AT63: 0 | AU63: 0 | AV63: 0 | AW63: 0 | AX63: 0 | AY63: 0 | AZ63: 0 | BA63: 0 | BB63: 0 | BC63: 0 | BD63: 0 | BE63: 0 | BF63: 0 | BG63: 0 | BH63: 0 | BI63: 0 | BJ63: 0 | BK63: 0 | BL63: 0 | BM63: 0
B64: Recruitment Charges | R64: 0 | S64: 0 | T64: 0 | U64: 0 | V64: 0 | W64: 0 | X64: 0 | Y64: 0 | Z64: 0 | AA64: 0 | AB64: 0 | AC64: 0 | AD64: 0 | AE64: 0 | AF64: 0 | AG64: 0 | AH64: 0 | AI64: 0 | AJ64: 0 | AK64: 0 | AL64: 0 | AM64: 0 | AN64: 0 | AO64: 0 | AP64: 0 | AQ64: 0 | AR64: 0 | AS64: 0 | AT64: 0 | AU64: 0 | AV64: 0 | AW64: 0 | AX64: 0 | AY64: 0 | AZ64: 0 | BA64: 0 | BB64: 0 | BC64: 0 | BD64: 0 | BE64: 0 | BF64: 0 | BG64: 0 | BH64: 0 | BI64: 0 | BJ64: 0 | BK64: 0 | BL64: 0 | BM64: 0
B65: Offices Expenses | P65: =6267.99-735.68 -> 5532.31 | Q65: 4440.32 | R65: 1000 | S65: 1000 | T65: 1000 | U65: 1000 | V65: 1000 | W65: 1000 | X65: 1000 | Y65: 1000 | Z65: 1000 | AA65: 1000 | AB65: 1000 | AC65: 1000 | AD65: 1000 | AE65: 1000 | AF65: 1000 | AG65: 1000 | AH65: 1000 | AI65: 1000 | AJ65: 1000 | AK65: 1000 | AL65: 1000 | AM65: 1000 | AN65: 1000 | AO65: 1000 | AP65: 1000 | AQ65: 1000 | AR65: 1000 | AS65: 1000 | AT65: 1000 | AU65: 1000 | AV65: 1000 | AW65: 1000 | AX65: 1000 | AY65: 1000 | AZ65: 1000 | BA65: 1000 | BB65: 1000 | BC65: 1000 | BD65: 1000 | BE65: 1000 | BF65: 1000 | BG65: 1000 | BH65: 1000 | BI65: 1000 | BJ65: 1000 | BK65: 1000 | BL65: 1000 | BM65: 1000
B66: Taxes, Permit | R66: 0 | S66: 0 | T66: 0 | U66: 0 | V66: 0 | W66: 0 | X66: 0 | Y66: 0 | Z66: 0 | AA66: 0 | AB66: 0 | AC66: 0 | AD66: 0 | AE66: 0 | AF66: 0 | AG66: 0 | AH66: 0 | AI66: 0 | AJ66: 0 | AK66: 0 | AL66: 0 | AM66: 0 | AN66: 0 | AO66: 0 | AP66: 0 | AQ66: 0 | AR66: 0 | AS66: 0 | AT66: 0 | AU66: 0 | AV66: 0 | AW66: 0 | AX66: 0 | AY66: 0 | AZ66: 0 | BA66: 0 | BB66: 0 | BC66: 0 | BD66: 0 | BE66: 0 | BF66: 0 | BG66: 0 | BH66: 0 | BI66: 0 | BJ66: 0 | BK66: 0 | BL66: 0 | BM66: 0
B67: Interest and bank charges | P67: 404.61 | Q67: 501.31 | R67: 500 | S67: 500 | T67: 500 | U67: 500 | V67: 500 | W67: 500 | X67: 500 | Y67: 500 | Z67: 500 | AA67: 500 | AB67: 500 | AC67: 500 | AD67: 500 | AE67: 500 | AF67: 500 | AG67: 500 | AH67: 500 | AI67: 500 | AJ67: 500 | AK67: 500 | AL67: 500 | AM67: 500 | AN67: 500 | AO67: 500 | AP67: 500 | AQ67: 500 | AR67: 500 | AS67: 500 | AT67: 500 | AU67: 500 | AV67: 500 | AW67: 500 | AX67: 500 | AY67: 500 | AZ67: 500 | BA67: 500 | BB67: 500 | BC67: 500 | BD67: 500 | BE67: 500 | BF67: 500 | BG67: 500 | BH67: 500 | BI67: 500 | BJ67: 500 | BK67: 500 | BL67: 500 | BM67: 500
B68: Transactions Fees - Credit Card | C68: 0.006 | P68: 2111.6 | Q68: 2359.71 | R68: =+$C$68*R17 -> 2407.7057 | S68: =+$C$68*S17 -> 2374.9308 | T68: =+$C$68*T17 -> 2358.58 | U68: =+$C$68*U17 -> 2616.8656 | V68: =+$C$68*V17 -> 2578.501 | W68: =+$C$68*W17 -> 2446.7893 | X68: =+$C$68*X17 -> 2773.5912 | Y68: =+$C$68*Y17 -> 2312.2529 | ... BM68: =+$C$68*BM17 -> 36454.744
B69: Packaging and Shipping | C69: from 5.5% to 4% of Gross | P69: =20487.03+498.78 -> 20985.81 | Q69: =22826.45+184.5 -> 23010.95 | R69: =17113.55+184.5 -> 17298.05 | S69: =0.055*S17 -> 21770.199 | T69: =0.055*T17 -> 21620.317 | U69: =0.055*U17 -> 23987.934 | V69: =0.055*V17 -> 23636.259 | W69: =0.055*W17 -> 22428.902 | X69: =0.05*X17 -> 23113.26 | Y69: =0.05*Y17 -> 19268.774 | Z69: =0.05*Z17 -> 19398.112 | AA69: =0.05*AA17 -> 25182.089 | AB69: =0.05*AB17 -> 22509.698 | AC69: =0.05*AC17 -> 23007.537 | AD69: =0.045*AC17 -> 20706.783 | AE69: =0.045*AD17 -> 19211.318 | AF69: =0.045*AE17 -> 19536.473 | AG69: =0.045*AF17 -> 20177.556 | AH69: =0.045*AG17 -> 22681.908 | AI69: =0.045*AH17 -> 25604.614 | AJ69: =0.045*AJ17 -> 32360.705 | AK69: =0.045*AK17 -> 36174.637 | AL69: =0.045*AL17 -> 41387.174 | AM69: =0.045*AM17 -> 46913.374 | AN69: =0.045*AN17 -> 52846.94 | AO69: =0.045*AO17 -> 58269.087 | AP69: =0.04*AP17 -> 57503.48 | AQ69: =0.04*AQ17 -> 63467.95 | AR69: =0.04*AR17 -> 69883.31 | AS69: =0.04*AS17 -> 73018.209 | AT69: =0.04*AT17 -> 79046.749 | AU69: =0.04*AU17 -> 85268.13 | AV69: =0.04*AV17 -> 91786.182 | AW69: =0.04*AW17 -> 98489.585 | ... BM69: =0.04*BM17 -> 243031.63
B70: Exchange Gain or Loss
B71: Loans
B74: Platform Fees - Medzy | P74: ='Marketing and Sales'!P10 -> 67254.145 | Q74: ='Marketing and Sales'!Q10 -> 69258.154 | R74: ='Marketing and Sales'!R10 -> 70328.32 | S74: ='Marketing and Sales'!S10 -> 69268.814 | T74: ='Marketing and Sales'!T10 -> 68791.918 | U74: ='Marketing and Sales'!U10 -> 68340.521 | V74: ='Marketing and Sales'!V10 -> 68246.948 | W74: ='Marketing and Sales'!W10 -> 68161.064 | ... BM74: ='Marketing and Sales'!BM10 -> 1293687.9
B76: TOTAL EXPENSES | F76: =SUM(F52:F74) -> 0 | G76: =SUM(G52:G74) -> 0 | H76: =SUM(H52:H74) -> 0 | I76: =SUM(I52:I74) -> 0 | J76: =SUM(J52:J74) -> 0 | K76: =SUM(K52:K74) -> 0 | L76: =SUM(L52:L74) -> 0 | M76: =SUM(M52:M74) -> 0 | ... BM76: =SUM(BM52:BM74) -> 1696531.6
B78: P&L (Before Taxes Credits) | L78: =L28-L76 -> #REF! | M78: =M28-M76 -> 0 | N78: =N28-N76 -> 0 | P78: =P28-P76 -> -67949.351 | Q78: =Q28-Q76 -> -77813.414 | R78: =R28-R76 -> -77038.517 | S78: =S28-S76 -> -83328.423 | T78: =T28-T76 -> -78599.848 | U78: =U28-U76 -> -57472.989 | V78: =V28-V76 -> -40231.473 | W78: =W28-W76 -> -44953.067 | ... BM78: =BM28-BM76 -> 432960.16
B79: CUMULATIVE P&L (Before Taxes Credit) | N79: =M79+N78 -> 0 | P79: =O79+P78 -> -67949.351 | Q79: =P79+Q78 -> -145762.77 | R79: =Q79+R78 -> -222801.28 | S79: =R79+S78 -> -306129.7 | T79: =S79+T78 -> -384729.55 | U79: =T79+U78 -> -442202.54 | V79: =U79+V78 -> -482434.01 | W79: =V79+W78 -> -527387.08 | ... BM79: =BL79+BM78 -> 5810726
B84: CASHFLOW | R84: 2023 | AD84: 2024 | AP84: 2025 | BB84: 2025
R85: 44927 | S85: 44958 | T85: 44986 | U85: 45017 | V85: 45047 | W85: 45078 | X85: 45108 | Y85: 45139 | Z85: 45170 | AA85: 45200 | AB85: 45231 | AC85: 45261 | AD85: 45292 | AE85: 45323 | AF85: 45352 | AG85: 45383 | AH85: 45413 | AI85: 45444 | AJ85: 45474 | AK85: 45505 | AL85: 45536 | AM85: 45566 | AN85: 45597 | AO85: 45627 | AP85: 45658 | AQ85: 45689 | AR85: 45717 | AS85: 45748 | AT85: 45778 | AU85: 45809 | AV85: 45839 | AW85: 45870 | AX85: 45901 | AY85: 45931 | AZ85: 45962 | BA85: 45992 | BB85: 45658 | BC85: 45689 | BD85: 45717 | BE85: 45748 | BF85: 45778 | BG85: 45809 | BH85: 45839 | BI85: 45870 | BJ85: 45901 | BK85: 45931 | BL85: 45962 | BM85: 45992
B87: Cash Beginning | P87: 0 | Q87: =P96 -> -695.2058 | R87: =Q96 -> -9250.4658 | S87: =R96 -> -15960.663 | T87: =S96 -> 9979.7286 | U87: =T96 -> 171.79853 | V87: =U96 -> 11039.331 | W87: =V96 -> 39054.806 | X87: =W96 -> 62262.804 | ... BM87: =BL96 -> 4735705.1
B89: Profit/Loss | P89: =P78 -> -67949.351 | Q89: =Q78 -> -77813.414 | R89: =R78 -> -77038.517 | S89: =S78 -> -83328.423 | T89: =T78 -> -78599.848 | U89: =U78 -> -57472.989 | V89: =V78 -> -40231.473 | W89: =W78 -> -44953.067 | ... BM89: =BM78 -> 432960.16
B90: Not Paid to Medzy | P90: =-'P&L Medzy '!P85 -> 67254.145 | Q90: =-'P&L Medzy '!Q85 -> 69258.154 | R90: =-'P&L Medzy '!R85 -> 70328.32 | S90: =-'P&L Medzy '!S85 -> 69268.814 | T90: =-'P&L Medzy '!T85 -> 68791.918 | U90: =-'P&L Medzy '!U85 -> 68340.521 | V90: =-'P&L Medzy '!V85 -> 68246.948 | W90: =-'P&L Medzy '!W85 -> 68161.064 | ... BM90: =-'P&L Medzy '!BM85 -> 0
B91: PSB Payment of Interco Partial | X91: -50000 | Y91: -50000 | Z91: -50000 | AA91: -50000 | AB91: -50000 | AC91: -50000
B92: PSB Payment of Interco Balance | P92: =-'P&L Medzy '!P87 -> 0 | Q92: =-'P&L Medzy '!Q87 -> 0 | R92: =-'P&L Medzy '!R87 -> 0 | S92: =-'P&L Medzy '!S87 -> 0 | T92: =-'P&L Medzy '!T87 -> 0 | U92: =-'P&L Medzy '!U87 -> 0 | V92: =-'P&L Medzy '!V87 -> 0 | W92: =-'P&L Medzy '!W87 -> 0 | ... BM92: =-'P&L Medzy '!BM87 -> 0
B94: Avance par Sonia | S94: 40000
B96: Cash End of Period | P96: =SUM(P87:P95) -> -695.2058 | Q96: =SUM(Q87:Q95) -> -9250.4658 | R96: =SUM(R87:R95) -> -15960.663 | S96: =SUM(S87:S95) -> 9979.7286 | T96: =SUM(T87:T95) -> 171.79853 | U96: =SUM(U87:U95) -> 11039.331 | V96: =SUM(V87:V95) -> 39054.806 | W96: =SUM(W87:W95) -> 62262.804 | ... BM96: =SUM(BM87:BM95) -> 5168665.3
B99: ='P&L Medzy '!#REF! -> #REF!
B101: ='P&L Medzy '!B111 -> PSB Owed to Medzy Balance | P101: ='P&L Medzy '!P111 -> 0 | Q101: ='P&L Medzy '!Q111 -> 1752759 | R101: ='P&L Medzy '!R111 -> 1823087.3 | S101: ='P&L Medzy '!S111 -> 1892356.1 | T101: ='P&L Medzy '!T111 -> 1961148.1 | U101: ='P&L Medzy '!U111 -> 2019488.6 | V101: ='P&L Medzy '!V111 -> 2037735.5 | W101: ='P&L Medzy '!W111 -> 2105896.6 | ... AY101: ='P&L Medzy '!AY111 -> 1225186 | BB101: ='P&L Medzy '!BB111 -> 1114186 | BC101: ='P&L Medzy '!BC111 -> 1114186 | BD101: ='P&L Medzy '!BD111 -> 1114186 | BE101: ='P&L Medzy '!BE111 -> 1114186 | BF101: ='P&L Medzy '!BF111 -> 1114186 | BG101: ='P&L Medzy '!BG111 -> 1114186 | BH101: ='P&L Medzy '!BH111 -> 1114186 | BI101: ='P&L Medzy '!BI111 -> 1114186 | ... BM101: ='P&L Medzy '!BM111 -> 1114186
B107: KPIs | R107: 2023 | AD107: 2024 | AP107: 2025 | BB107: 2025
R108: 44927 | S108: 44958 | T108: 44986 | U108: 45017 | V108: 45047 | W108: 45078 | X108: 45108 | Y108: 45139 | Z108: 45170 | AA108: 45200 | AB108: 45231 | AC108: 45261 | AD108: 45292 | AE108: 45323 | AF108: 45352 | AG108: 45383 | AH108: 45413 | AI108: 45444 | AJ108: 45474 | AK108: 45505 | AL108: 45536 | AM108: 45566 | AN108: 45597 | AO108: 45627 | AP108: 45658 | AQ108: 45689 | AR108: 45717 | AS108: 45748 | AT108: 45778 | AU108: 45809 | AV108: 45839 | AW108: 45870 | AX108: 45901 | AY108: 45931 | AZ108: 45962 | BA108: 45992 | BB108: 45658 | BC108: 45689 | BD108: 45717 | BE108: 45748 | BF108: 45778 | BG108: 45809 | BH108: 45839 | BI108: 45870 | BJ108: 45901 | BK108: 45931 | BL108: 45962 | BM108: 45992

Sheet PSB-Salaries & Contractuals
B2: Annual Raise | C2: 0.05
B4: SALARIES | G4: 2022 | S4: 2023 | AE4: 2024 | AQ4: 2025 | BC4: 2026
G5: 44562 | H5: 44593 | I5: 44621 | J5: 44652 | K5: 44682 | L5: 44713 | M5: 44743 | N5: 44774 | O5: 44805 | P5: 44835 | Q5: 44866 | R5: 44896 | S5: 44927 | T5: 44958 | U5: 44986 | V5: 45017 | W5: 45047 | X5: 45078 | Y5: 45108 | Z5: 45139 | AA5: 45170 | AB5: 45200 | AC5: 45231 | AD5: 45261 | AE5: 45292 | AF5: 45323 | AG5: 45352 | AH5: 45383 | AI5: 45413 | AJ5: 45444 | AK5: 45474 | AL5: 45505 | AM5: 45536 | AN5: 45566 | AO5: 45597 | AP5: 45627 | AQ5: 45658 | AR5: 45689 | AS5: 45717 | AT5: 45748 | AU5: 45778 | AV5: 45809 | AW5: 45839 | AX5: 45870 | AY5: 45901 | AZ5: 45931 | BA5: 45962 | BB5: 45992 | BC5: 45658 | BD5: 45689 | BE5: 45717 | BF5: 45748 | BG5: 45778 | BH5: 45809 | BI5: 45839 | BJ5: 45870 | BK5: 45901 | BL5: 45931 | BM5: 45962 | BN5: 45992
B6: Role | C6: Employee | D6: Annual Compesation
B8: Phamacists
A10: 1 | B10: Lead Pharmacist | C10: Anthony | D10: 150000 | E10: note: readjusting his salary | S10: =($D10/12)*(1+$C$2) -> 13125 | T10: =($D10/12)*(1+$C$2) -> 13125 | U10: =($D10/12)*(1+$C$2) -> 13125 | V10: =($D10/12)*(1+$C$2) -> 13125
A11: 2 | B11: Phamacist | C11: Maggee | D11: 150000 | S11: =($D11/12)*(1+$C$2) -> 13125 | T11: =($D11/12)*(1+$C$2) -> 13125 | U11: =T11 -> 13125
A12: 3 | B12: Pharmacist | C12: Charles | D12: 49920 | E12: part time | S12: =($D12/12)*(1+$C$2) -> 4368 | T12: =($D12/12)*(1+$C$2) -> 4368 | AE12: =($D12/12)*(1+$C$2+$C$2) -> 4576 | AF12: =($D12/12)*(1+$C$2+$C$2) -> 4576 | AG12: =($D12/12)*(1+$C$2+$C$2) -> 4576 | AH12: =($D12/12)*(1+$C$2+$C$2) -> 4576 | AI12: =($D12/12)*(1+$C$2+$C$2) -> 4576 | AJ12: =($D12/12)*(1+$C$2+$C$2) -> 4576 | AK12: =($D12/12)*(1+$C$2+$C$2) -> 4576 | AL12: =($D12/12)*(1+$C$2+$C$2) -> 4576 | ... AP12: =($D12/12)*(1+$C$2+$C$2) -> 4576 | AQ12: =($D12/12)*(1+$C$2+$C$2+$C$2) -> 4784 | AR12: =($D12/12)*(1+$C$2+$C$2+$C$2) -> 4784 | AS12: =($D12/12)*(1+$C$2+$C$2+$C$2) -> 4784 | AT12: =($D12/12)*(1+$C$2+$C$2+$C$2) -> 4784 | AU12: =($D12/12)*(1+$C$2+$C$2+$C$2) -> 4784 | AV12: =($D12/12)*(1+$C$2+$C$2+$C$2) -> 4784 | AW12: =($D12/12)*(1+$C$2+$C$2+$C$2) -> 4784 | AX12: =($D12/12)*(1+$C$2+$C$2+$C$2) -> 4784 | ... BN12: =($D12/12)*(1+$C$2+$C$2+$C$2) -> 4784
A13: 4 | B13: Phamacist | C13: Stephanie | D13: 78000 | E13: part time | S13: =($D13/12)*(1+$C$2) -> 6825 | T13: =($D13/12)*(1+$C$2) -> 6825 | U13: =($D13/12)*(1+$C$2) -> 6825 | V13: =($D13/12)*(1+$C$2) -> 6825
A14: 5 | B14: Phamacist | C14: Hubert | D14: 7560 | S14: =($D14/12)*(1+$C$2) -> 661.5 | T14: =($D14/12)*(1+$C$2) -> 661.5 | U14: =($D14/12)*(1+$C$2) -> 661.5 | V14: =($D14/12)*(1+$C$2) -> 661.5 | W14: =($D14/12)*(1+$C$2) -> 661.5 | X14: =($D14/12)*(1+$C$2) -> 661.5 | Y14: =($D14/12)*(1+$C$2) -> 661.5 | Z14: =($D14/12)*(1+$C$2) -> 661.5 | ... AD14: =($D14/12)*(1+$C$2) -> 661.5 | AE14: =($D14/12)*(1+$C$2+$C$2) -> 693 | AF14: =($D14/12)*(1+$C$2+$C$2) -> 693 | AG14: =($D14/12)*(1+$C$2+$C$2) -> 693 | AH14: =($D14/12)*(1+$C$2+$C$2) -> 693 | AI14: =($D14/12)*(1+$C$2+$C$2) -> 693 | AJ14: =($D14/12)*(1+$C$2+$C$2) -> 693 | AK14: =($D14/12)*(1+$C$2+$C$2) -> 693 | AL14: =($D14/12)*(1+$C$2+$C$2) -> 693 | ... AP14: =($D14/12)*(1+$C$2+$C$2) -> 693 | AQ14: =($D14/12)*(1+$C$2+$C$2+$C$2) -> 724.5 | AR14: =($D14/12)*(1+$C$2+$C$2+$C$2) -> 724.5 | AS14: =($D14/12)*(1+$C$2+$C$2+$C$2) -> 724.5 | AT14: =($D14/12)*(1+$C$2+$C$2+$C$2) -> 724.5 | AU14: =($D14/12)*(1+$C$2+$C$2+$C$2) -> 724.5 | AV14: =($D14/12)*(1+$C$2+$C$2+$C$2) -> 724.5 | AW14: =($D14/12)*(1+$C$2+$C$2+$C$2) -> 724.5 | AX14: =($D14/12)*(1+$C$2+$C$2+$C$2) -> 724.5 | ... BN14: =($D14/12)*(1+$C$2+$C$2+$C$2) -> 724.5
A15: 6 | B15: Nurse | C15: Ouafaa | D15: 11232 | S15: =($D15/12)*(1+$C$2) -> 982.8 | T15: =($D15/12)*(1+$C$2) -> 982.8 | U15: =($D15/12)*(1+$C$2) -> 982.8 | V15: =($D15/12)*(1+$C$2) -> 982.8 | W15: =($D15/12)*(1+$C$2) -> 982.8 | X15: =($D15/12)*(1+$C$2) -> 982.8 | Y15: =($D15/12)*(1+$C$2) -> 982.8 | Z15: =($D15/12)*(1+$C$2) -> 982.8 | ... AD15: =($D15/12)*(1+$C$2) -> 982.8 | AE15: =($D15/12)*(1+$C$2+$C$2) -> 1029.6 | AF15: =($D15/12)*(1+$C$2+$C$2) -> 1029.6 | AG15: =($D15/12)*(1+$C$2+$C$2) -> 1029.6 | AH15: =($D15/12)*(1+$C$2+$C$2) -> 1029.6 | AI15: =($D15/12)*(1+$C$2+$C$2) -> 1029.6 | AJ15: =($D15/12)*(1+$C$2+$C$2) -> 1029.6 | AK15: =($D15/12)*(1+$C$2+$C$2) -> 1029.6 | AL15: =($D15/12)*(1+$C$2+$C$2) -> 1029.6 | ... AP15: =($D15/12)*(1+$C$2+$C$2) -> 1029.6 | AQ15: =($D15/12)*(1+$C$2+$C$2+$C$2) -> 1076.4 | AR15: =($D15/12)*(1+$C$2+$C$2+$C$2) -> 1076.4 | AS15: =($D15/12)*(1+$C$2+$C$2+$C$2) -> 1076.4 | AT15: =($D15/12)*(1+$C$2+$C$2+$C$2) -> 1076.4 | AU15: =($D15/12)*(1+$C$2+$C$2+$C$2) -> 1076.4 | AV15: =($D15/12)*(1+$C$2+$C$2+$C$2) -> 1076.4 | AW15: =($D15/12)*(1+$C$2+$C$2+$C$2) -> 1076.4 | AX15: =($D15/12)*(1+$C$2+$C$2+$C$2) -> 1076.4 | ... BN15: =($D15/12)*(1+$C$2+$C$2+$C$2) -> 1076.4
A16: 7 | B16: Phamacist | C16: TBH | D16: 120000 | AA16: =($D16/12)*(1+$C$2+$C$2) -> 11000 | AB16: =($D16/12)*(1+$C$2+$C$2) -> 11000 | AC16: =($D16/12)*(1+$C$2+$C$2) -> 11000 | AD16: =($D16/12)*(1+$C$2+$C$2) -> 11000 | AE16: =($D16/12)*(1+$C$2+$C$2) -> 11000 | AF16: =($D16/12)*(1+$C$2+$C$2) -> 11000 | AG16: =($D16/12)*(1+$C$2+$C$2) -> 11000 | AH16: =($D16/12)*(1+$C$2+$C$2) -> 11000 | ... AP16: =($D16/12)*(1+$C$2+$C$2) -> 11000 | AQ16: =($D16/12)*(1+$C$2+$C$2+$C$2) -> 11500 | AR16: =($D16/12)*(1+$C$2+$C$2+$C$2) -> 11500 | AS16: =($D16/12)*(1+$C$2+$C$2+$C$2) -> 11500 | AT16: =($D16/12)*(1+$C$2+$C$2+$C$2) -> 11500 | AU16: =($D16/12)*(1+$C$2+$C$2+$C$2) -> 11500 | AV16: =($D16/12)*(1+$C$2+$C$2+$C$2) -> 11500 | AW16: =($D16/12)*(1+$C$2+$C$2+$C$2) -> 11500 | AX16: =($D16/12)*(1+$C$2+$C$2+$C$2) -> 11500 | ... BN16: =($D16/12)*(1+$C$2+$C$2+$C$2) -> 11500
A17: 8 | B17: Phamacist | C17: TBH | D17: 55000 | W17: =($D17/12)*(1+$C$2+$C$2) -> 5041.6667 | X17: =($D17/12)*(1+$C$2+$C$2) -> 5041.6667 | Y17: =($D17/12)*(1+$C$2+$C$2) -> 5041.6667 | Z17: =($D17/12)*(1+$C$2+$C$2) -> 5041.6667 | AA17: =($D17/12)*(1+$C$2+$C$2) -> 5041.6667 | AB17: =($D17/12)*(1+$C$2+$C$2) -> 5041.6667 | AC17: =($D17/12)*(1+$C$2+$C$2) -> 5041.6667 | AD17: =($D17/12)*(1+$C$2+$C$2) -> 5041.6667 | ... AP17: =($D17/12)*(1+$C$2+$C$2) -> 5041.6667 | AQ17: =($D17/12)*(1+$C$2+$C$2+$C$2) -> 5270.8333 | AR17: =($D17/12)*(1+$C$2+$C$2+$C$2) -> 5270.8333 | AS17: =($D17/12)*(1+$C$2+$C$2+$C$2) -> 5270.8333 | AT17: =($D17/12)*(1+$C$2+$C$2+$C$2) -> 5270.8333 | AU17: =($D17/12)*(1+$C$2+$C$2+$C$2) -> 5270.8333 | AV17: =($D17/12)*(1+$C$2+$C$2+$C$2) -> 5270.8333 | AW17: =($D17/12)*(1+$C$2+$C$2+$C$2) -> 5270.8333 | AX17: =($D17/12)*(1+$C$2+$C$2+$C$2) -> 5270.8333 | ... BN17: =($D17/12)*(1+$C$2+$C$2+$C$2) -> 5270.8333
